Workbook
Name sspdtipos_TipoGradoRedondeo: Lists!$B$3:$B$6
Name sspdtipos_TipoSiNo: Lists!$D$3:$D$4
Name sspdtipos_TipoPeriodoDeReexpresion: Lists!$F$3:$F$5
Name sspdtipos_TipoDivisa: Lists!$H$3:$H$5
Name sspdtipos_TipoIdentificacionResponsablesInformacion: Lists!$J$3:$J$5
Name sspdtipos_TipoDeDictamenDeAuditoria: Lists!$L$3:$L$10
Name sspdtipos_TipoClasificacionEmpresarialSegunResolucionCRA906Del2019: Lists!$N$3:$N$6
Name sspdtipos_TipoPeriodoFaseDeProgresividad: Lists!$P$3:$P$15

Sheet Indice
B2: Tabla de contenidos
B3: [110000] Información general sobre estados financieros
B4: [210000] Estado de situación financiera (corriente/no corriente) - Individual
B5: [310000] Estado de Resultados Integral, resultado del periodo, por función del gasto - Individual
B6: [420000] Estado de Resultados Integral, componentes ORI presentados antes de impuestos - Individual
B7: [510000] Estado de flujos de efectivo, método directo - Individual
B8: [610000] Estado de cambios en el patrimonio - Individual
B9: [800100] Notas - Subclasificaciones de activos, pasivos y patrimonios
B10: [800500] Notas - Lista de Notas
B11: [800600] Notas - Lista de políticas contables
B12: [810000] Notas - Información de la entidad y declaración de cumplimiento con el marco normativo
B13: [811001] Notas - Cambios por políticas contables, estimaciones contables o corrección de errores
... B66: [900110] FC60 - Porcentaje de provisión de la tarifa de aprovechamiento

Sheet Hoja1
B2: Indice
B3: Archivo: | C3: I:\Proyectos2025\proyecto_niif\_backup_legacy\Grupo1_Individual_Directo_ID20037_2024-12-31.xbrl
B4: Empresa: | C4: 20037
B5: Vista: | C5: [110000] Información general sobre estados financieros
B6: Eje X: | C6: N/A
B7: Eje Y: | C7: N/A
B8: Eje Z: | C8: N/A
E10: Periodo Actual
B11: Información general [resumen]
C12: Información a revelar sobre información general sobre los estados financieros [bloque de texto]
D13: Nombre de la entidad que informa u otras formas de identificación
D14: Identificación de la Empresa (ID RUPS)
D15: NIT
D16: Información a revelar sobre la naturaleza del negocio
D17: Fecha de inicio de operaciones (o fecha de constitución si no ha iniciado la prestación de servicios)
D18: Fecha de cierre del periodo sobre el que se informa
D19: Grado de redondeo utilizado en los estados financieros
C20: Detalle sobre este Informe
D21: ¿Estos estados financieros presentan información reexpresada?
D22: Periodo para el cual se presenta información reexpresada

Sheet Lists
B3: 1 - Pesos | D3: 1. Si | F3: 1. Reexpresión del patrimonio al inicio del periodo actual (Del patrimonio del periodo anterior) | H3: COP - Colombian peso | J3: 01 - CÉDULA DE CIUDADANÍA | L3: NAGAS - 1. Limpio | N3: 1 - Grandes Prestadores | P3: 2018
B4: 2 - Miles de pesos | D4: 2. No | F4: 2. Reexpresión del patrimonio al inicio del periodo anterior (Del patrimonio de dos periodos atrás) | H4: EUR - Euro | J4: 02 - CÉDULA DE EXTRANJERÍA | L4: NAGAS - 2. Con salvedad | N4: 2 - Pequeños Prestadores | P4: 2019
B5: 3 - Millones de pesos | F5: 3. Reexpresión del patrimonio al inicio de los periodos actual y anterior (Del patrimonio del periodo anterior y de dos periodos atrás) | H5: USD - US Dollar | J5: 03 - PASAPORTE | L5: NAGAS - 3. Negativo | N5: 3 - Prestadores Rurales | P5: 2020
B6: 4 - Pesos redondeada a miles | L6: NAGAS - 4. Abstención de opinión | N6: 4 - Esquema Diferencial | P6: 2021
L7: NIAS - 1. No modificada | P7: 2022
L8: NIAS - 2. Modificada; opinión con salvedades | P8: 2023
L9: NIAS - 3. Modificada; opinión desfavorable o adversa | P9: 2024
L10: NIAS - 4. Modificada; denegación o abstención de opinión | P10: 2025
P11: 2026
P12: 2027
P13: 2028
P14: 2029
P15: 2030

Sheet Hoja2
B2: Indice
B3: Archivo: | C3: I:\Proyectos2025\proyecto_niif\_backup_legacy\Grupo1_Individual_Directo_ID20037_2024-12-31.xbrl
B4: Empresa: | C4: 20037
B5: Vista: | C5: [210000] Estado de situación financiera (corriente/no corriente) - Individual
B6: Eje X: | C6: N/A
B7: Eje Y: | C7: N/A
B9: Eje Z: | C9: Periodo Actual
I10: Total [miembro]
I11: Acueducto [miembro] | J11: Alcantarillado [miembro] | K11: Aseo [miembro] | L11: Energía Eléctrica [miembro] | M11: Gas combustible por redes [miembro] | N11: Gas Licuado de Petróleo [miembro] | O11: Otras actividades no vigiladas por la SSPD [miembro] | P11: Operador del sistema y Administrador del mercado de energia (XM) [miembro]
B12: Estado de Situación Financiera por Servicio [partidas]
C13: Activos [resumen]
D14: Activos corrientes [resumen]
E15: Efectivo y equivalentes al efectivo | Q15: =Hoja7!F21+Hoja7!F26+Hoja7!F27
F16: Efectivo y equivalentes al efectivo de uso restringido corriente
E17: Cuentas comerciales por cobrar y otras cuentas por cobrar corrientes [Resumen]
F18: Cuentas comerciales por cobrar por prestación de servicios públicos corrientes [Resumen]
G19: Cuentas comerciales por cobrar corrientes por prestación de servicios públicos corrientes (Sin incluir subsidios ni actividades de aprovechamiento)
G20: Cuentas comerciales por cobrar por subsidios corrientes
H21: Cuentas comerciales por cobrar corrientes del servicio público al Ministerio de Minas por concepto de subsidios
G22: Cuentas comerciales por cobrar por actividad de aprovechamiento corrientes
G23: Total cuentas comerciales por cobrar por prestación de servicios públicos corrientes | I23: =I19+I20 | J23: =J19+J20 | K23: =K19+K20+K22 | L23: =L19+L20 | M23: =M19+M20 | N23: =N19+N20 | O23: =O19 | Q23: =Q19+Q20+Q22
F24: Cuentas comerciales por cobrar por venta de bienes corrientes
F25: Cuentas por cobrar partes relacionadas y asociadas corrientes
F26: Otras cuentas por cobrar corrientes
F27: Total cuentas comerciales por cobrar y otras cuentas por cobrar corrientes | I27: =SUM(I23:I26) | J27: =SUM(J23:J26) | K27: =SUM(K23:K26) | L27: =SUM(L23:L26) | M27: =SUM(M23:M26) | N27: =SUM(N23:N26) | O27: =SUM(O23:O26) | P27: =SUM(P24:P26) | Q27: =SUM(Q23:Q26)
E28: Inventarios corrientes
E29: Activos por impuestos corrientes
E30: Activos biológicos corrientes
E31: Otros activos financieros corrientes
E32: Otros activos no financieros corrientes
E33: Activos corrientes distintos al efectivo pignorados como garantía colateral para las que el receptor de transferencias tiene derecho por contrato o costumbre a vender o pignorar de nuevo dicha garantía colateral
E34: Total activos corrientes distintos de los activos no corrientes o grupo de activos para su disposición clasificados como mantenidos para la venta o como mantenidos para distribuir a los propietarios | I34: =I15+SUM(I27:I33) | J34: =J15+SUM(J27:J33) | K34: =K15+SUM(K27:K33) | L34: =L15+SUM(L27:L33) | M34: =M15+SUM(M27:M33) | N34: =N15+SUM(N27:N33) | O34: =O15+SUM(O27:O33) | P34: =P15+SUM(P27:P33) | Q34: =Q15+SUM(Q27:Q33)
E35: Activos no corrientes o grupos de activos para su disposición clasificados como mantenidos para la venta
E36: Activos no corrientes o grupos de activos para su disposición clasificados como mantenidos para distribuir a los propietarios
E37: Total de activos corrientes | I37: =SUM(I34:I36) | J37: =SUM(J34:J36) | K37: =SUM(K34:K36) | L37: =SUM(L34:L36) | M37: =SUM(M34:M36) | N37: =SUM(N34:N36) | O37: =SUM(O34:O36) | P37: =SUM(P34:P36) | Q37: =SUM(Q34:Q36)
D38: Activos no corrientes [resumen]
E39: Efectivo y equivalentes al efectivo de uso restringido
E40: Propiedades, planta y equipo
E41: Propiedad de inversión
E42: Plusvalía
E43: Activos intangibles distintos de la plusvalía
E44: Inversiones contabilizadas utilizando el método de la participación
E45: Inversiones en asociadas presentadas en estados financieros separados
E46: Inversiones en subsidiarias presentadas en estados financieros separados
E47: Inversiones en negocios conjuntos presentadas en estados financieros separados
E48: Activos biológicos no corrientes
E49: Cuentas comerciales por cobrar y otras cuentas por cobrar no corrientes [Resumen]
F50: Cuentas comerciales por cobrar por prestación de servicios públicos no corrientes [Resumen]
G51: Cuentas comerciales por cobrar no corrientes por prestación de servicios públicos corrientes (Sin incluir subsidios ni actividades de aprovechamiento)
G52: Cuentas comerciales por cobrar por subsidios no corrientes
H53: Cuentas comerciales por cobrar no corrientes del servicio público al Ministerio de Minas por concepto de subsidios
G54: Cuentas comerciales por cobrar por actividad de aprovechamiento no corrientes
G55: Total cuentas comerciales por cobrar por prestación de servicios públicos no corrientes | I55: =I51+I52 | J55: =J51+J52 | K55: =K51+K52+K54 | L55: =L51+L52 | M55: =M51+M52 | N55: =N51+N52 | O55: =O51 | Q55: =Q51+Q52+Q54
F56: Cuentas comerciales por cobrar por venta de bienes no corrientes
F57: Cuentas por cobrar partes relacionadas y asociadas no corrientes
F58: Otras cuentas comerciales por cobrar no corrientes
F59: Total cuentas comerciales por cobrar y otras cuentas por cobrar no corrientes | I59: =SUM(I55:I58) | J59: =SUM(J55:J58) | K59: =SUM(K55:K58) | L59: =SUM(L55:L58) | M59: =SUM(M55:M58) | N59: =SUM(N55:N58) | O59: =SUM(O55:O58) | P59: =SUM(P56:P58) | Q59: =SUM(Q55:Q58)
E60: Inventarios no corrientes
E61: Activos por impuestos diferidos
E62: Activos por impuestos corrientes, no corriente
E63: Otros activos financieros no corrientes
E64: Otros activos no financieros no corrientes
E65: Activos no corrientes distintos al efectivo pignorados como garantía colateral para las que el receptor de transferencias tiene derecho por contrato o costumbre a vender o pignorar de nuevo la garantía colateral
E66: Total de activos no corrientes | I66: =SUM(I39:I48)+SUM(I59:I65) | J66: =SUM(J39:J48)+SUM(J59:J65) | K66: =SUM(K39:K48)+SUM(K59:K65) | L66: =SUM(L39:L48)+SUM(L59:L65) | M66: =SUM(M39:M48)+SUM(M59:M65) | N66: =SUM(N39:N48)+SUM(N59:N65) | O66: =SUM(O39:O48)+SUM(O59:O65) | P66: =SUM(P39:P48)+SUM(P59:P65) | Q66: =SUM(Q39:Q48)+SUM(Q59:Q65)
D67: Total de activos | I67: =I37+I66 | J67: =J37+J66 | K67: =K37+K66 | L67: =L37+L66 | M67: =M37+M66 | N67: =N37+N66 | O67: =O37+O66 | P67: =P37+P66 | Q67: =Q37+Q66
C68: Patrimonio y pasivos [resumen]
D69: Pasivos [resumen]
E70: Pasivos corrientes [resumen]
F71: Provisiones corrientes [resumen]
G72: Provisiones corrientes por beneficios a los empleados
G73: Otras provisiones corrientes
G74: Total provisiones corrientes | I74: =I72+I73 | J74: =J72+J73 | K74: =K72+K73 | L74: =L72+L73 | M74: =M72+M73 | N74: =N72+N73 | O74: =O72+O73 | P74: =P72+P73 | Q74: =Q72+Q73
F75: Cuentas por pagar comerciales y otras cuentas por pagar corrientes [Resumen]
G76: Cuentas comerciales por pagar por adquisición de servicios corrientes
G77: Cuentas comerciales por pagar por adquisición de bienes corrientes
G78: Cuentas por pagar partes relacionadas y asociadas corrientes
G79: Otras cuentas comerciales por pagar corrientes
G80: Total cuentas comerciales por pagar y otras cuentas por pagar corrientes | I80: =SUM(I76:I79) | J80: =SUM(J76:J79) | K80: =SUM(K76:K79) | L80: =SUM(L76:L79) | M80: =SUM(M76:M79) | N80: =SUM(N76:N79) | O80: =SUM(O76:O79) | P80: =SUM(P76:P79) | Q80: =SUM(Q76:Q79)
F81: Pasivos por impuestos corrientes, corriente
F82: Obligaciones financieras corrientes
F83: Otros pasivos financieros corrientes
F84: Otros pasivos no financieros corrientes
F85: Total de pasivos corrientes distintos de los pasivos incluidos en grupos de activos para su disposición clasificados como mantenidos para la venta | I85: =I74+SUM(I80:I84) | J85: =J74+SUM(J80:J84) | K85: =K74+SUM(K80:K84) | L85: =L74+SUM(L80:L84) | M85: =M74+SUM(M80:M84) | N85: =N74+SUM(N80:N84) | O85: =O74+SUM(O80:O84) | P85: =P74+SUM(P80:P84) | Q85: =Q74+SUM(Q80:Q84)
F86: Pasivos incluidos en grupos de activos para su disposición clasificados como mantenidos para la venta
F87: Total pasivos corrientes | I87: =I85+I86 | J87: =J85+J86 | K87: =K85+K86 | L87: =L85+L86 | M87: =M85+M86 | N87: =N85+N86 | O87: =O85+O86 | P87: =P85+P86 | Q87: =Q85+Q86
E88: Pasivos no corrientes [resumen]
F89: Provisiones no corrientes [resumen]
G90: Provisiones no corrientes por beneficios a los empleados
G91: Otras provisiones no corrientes
G92: Total provisiones no corrientes | I92: =I90+I91 | J92: =J90+J91 | K92: =K90+K91 | L92: =L90+L91 | M92: =M90+M91 | N92: =N90+N91 | O92: =O90+O91 | P92: =P90+P91 | Q92: =Q90+Q91
F93: Cuentas por pagar comerciales y otras cuentas por pagar no corrientes [Resumen]
G94: Cuentas comerciales por pagar por adquisición de servicios no corrientes
G95: Cuentas comerciales por pagar por adquisición de bienes no corrientes
G96: Cuentas por pagar partes relacionadas y asociadas no corrientes
G97: Otras cuentas comerciales por pagar no corrientes
G98: Total cuentas comerciales por pagar y otras cuentas por pagar no corrientes | I98: =SUM(I94:I97) | J98: =SUM(J94:J97) | K98: =SUM(K94:K97) | L98: =SUM(L94:L97) | M98: =SUM(M94:M97) | N98: =SUM(N94:N97) | O98: =SUM(O94:O97) | P98: =SUM(P94:P97) | Q98: =SUM(Q94:Q97)
F99: Pasivo por impuestos diferidos
F100: Pasivos por impuestos corrientes, no corriente
F101: Obligaciones financieras no corrientes
F102: Otros pasivos financieros no corrientes
...

Sheet Hoja3
B2: Indice
B3: Archivo: | C3: I:\Proyectos2025\proyecto_niif\_backup_legacy\Grupo1_Individual_Directo_ID20037_2024-12-31.xbrl
B4: Empresa: | C4: 20037
B5: Vista: | C5: [310000] Estado de Resultados Integral, resultado del periodo, por función del gasto - Individual
B6: Eje X: | C6: N/A
B7: Eje Y: | C7: N/A
B9: Eje Z: | C9: Periodo Actual
F10: Total [miembro]
F11: Acueducto [miembro] | G11: Alcantarillado [miembro] | H11: Aseo [miembro] | I11: Energía Eléctrica [miembro] | J11: Gas combustible por redes [miembro] | K11: Gas Licuado de Petróleo [miembro] | L11: Otras actividades no vigiladas por la SSPD [miembro] | M11: Operador del sistema y Administrador del mercado de energia (XM) [miembro]
B12: Estado de Resultados Integral por Servicio [partidas]
C13: Ganancia (pérdida) [resumen]
D14: Ingresos de actividades ordinarias
D15: Costo de ventas
D16: Ganancia bruta | F16: =-F15+F14 | G16: =-G15+G14 | H16: =-H15+H14 | I16: =-I15+I14 | J16: =-J15+J14 | K16: =-K15+K14 | L16: =-L15+L14 | M16: =-M15+M14 | N16: =-N15+N14
D17: Otros ingresos
D18: Gastos de administración
D19: Otros gastos
D20: Otras ganancias (pérdidas)
D21: Ganancia (pérdida) por actividades de operación | F21: =F16+F17-F18-F19+F20 | G21: =G16+G17-G18-G19+G20 | H21: =H16+H17-H18-H19+H20 | I21: =I16+I17-I18-I19+I20 | J21: =J16+J17-J18-J19+J20 | K21: =K16+K17-K18-K19+K20 | L21: =L16+L17-L18-L19+L20 | M21: =M16+M17-M18-M19+M20 | N21: =N16+N17-N18-N19+N20
D22: Diferencia entre el importe en libros de dividendos pagaderos e importe en libros de activos distribuidos distintos al efectivo
D23: Ganancias (pérdidas) derivadas de la posición monetaria neta
D24: Ganancias (pérdidas) que surgen de la baja en cuentas de activos financieros medidos al costo amortizado
D25: Ingresos financieros
D26: Costos financieros
D27: Deterioro de valor de ganancias y reversión de pérdidas por deterioro de valor (pérdidas por deterioro de valor) determinado de acuerdo con la NIIF 9
D28: Participación en las ganancias (pérdidas) de asociadas y negocios conjuntos que se contabilicen utilizando el método de la participación
D29: Otros ingresos (gastos) procedentes de subsidiarias, entidades controladas de forma conjunta y asociadas
D30: Ganancias (pérdidas) que surgen de diferencias entre importes en libros anteriores y el valor razonable de activos financieros reclasificados como medidos al valor razonable
D31: Ganancia (pérdida) acumulada anteriormente reconocida en otro resultado integral que surge de la reclasificación de activos financieros de la categoría de medición de valor razonable con cambios en otro resultado integral a la de valor razonable con cambios en resultados
D32: Ganancias (pérdidas) de cobertura por cobertura de un grupo de partidas con posiciones de riesgo compensadoras
D33: Ganancia (pérdida), antes de impuestos | F33: =SUM(F21:F25)-F26-F27+SUM(F28:F32) | G33: =SUM(G21:G25)-G26-G27+SUM(G28:G32) | H33: =SUM(H21:H25)-H26-H27+SUM(H28:H32) | I33: =SUM(I21:I25)-I26-I27+SUM(I28:I32) | J33: =SUM(J21:J25)-J26-J27+SUM(J28:J32) | K33: =SUM(K21:K25)-K26-K27+SUM(K28:K32) | L33: =SUM(L21:L25)-L26-L27+SUM(L28:L32) | M33: =SUM(M21:M25)-M26-M27+SUM(M28:M32) | N33: =SUM(N21:N25)-N26-N27+SUM(N28:N32)
D34: Gasto (ingreso) por impuesto a las ganancias corriente
D35: Gasto (ingreso) por impuesto a las ganancias diferido
D36: Ganancia (pérdida) procedente de operaciones continuadas | F36: =F33-F34-F35 | G36: =G33-G34-G35 | H36: =H33-H34-H35 | I36: =I33-I34-I35 | J36: =J33-J34-J35 | K36: =K33-K34-K35 | L36: =L33-L34-L35 | M36: =M33-M34-M35 | N36: =N33-N34-N35
D37: Ganancia (pérdida) procedente de operaciones discontinuadas
D38: Ganancia (pérdida) | F38: =F36+F37 | G38: =G36+G37 | H38: =H36+H37 | I38: =I36+I37 | J38: =J36+J37 | K38: =K36+K37 | L38: =L36+L37 | M38: =M36+M37 | N38: =N36+N37
C39: Ganancias por acción [resumen]
D40: Ganancia por acción básica [resumen]
E41: Ganancia (pérdida) por acción básica en operaciones continuadas
E42: Ganancia (pérdida) por acción básica en operaciones discontinuadas
E43: Total ganancias (pérdidas) básicas por acción | N43: =N41+N42
D44: Ganancias por acción diluidas [resumen]
E45: Ganancias (pérdida) diluida por acción procedente de operaciones continuadas
E46: Ganancias (pérdida) diluida por acción procedentes de operaciones discontinuadas
E47: Total ganancias (pérdidas) por acción diluidas | N47: =N45+N46
B49: Eje Z: | C49: Periodo Anterior
F50: Total [miembro]
F51: Acueducto [miembro] | G51: Alcantarillado [miembro] | H51: Aseo [miembro] | I51: Energía Eléctrica [miembro] | J51: Gas combustible por redes [miembro] | K51: Gas Licuado de Petróleo [miembro] | L51: Otras actividades no vigiladas por la SSPD [miembro] | M51: Operador del sistema y Administrador del mercado de energia (XM) [miembro]
B52: Estado de Resultados Integral por Servicio [partidas]
C53: Ganancia (pérdida) [resumen]
D54: Ingresos de actividades ordinarias
D55: Costo de ventas
D56: Ganancia bruta | F56: =-F55+F54 | G56: =-G55+G54 | H56: =-H55+H54 | I56: =-I55+I54 | J56: =-J55+J54 | K56: =-K55+K54 | L56: =-L55+L54 | M56: =-M55+M54 | N56: =-N55+N54
D57: Otros ingresos
D58: Gastos de administración
D59: Otros gastos
D60: Otras ganancias (pérdidas)
D61: Ganancia (pérdida) por actividades de operación | F61: =F56+F57-F58-F59+F60 | G61: =G56+G57-G58-G59+G60 | H61: =H56+H57-H58-H59+H60 | I61: =I56+I57-I58-I59+I60 | J61: =J56+J57-J58-J59+J60 | K61: =K56+K57-K58-K59+K60 | L61: =L56+L57-L58-L59+L60 | M61: =M56+M57-M58-M59+M60 | N61: =N56+N57-N58-N59+N60
D62: Diferencia entre el importe en libros de dividendos pagaderos e importe en libros de activos distribuidos distintos al efectivo
D63: Ganancias (pérdidas) derivadas de la posición monetaria neta
D64: Ganancias (pérdidas) que surgen de la baja en cuentas de activos financieros medidos al costo amortizado
D65: Ingresos financieros
D66: Costos financieros
D67: Deterioro de valor de ganancias y reversión de pérdidas por deterioro de valor (pérdidas por deterioro de valor) determinado de acuerdo con la NIIF 9
D68: Participación en las ganancias (pérdidas) de asociadas y negocios conjuntos que se contabilicen utilizando el método de la participación
D69: Otros ingresos (gastos) procedentes de subsidiarias, entidades controladas de forma conjunta y asociadas
D70: Ganancias (pérdidas) que surgen de diferencias entre importes en libros anteriores y el valor razonable de activos financieros reclasificados como medidos al valor razonable
D71: Ganancia (pérdida) acumulada anteriormente reconocida en otro resultado integral que surge de la reclasificación de activos financieros de la categoría de medición de valor razonable con cambios en otro resultado integral a la de valor razonable con cambios en resultados
D72: Ganancias (pérdidas) de cobertura por cobertura de un grupo de partidas con posiciones de riesgo compensadoras
D73: Ganancia (pérdida), antes de impuestos | F73: =SUM(F61:F65)-F66-F67+SUM(F68:F72) | G73: =SUM(G61:G65)-G66-G67+SUM(G68:G72) | H73: =SUM(H61:H65)-H66-H67+SUM(H68:H72) | I73: =SUM(I61:I65)-I66-I67+SUM(I68:I72) | J73: =SUM(J61:J65)-J66-J67+SUM(J68:J72) | K73: =SUM(K61:K65)-K66-K67+SUM(K68:K72) | L73: =SUM(L61:L65)-L66-L67+SUM(L68:L72) | M73: =SUM(M61:M65)-M66-M67+SUM(M68:M72) | N73: =SUM(N61:N65)-N66-N67+SUM(N68:N72)
D74: Gasto (ingreso) por impuesto a las ganancias corriente
D75: Gasto (ingreso) por impuesto a las ganancias diferido
D76: Ganancia (pérdida) procedente de operaciones continuadas | F76: =F73-F74-F75 | G76: =G73-G74-G75 | H76: =H73-H74-H75 | I76: =I73-I74-I75 | J76: =J73-J74-J75 | K76: =K73-K74-K75 | L76: =L73-L74-L75 | M76: =M73-M74-M75 | N76: =N73-N74-N75
D77: Ganancia (pérdida) procedente de operaciones discontinuadas
D78: Ganancia (pérdida) | F78: =F76+F77 | G78: =G76+G77 | H78: =H76+H77 | I78: =I76+I77 | J78: =J76+J77 | K78: =K76+K77 | L78: =L76+L77 | M78: =M76+M77 | N78: =N76+N77
C79: Ganancias por acción [resumen]
D80: Ganancia por acción básica [resumen]
E81: Ganancia (pérdida) por acción básica en operaciones continuadas
E82: Ganancia (pérdida) por acción básica en operaciones discontinuadas
E83: Total ganancias (pérdidas) básicas por acción | N83: =N81+N82
D84: Ganancias por acción diluidas [resumen]
E85: Ganancias (pérdida) diluida por acción procedente de operaciones continuadas
E86: Ganancias (pérdida) diluida por acción procedentes de operaciones discontinuadas
E87: Total ganancias (pérdidas) por acción diluidas | N87: =N85+N86

Sheet Hoja4
B2: Indice
B3: Archivo: | C3: I:\Proyectos2025\proyecto_niif\_backup_legacy\Grupo1_Individual_Directo_ID20037_2024-12-31.xbrl
B4: Empresa: | C4: 20037
B5: Vista: | C5: [420000] Estado de Resultados Integral, componentes ORI presentados antes de impuestos - Individual
B6: Eje X: | C6: N/A
B7: Eje Y: | C7: N/A
B8: Eje Z: | C8: N/A
H10: Periodo Actual | I10: Periodo Anterior
B11: Estado del resultado integral [resumen]
C12: Ganancia (pérdida) | H12: =Hoja3!N36+Hoja3!N37 | I12: =Hoja3!N76+Hoja3!N77
C13: Otro resultado integral [resumen]
D14: Componentes de otro resultado integral que no se reclasificarán al resultado del periodo, antes de impuestos [resumen]
E15: Otro resultado integral, antes de impuestos, ganancias (pérdidas) de inversiones en instrumentos de patrimonio
E16: Otro resultado integral, antes de impuestos, ganancias (pérdidas) por nueva evaluación de las propiedades, planta y equipo, activos por derecho de uso y activos intangibles
E17: Otro resultado integral, antes de impuestos, ganancias (pérdidas) por nuevas mediciones de planes de beneficios definidos
E18: Otro resultado integral, antes de impuestos, diferencias de cambio en la conversión, distinto de la conversión de negocios en el extranjero
E19: Otro resultado integral, antes de impuestos, cambio en el valor razonable de pasivos financieros atribuible a cambios en el riesgo crediticio del pasivo
E20: Otro resultado integral, antes de impuestos, ganancias (pérdidas) por instrumentos de cobertura que cubren inversiones en instrumentos de patrimonio
E21: Otro resultado integral, antes de impuestos, ingresos (gastos) financieros por contratos de seguro emitidos excluidos del resultado del periodo que no se reclasificará al resultado del periodo
D22: Participación de otro resultado integral de asociadas y negocios conjuntos contabilizados utilizando el método de la participación que no se reclasificará al resultado del periodo, antes de impuestos
D23: Total otro resultado integral que no se reclasificará al resultado del periodo, antes de impuestos | H23: =SUM(H15:H22) | I23: =SUM(I15:I22)
D24: Componentes de otro resultado integral que se reclasificarán al resultado del periodo, antes de impuestos [resumen]
E25: Diferencias de cambio por conversión [resumen]
F26: Ganancias (pérdidas) por diferencias de cambio en la conversión de negocios en el extranjero, antes de impuestos
F27: Ajustes de reclasificación por diferencias de cambio en la conversión de negocios en el extranjero, antes de impuestos
F28: Otro resultado integral, antes de impuestos, diferencias de cambio en la conversión de negocios en el extranjero | H28: =-H27+H26 | I28: =-I27+I26
E29: Activos financieros disponibles para la venta [resumen]
F30: Ganancias (pérdidas) por nuevas mediciones de activos financieros disponibles para la venta, antes de impuestos
F31: Ajustes de reclasificación, activos financieros disponibles para la venta, antes de impuestos
F32: Otro resultado integral antes de impuestos, activos financieros disponibles para la venta | H32: =H30-H31 | I32: =I30-I31
E33: Coberturas del flujo de efectivo [resumen]
F34: Ganancias (pérdidas) por coberturas de flujos de efectivo, antes de impuestos
F35: Ajustes de reclasificación en coberturas de flujos de efectivo, antes de impuestos
F36: Importes eliminados del patrimonio e incluidos en el importe en libros de activos (pasivos) no financieros que se hayan adquirido o incurrido mediante una transacción prevista altamente probable cubierta, antes de impuestos
F37: Otro resultado integral, antes de impuestos, coberturas del flujo de efectivo | H37: =H34-H35-H36 | I37: =I34-I35-I36
E38: Coberturas de inversiones netas en negocios en el extranjero [resumen]
F39: Ganancias (pérdidas) por coberturas de inversiones netas en negocios en el extranjero, antes de impuestos
F40: Ajustes de reclasificación por coberturas de inversiones netas en negocios en el extranjero, antes de impuestos
F41: Otro resultado integral, antes de impuestos, coberturas de inversiones netas en negocios en el extranjero | H41: =-H40+H39 | I41: =-I40+I39
E42: Costo de la cobertura [resumen]
F43: Cambio en el valor temporal del dinero de opciones [resumen]
G44: Ganancia (pérdida) por cambios en el valor temporal del dinero de opciones, antes de impuestos
G45: Ajustes de reclasificación por cambios en el valor temporal del dinero de opciones, antes de impuestos
G46: Otro resultado integral, antes de impuestos, cambios en el valor del valor temporal del dinero de opciones | H46: =-H45+H44 | I46: =-I45+I44
F47: Cambios en el valor de los elementos a término de contratos a término [resumen]
G48: Ganancia (pérdida) por cambios en el valor de los elementos a término de contratos a término, antes de impuestos
G49: Ajustes de reclasificación por cambios en el valor de los elementos a término de contratos a término, antes de impuestos
G50: Otro resultado integral, antes de impuestos, cambios en el valor de los elementos a término de contratos a término | H50: =H48-H49 | I50: =I48-I49
F51: Cambio en el valor de los diferenciales de tasa cambio de moneda extranjera [resumen]
G52: Ganancia (pérdida) por cambios en el valor de los diferenciales de la tasa de cambio de la moneda extranjera, antes de impuestos
G53: Ajustes de reclasificación por cambios en el valor de los diferenciales de la tasa de cambio de la moneda extranjera, antes de impuestos
G54: Otro resultado integral, antes de impuestos, cambios en el valor de los diferenciales de tasa de cambio de la moneda extranjera | H54: =-H53+H52 | I54: =-I53+I52
E55: Activos financieros medidos al valor razonable con cambios en otro resultado integral [resumen]
F56: Ganancias (pérdidas) por activos financieros medidos al valor razonable con cambios en otro resultado integral, antes de impuestos
F57: Ajustes de reclasificación sobre activos financieros medidos al valor razonable con cambios en otro resultado integral, antes de impuestos
F58: Importes eliminados del patrimonio y ajustados contra el valor razonable de activos financieros en el momento de la reclasificación fuera de la categoría de medición de valor razonable con cambios en otro resultado integral, antes de impuestos
F59: Otro resultado integral, antes de Impuestos, activos financieros medidos al valor razonable con cambios en otro resultado integral | H59: =H56-H57-H58 | I59: =I56-I57-I58
E60: Ingresos (gastos) financieros por contratos de seguro emitidos excluidos del resultado del periodo [resumen]
F61: Ingresos (gastos) financieros por contratos de seguro emitidos excluidos del resultado del periodo que se reclasificarán al resultado del periodo, antes de impuestos
F62: Ajustes de reclasificación sobre los ingresos (gastos) financieros por seguros de contratos de seguro emitidos excluidos del resultado del periodo, antes de impuestos
F63: Otro resultado integral, antes de impuestos, ingresos (gastos) financieros por contratos de seguro emitidos excluidos del resultado del periodo que se reclasificará al resultado del periodo | H63: =H61-H62 | I63: =I61-I62
E64: Ingresos (gastos) financieros por contratos de reaseguro mantenidos excluidos del resultado del periodo [resumen]
F65: Ingresos (gastos) financieros por contratos de reaseguro mantenidos excluidos del resultado del periodo, antes de impuestos
F66: Ajustes de reclasificación sobre los ingresos (gastos) financieros por contratos de reaseguro mantenidos excluidos del resultado del periodo, antes de impuestos
F67: Otro resultado integral, antes de impuestos, ingresos (gastos) financieros por contratos de seguro mantenidos excluidos del resultado del periodo | H67: =H65-H66 | I67: =I65-I66
D68: Participación de otro resultado integral de asociadas y negocios conjuntos contabilizados utilizando el método de la participación que se reclasificará al resultado del periodo, antes de impuestos
D69: Total otro resultado integral que se reclasificará al resultado del periodo, antes de impuestos | H69: =H28+H32+H37+H41+H46+H50+H54+H59+H63+H67+H68 | I69: =I28+I32+I37+I41+I46+I50+I54+I59+I63+I67+I68
D70: Total otro resultado integral, antes de impuestos | H70: =H23+H69 | I70: =I23+I69
D71: Impuestos a las ganancias relativos a componentes de otro resultado integral que no se reclasificará al resultado del periodo [resumen]
E72: Impuesto a las ganancias relacionado con inversiones en instrumentos de patrimonio incluido en otro resultado integral
E73: Impuesto a las ganancias relativo a las variaciones de las superávit de revaluación de propiedades, planta y equipo, de los activos por derecho de uso y de los activos intangibles incluidos en otro resultado integral
E74: Impuesto a las ganancias relacionado con nuevas mediciones de planes de beneficios definidos incluido en otro resultado integral
E75: Impuesto a las ganancias relacionado con diferencias de cambio en conversiones distintas de las procedentes de negocios en el extranjero incluidos en otro resultado integral
E76: Impuesto a las ganancias relacionado con cambios en el valor razonable de pasivos financieros atribuibles a cambios en el riesgo crediticio de pasivos incluido en otro resultado integral
E77: Impuesto a las ganancias relacionado con coberturas de inversiones en instrumentos de patrimonio incluido en otro resultado integral
E78: Impuesto a las ganancias relacionado con ingresos (gastos) financieros por seguros de contratos de seguro emitidos incluido en otro resultado integral que no se reclasificará al resultado del periodo
E79: Impuestos a las ganancias acumulados relativos a componentes de otro resultado integral que no se reclasificarán al resultado del periodo | H79: =SUM(H72:H78) | I79: =SUM(I72:I78)
D80: Impuestos a las ganancias relativos a la participación de otro resultado integral de asociadas y negocios conjuntos contabilizados utilizando el método de la participación que no se reclasificará al resultado del periodo
D81: Impuestos a las ganancias relativos a componentes de otro resultado integral que se reclasificará al resultado del periodo [resumen]
E82: Impuesto a las ganancias relacionado con diferencias de cambio en conversiones de negocios en el extranjero incluido en otro resultado integral
E83: Impuesto a las ganancias relacionado con activos financieros disponibles para la venta incluido en otro resultado integral
E84: Impuesto a las ganancias relacionado con coberturas de flujos de efectivo incluido en otro resultado integral
E85: Impuesto a las ganancias relacionado con coberturas de inversiones netas en negocios en el extranjero incluido en otro resultado integral
E86: Impuesto a las ganancias relacionado con cambios en el valor temporal del dinero de opciones incluidas en otro resultado integral
E87: Impuesto a las ganancias relacionado con cambios en el valor de los elementos a término de contratos a término incluido en otro resultado integral
E88: Impuesto a las ganancias relacionado con cambios en el valor de los diferenciales de tasa de cambio de la moneda extranjera incluido en otro resultado integral
E89: Impuesto a las ganancias relacionado con activos financieros medidos al valor razonable con cambios en otro resultado integral incluido en otro resultado integral
E90: Impuesto a las ganancias relacionado con ingresos (gastos) financieros por seguros de contratos de seguro emitidos incluido en otro resultado integral que se reclasificará al resultado del periodo
E91: Impuesto a las ganancias relacionado con ingresos (gastos) financieros por contratos de reaseguro mantenidos incluido en otro resultado integral
E92: Impuestos a las ganancias acumulados relativos a componentes de otro resultado integral que se reclasificarán al resultado del periodo | H92: =SUM(H82:H91) | I92: =SUM(I82:I91)
D93: Impuestos a las ganancias relativos a la participación de otro resultado integral de asociadas y negocios conjuntos contabilizados utilizando el método de la participación que se reclasificará al resultado del periodo
D94: Total otro resultado integral | H94: =H70-H79-H80-H92-H93 | I94: =I70-I79-I80-I92-I93
C95: Resultado integral total | H95: =H12+H94 | I95: =I12+I94

Sheet Hoja5
B2: Indice
B3: Archivo: | C3: I:\Proyectos2025\proyecto_niif\_backup_legacy\Grupo1_Individual_Directo_ID20037_2024-12-31.xbrl
B4: Empresa: | C4: 20037
B5: Vista: | C5: [510000] Estado de flujos de efectivo, método directo - Individual
B6: Eje X: | C6: N/A
B7: Eje Y: | C7: N/A
B9: Eje Z: | C9: Periodo Actual
F10: Total [miembro]
F11: Acueducto [miembro] | G11: Alcantarillado [miembro] | H11: Aseo [miembro] | I11: Energía Eléctrica [miembro] | J11: Gas combustible por redes [miembro] | K11: Gas Licuado de Petróleo [miembro] | L11: Otras actividades no vigiladas por la SSPD [miembro] | M11: Operador del sistema y Administrador del mercado de energia (XM) [miembro]
B12: Estado de Flujo de Efectivo por Servicio [partidas]
C13: Flujos de efectivo procedentes de (utilizados en) actividades de operación [resumen]
D14: Clases de cobros por actividades de operación [resumen]
E15: Cobros procedentes de las ventas de bienes y prestación de servicios
E16: Cobros procedentes de regalías, cuotas, comisiones y otros ingresos de actividades ordinarias
E17: Cobros derivados de contratos mantenidos para intermediación o para negociar con ellos
E18: Cobros procedentes de primas y prestaciones, anualidades y otros beneficios de pólizas suscritas
E19: Cobros por rentas y ventas posteriores de activos mantenidos para arrendar a terceros y posteriormente mantenidos para la venta
E20: Otros cobros por actividades de operación
D21: Clases de pagos en efectivo procedentes de actividades de operación [resumen]
E22: Pagos a proveedores por el suministro de bienes y servicios
E23: Pagos procedentes de contratos mantenidos para intermediación o para negociar
E24: Pagos a y por cuenta de los empleados
E25: Pagos por primas y prestaciones, anualidades y otras obligaciones derivadas de las pólizas suscritas
E26: Pagos por producir o adquirir activos mantenidos para arrendar a terceros y posteriormente mantenidos para la venta
E27: Otros pagos por actividades de operación
D28: Flujos de efectivo netos procedentes (utilizados en) operaciones | F28: =SUM(F15:F20)-SUM(F22:F27) | G28: =SUM(G15:G20)-SUM(G22:G27) | H28: =SUM(H15:H20)-SUM(H22:H27) | I28: =SUM(I15:I20)-SUM(I22:I27) | J28: =SUM(J15:J20)-SUM(J22:J27) | K28: =SUM(K15:K20)-SUM(K22:K27) | L28: =SUM(L15:L20)-SUM(L22:L27) | M28: =SUM(M15:M20)-SUM(M22:M27) | N28: =SUM(N15:N20)-SUM(N22:N27)
D29: Dividendos pagados
D30: Dividendos recibidos
D31: Intereses pagados
D32: Intereses recibidos
D33: Impuestos a las ganancias reembolsados (pagados)
D34: Otras entradas (salidas) de efectivo
D35: Flujos de efectivo netos procedentes de (utilizados en) actividades de operación | F35: =F34+F30-F29+F32-F31-F33+F28 | G35: =G34+G30-G29+G32-G31-G33+G28 | H35: =H34+H30-H29+H32-H31-H33+H28 | I35: =I34+I30-I29+I32-I31-I33+I28 | J35: =J34+J30-J29+J32-J31-J33+J28 | K35: =K34+K30-K29+K32-K31-K33+K28 | L35: =L34+L30-L29+L32-L31-L33+L28 | M35: =M34+M30-M29+M32-M31-M33+M28 | N35: =N34+N30-N29+N32-N31-N33+N28
C36: Flujos de efectivo procedentes de (utilizados en) actividades de inversión [resumen]
D37: Flujos de efectivo procedentes de la pérdida de control de subsidiarias u otros negocios
D38: Flujos de efectivo utilizados para obtener el control de subsidiarias u otros negocios
D39: Otros cobros por la venta de patrimonio o instrumentos de deuda de otras entidades
D40: Otros pagos para adquirir patrimonio o instrumentos de deuda de otras entidades
D41: Otros cobros por la venta de participaciones en negocios conjuntos
D42: Otros pagos para adquirir participaciones en negocios conjuntos
D43: Importes procedentes de la venta de propiedades, planta y equipo
D44: Compras de propiedades, planta y equipo
D45: Importes procedentes de ventas de activos intangibles
D46: Compras de activos intangibles
D47: Recursos por ventas de otros activos a largo plazo
D48: Compras de otros activos a largo plazo
... D58: Otras entradas (salidas) de efectivo
D59: Flujos de efectivo netos procedentes de (utilizados en) actividades de inversión | F59: =F37-F38+F39-F40+F41-F42+F43-F44+F45-F46+F47-F48+F49-F50+F51-F52+F53+F54-F55+F56-F57+F58 | G59: =G37-G38+G39-G40+G41-G42+G43-G44+G45-G46+G47-G48+G49-G50+G51-G52+G53+G54-G55+G56-G57+G58 | H59: =H37-H38+H39-H40+H41-H42+H43-H44+H45-H46+H47-H48+H49-H50+H51-H52+H53+H54-H55+H56-H57+H58 | I59: =I37-I38+I39-I40+I41-I42+I43-I44+I45-I46+I47-I48+I49-I50+I51-I52+I53+I54-I55+I56-I57+I58 | J59: =J37-J38+J39-J40+J41-J42+J43-J44+J45-J46+J47-J48+J49-J50+J51-J52+J53+J54-J55+J56-J57+J58 | K59: =K37-K38+K39-K40+K41-K42+K43-K44+K45-K46+K47-K48+K49-K50+K51-K52+K53+K54-K55+K56-K57+K58 | L59: =L37-L38+L39-L40+L41-L42+L43-L44+L45-L46+L47-L48+L49-L50+L51-L52+L53+L54-L55+L56-L57+L58 | M59: =M37-M38+M39-M40+M41-M42+M43-M44+M45-M46+M47-M48+M49-M50+M51-M52+M53+M54-M55+M56-M57+M58 | N59: =N37-N38+N39-N40+N41-N42+N43-N44+N45-N46+N47-N48+N49-N50+N51-N52+N53+N54-N55+N56-N57+N58
C60: Flujos de efectivo procedentes de (utilizados en) actividades de financiación [resumen]
D61: Recursos por cambios en las participaciones en la propiedad en subsidiarias que no dan lugar a la pérdida de control
D62: Pagos por cambios en las participaciones en la propiedad en subsidiarias que no dan lugar a la pérdida de control
D63: Importes procedentes de la emisión de acciones
D64: Importes procedentes de la emisión de otros instrumentos de patrimonio
D65: Pagos por adquirir o rescatar las acciones de la entidad
D66: Pagos por otras participaciones en el patrimonio
D67: Importes procedentes de préstamos
D68: Reembolsos de préstamos
D69: Pagos de pasivos por arrendamiento
D70: Importes procedentes de subvenciones del gobierno
D71: Dividendos pagados
D72: Intereses pagados
... D74: Otras entradas (salidas) de efectivo
D75: Flujos de efectivo netos procedentes de (utilizados en) actividades de financiación | F75: =F61-F62+F63+F64-F65-F66+F67-F68-F69+F70-SUM(F71:F73)+F74 | G75: =G61-G62+G63+G64-G65-G66+G67-G68-G69+G70-SUM(G71:G73)+G74 | H75: =H61-H62+H63+H64-H65-H66+H67-H68-H69+H70-SUM(H71:H73)+H74 | I75: =I61-I62+I63+I64-I65-I66+I67-I68-I69+I70-SUM(I71:I73)+I74 | J75: =J61-J62+J63+J64-J65-J66+J67-J68-J69+J70-SUM(J71:J73)+J74 | K75: =K61-K62+K63+K64-K65-K66+K67-K68-K69+K70-SUM(K71:K73)+K74 | L75: =L61-L62+L63+L64-L65-L66+L67-L68-L69+L70-SUM(L71:L73)+L74 | M75: =M61-M62+M63+M64-M65-M66+M67-M68-M69+M70-SUM(M71:M73)+M74 | N75: =N61-N62+N63+N64-N65-N66+N67-N68-N69+N70-SUM(N71:N73)+N74
C76: Incremento (disminución) neto de efectivo y equivalentes al efectivo, antes del efecto de los cambios en la tasa de cambio | F76: =F35+F75+F59 | G76: =G35+G75+G59 | H76: =H35+H75+H59 | I76: =I35+I75+I59 | J76: =J35+J75+J59 | K76: =K35+K75+K59 | L76: =L35+L75+L59 | M76: =M35+M75+M59 | N76: =N35+N75+N59
C77: Efectos de la variación en la tasa de cambio sobre el efectivo y equivalentes al efectivo [resumen]
D78: Efectos de la variación en la tasa de cambio sobre el efectivo y equivalentes al efectivo
C79: Incremento (disminución) neto del efectivo y equivalentes de efectivo después del efecto de los cambios en la tasa de cambio | F79: =F76+F78 | G79: =G76+G78 | H79: =H76+H78 | I79: =I76+I78 | J79: =J76+J78 | K79: =K76+K78 | L79: =L76+L78 | M79: =M76+M78 | N79: =N76+N78
C80: Efectivo y equivalentes al efectivo al principio del periodo | N80: =Hoja2!Q126
C81: Efectivo y equivalentes al efectivo al final del periodo | N81: =Hoja7!F21+Hoja7!F26+Hoja7!F27
B83: Eje Z: | C83: Periodo Anterior
F84: Total [miembro]
F85: Acueducto [miembro] | G85: Alcantarillado [miembro] | H85: Aseo [miembro] | I85: Energía Eléctrica [miembro] | J85: Gas combustible por redes [miembro] | K85: Gas Licuado de Petróleo [miembro] | L85: Otras actividades no vigiladas por la SSPD [miembro] | M85: Operador del sistema y Administrador del mercado de energia (XM) [miembro]
B86: Estado de Flujo de Efectivo por Servicio [partidas]
C87: Flujos de efectivo procedentes de (utilizados en) actividades de operación [resumen]
D88: Clases de cobros por actividades de operación [resumen]
E89: Cobros procedentes de las ventas de bienes y prestación de servicios
E90: Cobros procedentes de regalías, cuotas, comisiones y otros ingresos de actividades ordinarias
E91: Cobros derivados de contratos mantenidos para intermediación o para negociar con ellos
E92: Cobros procedentes de primas y prestaciones, anualidades y otros beneficios de pólizas suscritas
E93: Cobros por rentas y ventas posteriores de activos mantenidos para arrendar a terceros y posteriormente mantenidos para la venta
E94: Otros cobros por actividades de operación
D95: Clases de pagos en efectivo procedentes de actividades de operación [resumen]
E96: Pagos a proveedores por el suministro de bienes y servicios
E97: Pagos procedentes de contratos mantenidos para intermediación o para negociar
E98: Pagos a y por cuenta de los empleados
E99: Pagos por primas y prestaciones, anualidades y otras obligaciones derivadas de las pólizas suscritas
E100: Pagos por producir o adquirir activos mantenidos para arrendar a terceros y posteriormente mantenidos para la venta
E101: Otros pagos por actividades de operación
D102: Flujos de efectivo netos procedentes (utilizados en) operaciones | F102: =SUM(F89:F94)-SUM(F96:F101) | G102: =SUM(G89:G94)-SUM(G96:G101) | H102: =SUM(H89:H94)-SUM(H96:H101) | I102: =SUM(I89:I94)-SUM(I96:I101) | J102: =SUM(J89:J94)-SUM(J96:J101) | K102: =SUM(K89:K94)-SUM(K96:K101) | L102: =SUM(L89:L94)-SUM(L96:L101) | M102: =SUM(M89:M94)-SUM(M96:M101) | N102: =SUM(N89:N94)-SUM(N96:N101)
D103: Dividendos pagados
D104: Dividendos recibidos
D105: Intereses pagados
D106: Intereses recibidos
D107: Impuestos a las ganancias reembolsados (pagados)
D108: Otras entradas (salidas) de efectivo
D109: Flujos de efectivo netos procedentes de (utilizados en) actividades de operación | F109: =F108+F104-F103+F106-F105-F107+F102 | G109: =G108+G104-G103+G106-G105-G107+G102 | H109: =H108+H104-H103+H106-H105-H107+H102 | I109: =I108+I104-I103+I106-I105-I107+I102 | J109: =J108+J104-J103+J106-J105-J107+J102 | K109: =K108+K104-K103+K106-K105-K107+K102 | L109: =L108+L104-L103+L106-L105-L107+L102 | M109: =M108+M104-M103+M106-M105-M107+M102 | N109: =N108+N104-N103+N106-N105-N107+N102
C110: Flujos de efectivo procedentes de (utilizados en) actividades de inversión [resumen]
D111: Flujos de efectivo procedentes de la pérdida de control de subsidiarias u otros negocios
D112: Flujos de efectivo utilizados para obtener el control de subsidiarias u otros negocios
D113: Otros cobros por la venta de patrimonio o instrumentos de deuda de otras entidades
...

Sheet Hoja6
B2: Indice
B3: Archivo: | C3: I:\Proyectos2025\proyecto_niif\_backup_legacy\Grupo1_Individual_Directo_ID20037_2024-12-31.xbrl
B4: Empresa: | C4: 20037
B5: Vista: | C5: [610000] Estado de cambios en el patrimonio - Individual
B6: Eje X: | C6: N/A
B7: Eje Y: | C7: N/A
B9: Eje Z: | C9: Periodo Actual
F10: Patrimonio [miembro]
F11: Capital emitido [miembro] | G11: Acciones propias en cartera [miembro] | H11: Prima de emisión [miembro] | I11: Ganancias acumuladas [miembro] | J11: Total otras reservas [miembro] | Q11: Otras partidas patrimoniales [miembro] | AI11: Otras participaciones en el patrimonio (No ORI) [miembro]
J12: Reserva legal [miembro] | K12: Reserva para catástrofes [miembro] | L12: Reserva para estabilización [miembro] | M12: Reserva de componentes de participación discrecional [miembro] | N12: Reserva de pagos basados en acciones [miembro] | O12: Otras reservas [miembro] | Q12: Reserva de ganancias y pérdidas por inversiones en instrumentos de patrimonio [miembro] | R12: Importes reconocidos en otro resultado integral y acumulados en el patrimonio relativos a activos no corrientes o grupos de activos para su disposición mantenidos para la venta [miembro] | S12: Superávit de revaluación [miembro] | T12: Reserva de nuevas mediciones de planes de beneficios definidos [miembro] | U12: Reserva para cambios en el valor razonable de pasivos financieros atribuibles a cambios en el riesgo crediticio del pasivo [miembro] | V12: Reserva de ganancias y pérdidas sobre instrumentos de cobertura que cubren inversiones en instrumentos de patrimonio [miembro] | W12: Reserva de diferencias de cambio en conversiones [miembro] | X12: Participación de otro resultado integral de asociadas y negocios conjuntos contabilizados utilizando el método de la participación [miembro] | Y12: Reserva de ganancias y pérdidas en nuevas mediciones de activos financieros disponibles para la venta [miembro] | Z12: Reserva de coberturas de flujo de efectivo [miembro] | AA12: Reserva de coberturas de inversiones netas en negocios en el extranjero [miembro] | AB12: Reserva por cambios en el valor temporal del dinero de opciones [miembro] | AC12: Reserva por cambios en el valor de los elementos a término de contratos a término [miembro] | AD12: Reserva por cambios en el valor de los diferenciales de la tasa de cambio de la moneda extranjera [miembro] | AE12: Reserva de ingresos (gastos) financieros por contratos de reaseguro mantenidos, excluidos del resultado del periodo [miembro] | AF12: Reserva de ingresos (gastos) financieros por contratos de seguro emitidos excluidos del resultado del periodo que no se reclasificará al resultado del periodo [miembro] | AG12: Reversión de ganancias y pérdidas sobre activos financieros medidos al valor razonable con cambios en otro resultado integral [miembro]
B13: Estado de cambios en el patrimonio [partidas]
C14: Patrimonio al comienzo del periodo | AJ14: =Hoja2!Q218+Hoja2!Q219-Hoja2!Q220+Hoja2!Q221+Hoja2!Q222+SUM(Hoja2!Q224:Q227)
C15: Incremento (disminución) por cambios en políticas contables
C16: Incremento (disminución) por correcciones de errores de periodos anteriores
C17: Patrimonio al comienzo del periodo incluyendo reexpresión. (Si la hubo).
C18: Cambios en el patrimonio [resumen]
D19: Resultado integral [resumen]
E20: Ganancia (pérdida) | AJ20: =Hoja3!N36+Hoja3!N37
E21: Otro resultado integral | AJ21: =Hoja4!H70-Hoja4!H79-Hoja4!H80-Hoja4!H92-Hoja4!H93
E22: Resultado integral total | F22: =F20+F21 | G22: =G20+G21 | H22: =H20+H21 | I22: =I20+I21 | J22: =J20+J21 | K22: =K20+K21 | L22: =L20+L21 | M22: =M20+M21 | ... AJ22: =AJ20+AJ21
D23: Emisión de patrimonio
D24: Dividendos reconocidos como distribuciones a los propietarios
D25: Incrementos por otras aportaciones de los propietarios, patrimonio
D26: Disminución por otras distribuciones a los propietarios, patrimonio
D27: Incrementos (disminuciones) por otros cambios, patrimonio
D28: Incrementos (disminuciones) por transacciones con acciones propias, patrimonio
D29: Incrementos (disminuciones) por cambios las participaciones en la propiedad de subsidiarias que no dan lugar a pérdida de control, patrimonio
D30: Incrementos (disminuciones) por transacciones con pagos basados en acciones, patrimonio
D31: Importe eliminado de reservas de coberturas de flujos de efectivo e incluido en el costo inicial u otro importe en libros de activos (pasivos) no financieros o compromisos en firme para los que se aplica la contabilidad de coberturas del valor razonable
D32: Importe eliminado de reservas de cambios en el valor temporal del dinero de opciones e incluido en el costo inicial u otro importe en libros de activos (pasivos) no financieros o compromisos en firme para los que se aplica la contabilidad de coberturas del valor razonable
D33: Importe eliminado de reservas de cambios en el valor de los elementos a término de contratos a término e incluido en el costo inicial u otro importe en libros de activos (pasivos) no financieros o compromisos en firme para los que se aplica la contabilidad de coberturas del valor razonable
D34: Importe eliminado de reservas de cambios en el valor de los diferenciales de tasa cambio de moneda extranjera e incluido en el costo inicial u otro importe en libros de activos (pasivos) no financieros o compromisos en firme para los que se aplica la contabilidad de coberturas del valor razonable
D35: Total incremento (disminución) en el patrimonio | F35: =F22+F23-F24+F25-F26+SUM(F27:F30)-SUM(F31:F34) | G35: =G22+G23-G24+G25-G26+SUM(G27:G30)-SUM(G31:G34) | H35: =H22+H23-H24+H25-H26+SUM(H27:H30)-SUM(H31:H34) | I35: =I22+I23-I24+I25-I26+SUM(I27:I30)-SUM(I31:I34) | J35: =J22+J23-J24+J25-J26+SUM(J27:J30)-SUM(J31:J34) | K35: =K22+K23-K24+K25-K26+SUM(K27:K30)-SUM(K31:K34) | L35: =L22+L23-L24+L25-L26+SUM(L27:L30)-SUM(L31:L34) | M35: =M22+M23-M24+M25-M26+SUM(M27:M30)-SUM(M31:M34) | ... AJ35: =AJ22+AJ23-AJ24+AJ25-AJ26+SUM(AJ27:AJ30)-SUM(AJ31:AJ34)
C36: Patrimonio al final del periodo | AJ36: =Hoja2!Q107+Hoja2!Q108-Hoja2!Q109+Hoja2!Q110+Hoja2!Q111+SUM(Hoja2!Q113:Q116)
B38: Eje Z: | C38: Periodo Anterior
F39: Patrimonio [miembro]
F40: Capital emitido [miembro] | G40: Acciones propias en cartera [miembro] | H40: Prima de emisión [miembro] | I40: Ganancias acumuladas [miembro] | J40: Total otras reservas [miembro] | Q40: Otras partidas patrimoniales [miembro] | AI40: Otras participaciones en el patrimonio (No ORI) [miembro]
J41: Reserva legal [miembro] | K41: Reserva para catástrofes [miembro] | L41: Reserva para estabilización [miembro] | M41: Reserva de componentes de participación discrecional [miembro] | N41: Reserva de pagos basados en acciones [miembro] | O41: Otras reservas [miembro] | Q41: Reserva de ganancias y pérdidas por inversiones en instrumentos de patrimonio [miembro] | R41: Importes reconocidos en otro resultado integral y acumulados en el patrimonio relativos a activos no corrientes o grupos de activos para su disposición mantenidos para la venta [miembro] | S41: Superávit de revaluación [miembro] | T41: Reserva de nuevas mediciones de planes de beneficios definidos [miembro] | U41: Reserva para cambios en el valor razonable de pasivos financieros atribuibles a cambios en el riesgo crediticio del pasivo [miembro] | V41: Reserva de ganancias y pérdidas sobre instrumentos de cobertura que cubren inversiones en instrumentos de patrimonio [miembro] | W41: Reserva de diferencias de cambio en conversiones [miembro] | X41: Participación de otro resultado integral de asociadas y negocios conjuntos contabilizados utilizando el método de la participación [miembro] | Y41: Reserva de ganancias y pérdidas en nuevas mediciones de activos financieros disponibles para la venta [miembro] | Z41: Reserva de coberturas de flujo de efectivo [miembro] | AA41: Reserva de coberturas de inversiones netas en negocios en el extranjero [miembro] | AB41: Reserva por cambios en el valor temporal del dinero de opciones [miembro] | AC41: Reserva por cambios en el valor de los elementos a término de contratos a término [miembro] | AD41: Reserva por cambios en el valor de los diferenciales de la tasa de cambio de la moneda extranjera [miembro] | AE41: Reserva de ingresos (gastos) financieros por contratos de reaseguro mantenidos, excluidos del resultado del periodo [miembro] | AF41: Reserva de ingresos (gastos) financieros por contratos de seguro emitidos excluidos del resultado del periodo que no se reclasificará al resultado del periodo [miembro] | AG41: Reversión de ganancias y pérdidas sobre activos financieros medidos al valor razonable con cambios en otro resultado integral [miembro]
B42: Estado de cambios en el patrimonio [partidas]
C43: Patrimonio al comienzo del periodo
C44: Incremento (disminución) por cambios en políticas contables
C45: Incremento (disminución) por correcciones de errores de periodos anteriores
C46: Patrimonio al comienzo del periodo incluyendo reexpresión. (Si la hubo).
C47: Cambios en el patrimonio [resumen]
D48: Resultado integral [resumen]
E49: Ganancia (pérdida) | AJ49: =Hoja3!N76+Hoja3!N77
E50: Otro resultado integral | AJ50: =Hoja4!I70-Hoja4!I79-Hoja4!I80-Hoja4!I92-Hoja4!I93
E51: Resultado integral total | F51: =F49+F50 | G51: =G49+G50 | H51: =H49+H50 | I51: =I49+I50 | J51: =J49+J50 | K51: =K49+K50 | L51: =L49+L50 | M51: =M49+M50 | ... AJ51: =AJ49+AJ50
D52: Emisión de patrimonio
D53: Dividendos reconocidos como distribuciones a los propietarios
D54: Incrementos por otras aportaciones de los propietarios, patrimonio
D55: Disminución por otras distribuciones a los propietarios, patrimonio
D56: Incrementos (disminuciones) por otros cambios, patrimonio
D57: Incrementos (disminuciones) por transacciones con acciones propias, patrimonio
D58: Incrementos (disminuciones) por cambios las participaciones en la propiedad de subsidiarias que no dan lugar a pérdida de control, patrimonio
D59: Incrementos (disminuciones) por transacciones con pagos basados en acciones, patrimonio
D60: Importe eliminado de reservas de coberturas de flujos de efectivo e incluido en el costo inicial u otro importe en libros de activos (pasivos) no financieros o compromisos en firme para los que se aplica la contabilidad de coberturas del valor razonable
D61: Importe eliminado de reservas de cambios en el valor temporal del dinero de opciones e incluido en el costo inicial u otro importe en libros de activos (pasivos) no financieros o compromisos en firme para los que se aplica la contabilidad de coberturas del valor razonable
D62: Importe eliminado de reservas de cambios en el valor de los elementos a término de contratos a término e incluido en el costo inicial u otro importe en libros de activos (pasivos) no financieros o compromisos en firme para los que se aplica la contabilidad de coberturas del valor razonable
D63: Importe eliminado de reservas de cambios en el valor de los diferenciales de tasa cambio de moneda extranjera e incluido en el costo inicial u otro importe en libros de activos (pasivos) no financieros o compromisos en firme para los que se aplica la contabilidad de coberturas del valor razonable
D64: Total incremento (disminución) en el patrimonio | F64: =F51+F52-F53+F54-F55+SUM(F56:F59)-SUM(F60:F63) | G64: =G51+G52-G53+G54-G55+SUM(G56:G59)-SUM(G60:G63) | H64: =H51+H52-H53+H54-H55+SUM(H56:H59)-SUM(H60:H63) | I64: =I51+I52-I53+I54-I55+SUM(I56:I59)-SUM(I60:I63) | J64: =J51+J52-J53+J54-J55+SUM(J56:J59)-SUM(J60:J63) | K64: =K51+K52-K53+K54-K55+SUM(K56:K59)-SUM(K60:K63) | L64: =L51+L52-L53+L54-L55+SUM(L56:L59)-SUM(L60:L63) | M64: =M51+M52-M53+M54-M55+SUM(M56:M59)-SUM(M60:M63) | ... AJ64: =AJ51+AJ52-AJ53+AJ54-AJ55+SUM(AJ56:AJ59)-SUM(AJ60:AJ63)
C65: Patrimonio al final del periodo | F65: =F14 | G65: =G14 | H65: =H14 | I65: =I14 | J65: =J14 | K65: =K14 | L65: =L14 | M65: =M14 | ... AI65: =AI14 | AJ65: =Hoja2!Q218+Hoja2!Q219-Hoja2!Q220+Hoja2!Q221+Hoja2!Q222+SUM(Hoja2!Q224:Q227)

Sheet Hoja7
B2: Indice
B3: Archivo: | C3: I:\Proyectos2025\proyecto_niif\_backup_legacy\Grupo1_Individual_Directo_ID20037_2024-12-31.xbrl
B4: Empresa: | C4: 20037
B5: Vista: | C5: [800100] Notas - Subclasificaciones de activos, pasivos y patrimonios
B6: Eje X: | C6: N/A
B7: Eje Y: | C7: N/A
B8: Eje Z: | C8: N/A
F10: Periodo Actual
B11: Subclasificaciones de activos, pasivos y patrimonios [resumen]
C12: Inversiones en subsidiarias, negocios conjuntos y asociadas presentadas en los estados financieros separados [resumen]
D13: Inversiones en subsidiarias presentadas en estados financieros separados | F13: =Hoja2!Q46
D14: Inversiones en negocios conjuntos presentadas en estados financieros separados | F14: =Hoja2!Q47
D15: Inversiones en asociadas presentadas en estados financieros separados | F15: =Hoja2!Q45
D16: Total de inversiones en subsidiarias, negocios conjuntos y asociadas en los estados financieros separados | F16: =SUM(F13:F15)
C17: Efectivo y equivalentes al efectivo [resumen]
D18: Efectivo [resumen]
E19: Efectivo en caja
E20: Saldos en bancos
E21: Total efectivo | F21: =F19+F20
D22: Equivalentes al efectivo [resumen]
E23: Depósitos a corto plazo, clasificados como equivalentes al efectivo
E24: Inversiones a corto plazo, clasificados como equivalentes al efectivo
E25: Otros acuerdos bancarios, clasificados como equivalentes al efectivo
E26: Total equivalentes al efectivo | F26: =SUM(F23:F25)
D27: Otro efectivo y equivalentes al efectivo
D28: Total de efectivo y equivalentes al efectivo | F28: =F21+F26+F27
C29: Préstamos tomados [resumen]
D30: Parte no corriente de préstamos no corrientes
D31: Préstamos corrientes y parte corriente de préstamos no corrientes [resumen]
E32: Préstamos corrientes
E33: Parte corriente de préstamos no corrientes
E34: Total préstamos corrientes y parte corriente de préstamos no corrientes | F34: =F32+F33
D35: Total préstamos | F35: =F30+F34

Sheet Hoja8
B2: Indice
B3: Archivo: | C3: I:\Proyectos2025\proyecto_niif\_backup_legacy\Grupo1_Individual_Directo_ID20037_2024-12-31.xbrl
B4: Empresa: | C4: 20037
B5: Vista: | C5: [800500] Notas - Lista de Notas
B6: Eje X: | C6: N/A
B7: Eje Y: | C7: N/A
B8: Eje Z: | C8: N/A
D10: Periodo Actual
B11: Información a revelar sobre notas y otra información explicativa [bloque de texto]
C12: Información a revelar sobre juicios y estimaciones contables [bloque de texto]
C13: Información a revelar sobre gastos acumulados (devengados) y otros pasivos [bloque de texto]
C14: Información a revelar sobre correcciones de valor por pérdidas crediticias [bloque de texto]
C15: Información a revelar sobre asociadas [bloque de texto]
C16: Información a revelar sobre remuneración de los auditores [bloque de texto]
C17: Información a revelar sobre la autorización de los estados financieros [bloque de texto]
C18: información a revelar sobre activos financieros disponibles para la venta [bloque de texto]
C19: Información a revelar sobre criterios de consolidación [bloque de texto]
C20: Información a revelar sobre criterios de elaboración de los estados financieros [bloque de texto]
C21: Información a revelar sobre préstamos [bloque de texto]
C22: Información a revelar sobre combinaciones de negocios [bloque de texto]
C23: Información a revelar sobre saldos bancarios y de efectivo en bancos centrales [bloque de texto]
... C132: Información a revelar sobre derechos a participaciones que surgen de fondos de desmantelamiento, restauración y la rehabilitación medioambiental [bloque de texto]

Sheet Hoja9
B2: Indice
B3: Archivo: | C3: I:\Proyectos2025\proyecto_niif\_backup_legacy\Grupo1_Individual_Directo_ID20037_2024-12-31.xbrl
B4: Empresa: | C4: 20037
B5: Vista: | C5: [800600] Notas - Lista de políticas contables
B6: Eje X: | C6: N/A
B7: Eje Y: | C7: N/A
B8: Eje Z: | C8: N/A
D10: Periodo Actual
B11: Información a revelar sobre las políticas contables significativas [bloque de texto]
C12: Descripción de la política contable para activos financieros disponibles para la venta [bloque de texto]
C13: Descripción de la política contable para costos de préstamos [bloque de texto]
C14: Descripción de la política contable para préstamos [bloque de texto]
C15: Descripción de la política contable para combinaciones de negocios y plusvalía [bloque de texto]
C16: Descripción de la política contable para flujos de efectivo [bloque de texto]
C17: Descripción de la política contable para construcciones en proceso [bloque de texto]
C18: Descripción de la política contable para pasivos contingentes y activos contingentes [bloque de texto]
C19: Descripción de la política contable para provisiones para retiro del servicio, restauración y rehabilitación [bloque de texto]
C20: Descripción de la política contable para impuesto a las ganancias diferido [bloque de texto]
C21: Descripción de la política contable para gastos por depreciación [bloque de texto]
C22: Descripción de la política contable para baja en cuentas de instrumentos financieros [bloque de texto]
C23: Descripción de la política contable para instrumentos financieros derivados y coberturas [bloque de texto]
... C81: Descripción de otras políticas contables relevantes para comprender los estados financieros [bloque de texto]

Sheet Hoja10
B2: Indice
B3: Archivo: | C3: I:\Proyectos2025\proyecto_niif\_backup_legacy\Grupo1_Individual_Directo_ID20037_2024-12-31.xbrl
B4: Empresa: | C4: 20037
B5: Vista: | C5: [810000] Notas - Información de la entidad y declaración de cumplimiento con el marco normativo
B6: Eje X: | C6: N/A
B7: Eje Y: | C7: N/A
B8: Eje Z: | C8: N/A
F10: Periodo Actual
B11: Información a revelar sobre notas y otra información explicativa [bloque de texto]
C12: Sede de la entidad
C13: Forma legal de la entidad
C14: País de constitución
C15: Ciudad donde se encuentra ubicada la sede administrativa
C16: Dirección de la sede administrativa de la entidad
C17: E-mail corporativo
C18: Número de empleados
C19: Número promedio de empleados
C20: Descripción de la naturaleza de las operaciones de la entidad y actividades principales
C21: Nombre de la entidad controladora
C22: Nombre de la controladora última del grupo
C23: Fecha establecida de duración de la entidad, para entidades de vida limitada
... C33: Hubo reclasificaciones que den lugar a variaciones en los valores certificados en el periodo anterior frente al comparado del periodo actual que se está presentando
D34: Explicación de reclasificaciones que den lugar a variaciones en los valores certificados en el periodo anterior frente al comparado del periodo actual que se está presentando
D35: Importe de reclasificaciones o cambios en la presentación
D36: Descripción de la naturaleza de los ajustes necesarios para presentar información comparativa
C37: Información a revelar sobre finalización de la prestación de los servicios inscritos en RUPS [resumen]
D38: Información a revelar sobre incertidumbres sobre la capacidad de dar continuidad a la prestación de uno o más servicios inscritos en RUPS
D39: ¿Durante el periodo sobre el que se informa se finalizó la prestación de uno o más servicios inscritos en RUPS?
E40: Detalle sobre la finalización de la prestación de los servicios inscritos en RUPS. (indicar servicio y fecha de finalización del servicio, indicar si otra empresa de servicios públicos tomó la prestación del servicio, ¿cuál?)
C41: Descripción del hecho de que los importes presentados en los estados financieros no son totalmente comparables
C42: Información relacionada con Objetivos de Desarrollo Sostenible impulsadas por la Organización de Naciones Unidas [Abstracto]
D43: La entidad ha implementado programas, prácticas o políticas relacionados con objetivos de desarrollo sostenible?
D44: La entidad prepara reportes de sostenibilidad?
D45: Si lo presenta como reporte a una entidad de supervisión específica, a cuál?
D46: La entidad cuenta con objetivos de desarrollo sostenible para el eje económico?
D47: Mencione que indicadores calcula. Explique los elementos que componen cada indicador.

Sheet Hoja11
B2: Indice
B3: Archivo: | C3: I:\Proyectos2025\proyecto_niif\_backup_legacy\Grupo1_Individual_Directo_ID20037_2024-12-31.xbrl
B4: Empresa: | C4: 20037
B5: Vista: | C5: [811001] Notas - Cambios por políticas contables, estimaciones contables o corrección de errores
B6: Eje X: | C6: N/A
B7: Eje Y: | C7: N/A
B8: Eje Z: | C8: Periodo Actual
C10: Detalle de los cambios en políticas contables, estimaciones contables y errores [Resumen]
C11: Tipo de Cambio por politica, estimación o corrección de error | D11: Descripción del cambio en política, estimación o corrección de error | E11: Impacto en el activo por cambio por política, estimación o corrección de error | F11: Impacto en el pasivo por cambio por política, estimación o corrección de error | G11: Impacto en el patrimonio por cambio por política, estimación o corrección de error | H11: Impacto en el resultado por cambio por política, estimación o corrección de error
B12: # Fila de cambio por política, estimación o error

Sheet Hoja12
B2: Indice
B3: Archivo: | C3: I:\Proyectos2025\proyecto_niif\_backup_legacy\Grupo1_Individual_Directo_ID20037_2024-12-31.xbrl
B4: Empresa: | C4: 20037
B5: Vista: | C5: [822100] Notas - Propiedades, planta y equipo - Bloques de texto
B6: Eje X: | C6: N/A
B7: Eje Y: | C7: N/A
B8: Eje Z: | C8: N/A
D10: Periodo Actual
B11: Información a revelar sobre propiedades, planta y equipo [bloque de texto]
C12: Información a revelar detallada sobre propiedades, planta y equipo [bloque de texto]
C13: Propiedades, planta y equipo, restricciones en la titularidad
C14: Descripción de la existencia de restricciones en la titularidad, propiedades, planta y equipo
C15: Propiedades, planta y equipo, pignoradas como garantía
C16: Compromisos contractuales para la adquisición de propiedades, planta y equipo

Sheet Hoja13
B2: Indice
B3: Archivo: | C3: I:\Proyectos2025\proyecto_niif\_backup_legacy\Grupo1_Individual_Directo_ID20037_2024-12-31.xbrl
B4: Empresa: | C4: 20037
B5: Vista: | C5: [822100a] Notas - Propiedades, planta y equipo - Información a revelar
B6: Eje X: | C6: N/A
B7: Eje Y: | C7: N/A
B8: Eje Z: | C8: Periodo Actual
F10: Propiedades, planta y equipo [miembro]
F11: Terrenos y construcciones [miembro] | H11: Maquinaria [miembro] | I11: Vehículos [miembro] | J11: Enseres y accesorios [miembro] | K11: Equipo de oficina [miembro] | L11: Equipos informáticos [miembro] | M11: Equipos de redes y comunicación [miembro] | N11: Construcciones en proceso [miembro] | O11: Información complementaria [miembro] | T11: Otras propiedades, planta y equipo [miembro]
F12: Terrenos [miembro] | G12: Edificios [miembro] | O12: Plantas [miembro] | P12: Ductos [miembro] | Q12: Vías [miembro] | R12: Redes y Cables [miembro] | S12: Relleno sanitario [miembro]
B13: Información a revelar detallada sobre propiedades, planta y equipo [partidas]
C14: Bases de medición, propiedades, planta y equipo
C15: Método de depreciación, propiedades, planta y equipo
C16: Vidas útiles o tasas de depreciación, propiedades, planta y equipo
C17: Fechas de vigencia de revaluación, propiedades, planta y equipo
C18: Explicación de la implicación del tasador independiente en la revaluación, propiedades, planta y equipo
C19: Conciliación de cambios en propiedades, planta y equipo [resumen]
D20: Propiedades, planta y equipo al comienzo del periodo | U20: =Hoja2!Q151
D21: Cambios en propiedades, planta y equipo [resumen]
E22: Incrementos distintos de los procedentes de combinaciones de negocios, propiedades, planta y equipo
E23: Adquisiciones realizadas mediante combinaciones de negocios, propiedades, planta y equipo
E24: Incremento (disminución) por diferencias de cambio netas, propiedades, planta y equipo
E25: Depreciación, propiedades, planta y equipo
E26: Pérdidas por deterioro de valor reconocidas en el resultado del periodo, propiedades, planta y equipo
E27: Reversión de pérdidas por deterioro de valor reconocidas en el resultado del periodo, propiedades, planta y equipo
E28: Incrementos (disminuciones) de revaluaciones, propiedades, planta y equipo
E29: Pérdidas por deterioro de valor reconocidas en otro resultado integral, propiedades, planta y equipo
E30: Reversión de pérdidas por deterioro de valor reconocidas en otro resultado integral, propiedades, planta y equipo
E31: Disposiciones y retiros de servicio, propiedades, planta y equipo
E32: Disminuciones por clasificar como mantenidos para la venta, propiedades, planta y equipo
E33: Incrementos (disminuciones) por otros cambios, propiedades, planta y equipo
E34: Total incremento (disminución) en propiedades, planta y equipo | F34: =SUM(F22:F24)-F25-F26+F27+F28-F29+F30-F31-F32+F33 | G34: =SUM(G22:G24)-G25-G26+G27+G28-G29+G30-G31-G32+G33 | H34: =SUM(H22:H24)-H25-H26+H27+H28-H29+H30-H31-H32+H33 | I34: =SUM(I22:I24)-I25-I26+I27+I28-I29+I30-I31-I32+I33 | J34: =SUM(J22:J24)-J25-J26+J27+J28-J29+J30-J31-J32+J33 | K34: =SUM(K22:K24)-K25-K26+K27+K28-K29+K30-K31-K32+K33 | L34: =SUM(L22:L24)-L25-L26+L27+L28-L29+L30-L31-L32+L33 | M34: =SUM(M22:M24)-M25-M26+M27+M28-M29+M30-M31-M32+M33 | ... U34: =SUM(U22:U24)-U25-U26+U27+U28-U29+U30-U31-U32+U33
D35: Propiedades, planta y equipo al final del periodo | U35: =Hoja2!Q40
C36: Información adicional [resumen]
D37: Propiedades, planta y equipo, desembolsos reconocidos en el curso de su construcción.
D38: Propiedades, planta y equipo, ociosos temporalmente.
D39: Propiedades, planta y equipo, importe en libros en términos brutos de los activos depreciados en su totalidad todavía en uso.
D40: Propiedades, planta y equipo, activos retirados del uso activo y no clasificados como mantenidos para la venta.
C41: Propiedades, planta y equipo, revaluación [resumen]
D42: Propiedades, planta y equipo, activos revaluados.
D43: Propiedades, planta y equipo, activos revaluados, al costo.
D44: Propiedades, planta y equipo, superávit de revaluación.
D45: Descripción de restricciones sobre la distribución del superávit de revaluación a los accionistas, propiedades, planta y equipo

Sheet Hoja14
B2: Indice
B3: Archivo: | C3: I:\Proyectos2025\proyecto_niif\_backup_legacy\Grupo1_Individual_Directo_ID20037_2024-12-31.xbrl
B4: Empresa: | C4: 20037
B5: Vista: | C5: [822390] Notas - Instrumentos financieros - Bloques de texto
B6: Eje X: | C6: N/A
B7: Eje Y: | C7: N/A
B8: Eje Z: | C8: N/A
D10: Periodo Actual
B11: Información a revelar sobre instrumentos financieros [bloque de texto]
C12: Información a revelar de activos financieros [bloque de texto]
C13: Información a revelar sobre pasivos financieros [bloque de texto]
C14: Información a revelar detallada sobre coberturas [bloque de texto]

Sheet Hoja15
B2: Indice
B3: Archivo: | C3: I:\Proyectos2025\proyecto_niif\_backup_legacy\Grupo1_Individual_Directo_ID20037_2024-12-31.xbrl
B4: Empresa: | C4: 20037
B5: Vista: | C5: [822390a] Notas - Instrumentos financieros - Activos financieros
B6: Eje X: | C6: N/A
B7: Eje Y: | C7: N/A
B8: Eje Z: | C8: Periodo Actual
D10: Activos financieros, categoría [miembro]
D11: Activos financieros al valor razonable con cambios en resultados, categoría [miembro] | E11: Activos financieros disponibles para la venta, categoría [miembro] | F11: Inversiones mantenidas hasta el vencimiento, categoría [miembro] | G11: Préstamos y cuentas por cobrar, categoría [miembro] | H11: Activos financieros al costo amortizado, categoría [miembro] | I11: Activos financieros al valor razonable con cambios en otro resultado integral, categoría [miembro] | J11: Inversiones en instrumentos de patrimonio designadas a valor razonable con cambios en otro resultado integral [miembro]
B12: Información a revelar sobre activos financieros [partidas]
C13: Activos financieros
C14: Activos financieros, al valor razonable
C15: Importe nocional
C16: Pérdidas por deterioro de valor, activos financieros

Sheet Hoja16
B2: Indice
B3: Archivo: | C3: I:\Proyectos2025\proyecto_niif\_backup_legacy\Grupo1_Individual_Directo_ID20037_2024-12-31.xbrl
B4: Empresa: | C4: 20037
B5: Vista: | C5: [822390b] Notas - Instrumentos financieros - Pasivos financieros
B6: Eje X: | C6: N/A
B7: Eje Y: | C7: N/A
B8: Eje Z: | C8: Periodo Actual
D10: Pasivos financieros, categoría [miembro]
D11: Pasivos financieros al valor razonable con cambios en resultados, categoría [miembro] | E11: Pasivos financieros al costo amortizado, categoría [miembro] | F11: Pasivos financieros que quedan fuera del alcance de la NIIF 7 [miembro]
B12: Información a revelar sobre pasivos financieros [partidas de los estados financieros]
C13: Pasivos financieros
C14: Pasivos financieros, al valor razonable

Sheet Hoja17
B2: Indice
B3: Archivo: | C3: I:\Proyectos2025\proyecto_niif\_backup_legacy\Grupo1_Individual_Directo_ID20037_2024-12-31.xbrl
B4: Empresa: | C4: 20037
B5: Vista: | C5: [822390c] Notas - Instrumentos financieros - Coberturas
B6: Eje X: | C6: N/A
B7: Eje Y: | C7: N/A
B8: Eje Z: | C8: Periodo Actual
D10: Coberturas [miembro]
D11: Coberturas del valor razonable [miembro] | E11: Coberturas del flujo de efectivo [miembro] | F11: Coberturas de inversiones netas en negocios en el extranjero [miembro]
B12: Información a revelar detallada sobre coberturas [partidas]
C13: Descripción del tipo de cobertura
C14: Descripción de instrumentos financieros designados como instrumentos de cobertura
C15: Descripción de la naturaleza de los riesgos que han sido cubiertos
C16: Instrumentos financieros designados como instrumentos de cobertura

Sheet Hoja18
B2: Indice
B3: Archivo: | C3: I:\Proyectos2025\proyecto_niif\_backup_legacy\Grupo1_Individual_Directo_ID20037_2024-12-31.xbrl
B4: Empresa: | C4: 20037
B5: Vista: | C5: [823000] Notas - Medición del valor razonable
B6: Eje X: | C6: N/A
B7: Eje Y: | C7: N/A
B8: Eje Z: | C8: N/A
D10: Periodo Actual
B11: Información a revelar sobre medición del valor razonable [bloque de texto]
C12: Información a revelar sobre medición del valor razonable de activos [bloque de texto]
C13: Información a revelar sobre medición del valor razonable de pasivos [bloque de texto]
C14: Información a revelar sobre medición del valor razonable del patrimonio [bloque de texto]
C15: Información a revelar sobre datos de entrada no observables significativos utilizados en la medición del valor razonable de activos [bloque de texto]
C16: Información a revelar sobre datos de entrada no observables significativos utilizados en la medición del valor razonable de pasivos [bloque de texto]
C17: Información a revelar sobre datos de entrada no observables significativos utilizados en la medición del valor razonable del patrimonio [bloque de texto]

Sheet Hoja19
B2: Indice
B3: Archivo: | C3: I:\Proyectos2025\proyecto_niif\_backup_legacy\Grupo1_Individual_Directo_ID20037_2024-12-31.xbrl
B4: Empresa: | C4: 20037
B5: Vista: | C5: [823180] Notas - Activos intangibles - Información descriptiva
B6: Eje X: | C6: N/A
B7: Eje Y: | C7: N/A
B8: Eje Z: | C8: N/A
D10: Periodo Actual
B11: Información a revelar detallada sobre activos intangibles [resumen]
C12: Información a revelar detallada sobre activos intangibles [bloque de texto]
C13: Información a revelar sobre activos intangibles con vidas útiles indefinidas [bloque de texto]
C14: Activos intangibles con vidas útiles indefinidas
C15: Descripción de los activos intangibles con vida útil indefinida que soportan la evaluación de vida útil indefinida
C16: Información a revelar sobre activos intangibles significativos para la entidad [bloque de texto]
C17: Descripción de los activos intangibles de importancia relativa para la entidad
C18: Activos intangibles materiales (con importancia relativa) para la entidad
C19: Periodo de amortización restante de activos intangibles significativos para la entidad
C20: Activos intangibles adquiridos mediante subvenciones del gobierno
C21: Explicación de activos adquiridos mediante una subvención del gobierno y reconocidos inicialmente por su valor razonable
C22: Activos intangibles cuya titularidad está restringida
C23: Descripción de los activos intangibles totalmente amortizados
... C27: Información a revelar sobre la conciliación de cambios en activos intangibles y plusvalía [bloque de texto]

Sheet Hoja20
B2: Indice
B3: Archivo: | C3: I:\Proyectos2025\proyecto_niif\_backup_legacy\Grupo1_Individual_Directo_ID20037_2024-12-31.xbrl
B4: Empresa: | C4: 20037
B5: Vista: | C5: [823180a] Notas - Activos intangibles - Conciliación incluye plusvalía
B6: Eje X: | C6: N/A
B7: Eje Y: | C7: N/A
B8: Eje Z: | C8: Periodo Actual
F10: Activos [miembro]
F11: Activos intangibles distintos a la plusvalía y plusvalía [miembro] | P11: Métodos de generación [miembro]
F12: Activos intangibles distintos de la plusvalía [miembro] | N12: Plusvalía [miembro] | P12: Generados internamente [miembro] | Q12: No generados internamente [miembro]
F13: Marcas comerciales [miembro] | G13: Activos intangibles de exploración y evaluación [miembro] | H13: Programas de computador [miembro] | I13: Valor de negocio adquirido [miembro] | J13: Desembolsos de desarrollo capitalizados [miembro] | K13: Activos intangibles en desarrollo [miembro] | L13: Otros activos intangibles [miembro]
B14: Información a revelar sobre la conciliación de cambios en activos intangibles y plusvalía [partidas de los estados financieros]
C15: Conciliación de los cambios en activos intangibles y plusvalía [resumen]
D16: Activos intangibles y plusvalía al comienzo del periodo
D17: Cambios en activos intangibles y plusvalía [resumen]
E18: Amortización, activos intangibles distintos de la plusvalía
E19: Pérdida por deterioro de valor reconocida en el resultado del periodo, activos intangibles y plusvalía
E20: Reversión de pérdidas por deterioro de valor reconocidas en el resultado del periodo, activos intangibles distintos de la plusvalía
E21: Incrementos (disminuciones) de revaluaciones, activos intangibles distintos de la plusvalía
E22: Pérdidas por deterioro de valor reconocidas en otro resultado integral, activos intangibles distintos de la plusvalía
E23: Reversión de pérdidas por deterioro de valor reconocidas en otro resultado integral, activos intangibles distintos de la plusvalía
E24: Incrementos (disminuciones) por transferencias y otros cambios, activos intangibles y plusvalía
E25: Disposiciones y retiros de servicio, activos intangibles y plusvalía
E26: Disminuciones por clasificar como mantenidos para la venta, activos intangibles y plusvalía
E27: Disminución por la pérdida de control de una subsidiaria, activos intangibles y plusvalía
E28: Reconocimiento posterior de activos por impuestos diferidos, plusvalía
E29: Total incrementos (disminuciones) de activos intangibles y plusvalía | F29: =-F18-F19+F20+F21-F22+F23+F24-SUM(F25:F28) | G29: =-G18-G19+G20+G21-G22+G23+G24-SUM(G25:G28) | H29: =-H18-H19+H20+H21-H22+H23+H24-SUM(H25:H28) | I29: =-I18-I19+I20+I21-I22+I23+I24-SUM(I25:I28) | J29: =-J18-J19+J20+J21-J22+J23+J24-SUM(J25:J28) | K29: =-K18-K19+K20+K21-K22+K23+K24-SUM(K25:K28) | L29: =-L18-L19+L20+L21-L22+L23+L24-SUM(L25:L28) | M29: =-M18-M19+M20+M21-M22+M23+M24-SUM(M25:M28) | ... Q29: =-Q18-Q19+Q20+Q21-Q22+Q23+Q24-SUM(Q25:Q28)
D30: Activos intangibles y plusvalía al final del periodo
C31: Revaluación de activos intangibles [resumen]
D32: Activos intangibles distintos de la plusvalía, activos revaluados
D33: Activos intangibles distintos de la plusvalía, activos revaluados, al costo
D34: Activos intangibles distintos de la plusvalía, superávit de revaluación

Sheet Hoja21
B2: Indice
B3: Archivo: | C3: I:\Proyectos2025\proyecto_niif\_backup_legacy\Grupo1_Individual_Directo_ID20037_2024-12-31.xbrl
B4: Empresa: | C4: 20037
B5: Vista: | C5: [825100] Notas - Propiedades de inversión - Información descriptiva
B6: Eje X: | C6: N/A
B7: Eje Y: | C7: N/A
B8: Eje Z: | C8: N/A
D10: Periodo Actual
B11: Información a revelar sobre propiedades de inversión [bloque de texto]
C12: Explicación de si la entidad aplicaba el modelo del valor razonable o el modelo del costo para medir las propiedades de inversión
C13: Descripción de los criterios utilizados para distinguir entre propiedades de inversión de las propiedades ocupadas por el propietario y de las propiedades mantenidas para la venta en el curso ordinario del negocio
C14: Descripción de la medida en que el valor razonable de las propiedades de inversión se basan en la valoración por un tasador independiente
C15: Ingreso por alquileres de propiedades de inversión, neto de gastos de operación directos
C16: Cambio acumulado en el valor razonable reconocido en el resultado del periodo por la venta de propiedades de inversión entre conjuntos de activos medidos usando diferentes modelos
C17: Explicación de las restricciones sobre la realización de las propiedades de inversión o remisión de los ingresos y recursos obtenidos por su disposición
C18: Restricciones sobre la realización de propiedades de inversión o la remisión de ingresos e importes obtenidos por su disposición
C19: Explicación de obligaciones contractuales para adquisición, construcción o desarrollo de propiedades de inversión o por reparaciones, mantenimiento o mejoras
C20: Información a revelar sobre ajustes significativos a la valoración obtenida [bloque de texto]
C21: Descripción de propiedades de inversión, al costo o de acuerdo con la NIIF 16 dentro del modelo de valor razonable
C22: Explicación de por qué el valor razonable no puede medirse con fiabilidad para propiedades de inversión, al costo o de acuerdo con la NIIF 16 dentro del modelo del valor razonable
C23: Rango de estimaciones dentro del cual es probable que quede el valor razonable para propiedades de inversión, al costo o de acuerdo con la NIIF 16 dentro del modelo del valor razonable
... C30: Rango de estimaciones dentro de las que es probable que se encuentre el valor razonable para propiedades de inversión, modelo del costo

Sheet Hoja22
B2: Indice
B3: Archivo: | C3: I:\Proyectos2025\proyecto_niif\_backup_legacy\Grupo1_Individual_Directo_ID20037_2024-12-31.xbrl
B4: Empresa: | C4: 20037
B5: Vista: | C5: [825100a] Notas - Propiedades de inversión - Información detallada
B6: Eje X: | C6: N/A
B7: Eje Y: | C7: N/A
B8: Eje Z: | C8: Periodo Actual
F10: Suma de mediciones [miembro]
F11: Al costo [miembro] | G11: Modelo del valor razonable [miembro]
G12: A valor razonable [miembro] | H12: Al costo o de acuerdo con la NIIF 16 dentro del modelo de valor razonable [miembro]
B13: Información a revelar detallada sobre propiedades de inversión [partidas]
C14: Propiedades de inversión al comienzo del periodo | J14: =Hoja2!Q152
C15: Cambios en propiedades de inversión [resumen]
D16: Incrementos, propiedades de inversión [resumen]
E17: Incrementos derivados de desembolsos posteriores reconocidos como activos, propiedades de inversión
E18: Adiciones derivados de adquisiciones, propiedades de inversión
E19: Total adiciones distintas de las de por combinaciones de negocios, propiedades de inversión | F19: =F17+F18 | G19: =G17+G18 | H19: =H17+H18 | I19: =I17+I18 | J19: =J17+J18
D20: Adquisiciones realizadas mediante combinaciones de negocios, propiedades de inversión
D21: Incremento (disminución) por diferencias de cambio netas, propiedades de inversión
D22: Depreciación, propiedades de inversión
D23: Pérdidas por deterioro de valor reconocida en resultados, propiedades de inversión
D24: Reversión de deterioro de valor reconocida en resultados, propiedades de inversión
D25: Ganancias (pérdidas) por ajustes del valor razonable, propiedades de inversión
D26: Transferencias de (a) inventarios y bienes inmuebles ocupados por el propietario, propiedades de inversión
D27: Disposiciones, propiedades de inversión
D28: Disminuciones mediante la clasificación de mantenidos para la venta, propiedades de inversión
D29: Incremento (disminución) por otros cambios, propiedades de inversión
D30: Total incremento (disminución) en propiedades de inversión | F30: =SUM(F19:F21)-F22-F23+SUM(F24:F26)-F27-F28+F29 | G30: =SUM(G19:G21)-G22-G23+SUM(G24:G26)-G27-G28+G29 | H30: =SUM(H19:H21)-H22-H23+SUM(H24:H26)-H27-H28+H29 | I30: =SUM(I19:I21)-I22-I23+SUM(I24:I26)-I27-I28+I29 | J30: =SUM(J19:J21)-J22-J23+SUM(J24:J26)-J27-J28+J29
C31: Propiedades de inversión al final del periodo | J31: =Hoja2!Q41

Sheet Hoja23
B2: Indice
B3: Archivo: | C3: I:\Proyectos2025\proyecto_niif\_backup_legacy\Grupo1_Individual_Directo_ID20037_2024-12-31.xbrl
B4: Empresa: | C4: 20037
B5: Vista: | C5: [825701] Notas - Información a revelar detallada sobre partes relacionadas
B6: Eje X: | C6: N/A
B7: Eje Y: | C7: N/A
B8: Eje Z: | C8: Periodo Actual
C10: Detalle de la parte relacionada [Resumen]
C11: Tipo de parte relacionada | D11: Nombre de la parte relacionada | E11: NIT de la parte relacionada | F11: ID de Prestador de la parte relacionada (Si está vigilado por la Superservicios) | G11: Ciudad de domicilio de la parte relacionada | H11: País donde está constituida la parte relacionada | I11: Porcentaje de participación en la parte relacionada | J11: Participación en parte relacionada | K11: Porcentaje de derechos de voto mantenidos por las participaciones no controladoras | L11: Porcentaje de derechos de voto mantenidos en la parte relacionada | M11: Ganancia (pérdida), atribuible a participaciones no controladoras | N11: Inversiones contabilizadas utilizando el método de la participación de la parte relacionada | O11: Inversiones contabilizadas utilizando el modelo del costo | P11: Inversiones contabilizadas utilizando el modelo del valor razonable | Q11: Nombre Controladora última del Grupo | R11: ID Controladora última del Grupo | S11: Nombre Controladora que emite Estados Financieros Consolidados disponible para uso público | T11: Saldos pendientes de transacciones con partes relacionadas: Importe de las Cuentas por cobrar con partes relacionadas | U11: Saldos pendientes de transacciones con partes relacionadas: Importe de las Cuentas por pagar con partes relacionadas | V11: Importe de los Ingresos con partes relacionadas | W11: Importe de Otros ingresos con partes relacionadas | X11: Importe de los Costos y Gastos con partes relacionadas | Y11: Los costos y gastos reconocido durante el periodo con respecto a las deudas incobrables y de dudoso cobro, procedentes de partes relacionadas | Z11: Importe de los servicios recibidos, transacciones con partes relacionadas | AA11: Descripción de los servicios recibidos, transacciones con partes relacionadas | AB11: Importe de compras de bienes muebles e inmuebles y otros activos, transacciones con partes relacionadas | AC11: Importe de ventas de bienes muebles e inmuebles y otros activos, transacciones con partes relacionadas | AD11: Descripción de las Compras y/o ventas de bienes muebles, inmuebles y otros activos con partes relacionadas | AE11: Información a revelar sobre esta parte relacionada | AF11: Descripción de las políticas contables aplicadas a esta parte relacionada | AG11: ¿La inversión en esta parte relacionada es significativa? | AH11: Activo corriente | AI11: Activo no corriente | AJ11: Activo total | AK11: Pasivo corriente | AL11: Pasivo no corriente | AM11: Pasivo total | AN11: Resultado Integral total
B12: # Fila de parte relacionada

Sheet Hoja24
B2: Indice
B3: Archivo: | C3: I:\Proyectos2025\proyecto_niif\_backup_legacy\Grupo1_Individual_Directo_ID20037_2024-12-31.xbrl
B4: Empresa: | C4: 20037
B5: Vista: | C5: [826380] Notas - Inventarios
B6: Eje X: | C6: N/A
B7: Eje Y: | C7: N/A
B8: Eje Z: | C8: N/A
D10: Periodo Actual
B11: Información a revelar sobre inventarios [bloque de texto]
C12: Descripción de las políticas contables para la medición de inventarios [bloque de texto]
C13: Descripción de las fórmulas del costo de inventario
C14: Inventarios al valor razonable menos los costos de venta
C15: Inventarios, a valor neto realizable
C16: Rebaja del valor del inventario
C17: Reversión de la rebaja del inventario
C18: Descripción de las circunstancias que conducen a reversiones de rebajas de inventarios
C19: Costo de inventarios reconocidos como gasto durante el periodo
C20: Inventarios pignorados como garantía de pasivos

Sheet Hoja25
B2: Indice
B3: Archivo: | C3: I:\Proyectos2025\proyecto_niif\_backup_legacy\Grupo1_Individual_Directo_ID20037_2024-12-31.xbrl
B4: Empresa: | C4: 20037
B5: Vista: | C5: [827570] Notas - Otras provisiones, pasivos contingentes y activos contingentes - Información a revelar
B6: Eje X: | C6: N/A
B7: Eje Y: | C7: N/A
B8: Eje Z: | C8: N/A
D10: Periodo Actual
B11: Información a revelar sobre otras provisiones, pasivos contingentes y activos contingentes [bloque de texto]
C12: Información a revelar sobre otras provisiones [bloque de texto]
C13: Descripción de la naturaleza de activos contingentes
C14: Explicación del efecto financiero estimado de activos contingentes
C15: Efecto financiero esperado de activos contingentes
C16: Información sobre activos contingentes cuya información a revelar no es practicable
C17: Información sobre pasivos contingentes cuya información a revelar no es practicable
C18: Explicación de la naturaleza general del conflicto y de la razón para no revelar información con respecto a provisiones
C19: Explicación de la naturaleza general del conflicto y de la razón para no revelar información con respecto a pasivos contingentes
C20: Explicación de la naturaleza general del conflicto y de la razón para no revelar información con respecto a activos contingentes

Sheet Hoja26
B2: Indice
B3: Archivo: | C3: I:\Proyectos2025\proyecto_niif\_backup_legacy\Grupo1_Individual_Directo_ID20037_2024-12-31.xbrl
B4: Empresa: | C4: 20037
B5: Vista: | C5: [827570a] Notas - Otras provisiones, pasivos contingentes y activos contingentes - Otras provisiones
B6: Eje X: | C6: N/A
B7: Eje Y: | C7: N/A
B8: Eje Z: | C8: Periodo Actual
G10: Otras provisiones [miembro]
G11: Provisiones por procesos legales [miembro] | H11: Provisión por contratos onerosos [miembro] | I11: Provisiones por costos de dejar fuera de servicio, restauración y rehabilitación [miembro] | J11: Otra provisión relacionada con el medioambiente [miembro] | K11: Provisión por impuestos distintos a los impuestos a las ganancias [miembro] | L11: Otras provisiones diversas [miembro]
B12: Información a revelar sobre otras provisiones [partidas de los estados financieros]
C13: Conciliación de cambios en otras provisiones [resumen]
D14: Otras provisiones al comienzo del periodo
D15: Cambios en otras provisiones [resumen]
E16: Provisiones adicionales, otras provisiones [resumen]
F17: Provisiones nuevas, otras provisiones
F18: Aumento de provisiones existentes, otras provisiones
F19: Total provisiones adicionales, otras provisiones | G19: =G17+G18 | H19: =H17+H18 | I19: =I17+I18 | J19: =J17+J18 | K19: =K17+K18 | L19: =L17+L18 | M19: =M17+M18
E20: Adquisiciones realizadas mediante combinaciones de negocios, otras provisiones
E21: Provisiones utilizadas, otras provisiones
E22: Provisiones revertidas no utilizadas, otras provisiones
E23: Incremento por ajustes que surgen por el paso del tiempo, otras provisiones
E24: Incremento (disminución) por cambios en la tasa de descuento, otras provisiones
E25: Incremento (disminución) por diferencias de cambio netas, otras provisiones
E26: Disminución por la pérdida de control de una subsidiaria, otras provisiones
E27: Incremento (disminución) por transferencias y otros cambios, otras provisiones
F28: Disminución por transferencias a pasivos incluidos en grupos de activos para su disposición clasificados como mantenidos para la venta, otras provisiones
E29: Total incremento (disminución) en otras provisiones | G29: =G19+G20-G21-G22+SUM(G23:G25)-G26+G27 | H29: =H19+H20-H21-H22+SUM(H23:H25)-H26+H27 | I29: =I19+I20-I21-I22+SUM(I23:I25)-I26+I27 | J29: =J19+J20-J21-J22+SUM(J23:J25)-J26+J27 | K29: =K19+K20-K21-K22+SUM(K23:K25)-K26+K27 | L29: =L19+L20-L21-L22+SUM(L23:L25)-L26+L27 | M29: =M19+M20-M21-M22+SUM(M23:M25)-M26+M27
D30: Otras provisiones al final del periodo
C31: Descripción de la naturaleza de obligaciones, otras provisiones
C32: Descripción del calendario esperado de flujos de salida, otras provisiones
C33: Indicación de incertidumbres de importes o calendario de salidas, otras provisiones
C34: Descripción de las hipótesis más importantes realizadas sobre eventos futuros, otras provisiones
C35: Activo reconocido por reembolsos esperados, otras provisiones
C36: Reembolso esperado, otras provisiones

Sheet Hoja27
B2: Indice
B3: Archivo: | C3: I:\Proyectos2025\proyecto_niif\_backup_legacy\Grupo1_Individual_Directo_ID20037_2024-12-31.xbrl
B4: Empresa: | C4: 20037
B5: Vista: | C5: [827570b] Notas - Otras provisiones, pasivos contingentes y activos contingentes - Pasivos contingentes
B6: Eje X: | C6: N/A
B7: Eje Y: | C7: N/A
B8: Eje Z: | C8: Periodo Actual
D10: Pasivos contingentes [miembro]
D11: Pasivos contingentes por procesos legales [miembro] | E11: Pasivos contingentes por contratos onerosos [miembro] | F11: Pasivos contingentes por costos de retiro del servicio, restauración y rehabilitación [miembro] | G11: Otro pasivo contingente relacionado con el medioambiente [miembro] | H11: Pasivo contingente por impuestos [miembro] | I11: Pasivo contingente que surge de obligaciones por beneficios post-empleo [miembro] | J11: Otros pasivos contingentes [miembro]
B12: Información a revelar sobre pasivos contingentes [partidas de los estados financieros]
C13: Descripción de la naturaleza de obligaciones, pasivos contingentes
C14: Explicación del efecto financiero estimado de los pasivos contingentes
C15: Efecto financiero esperado de pasivos contingentes
C16: Explicación de la posibilidad de reembolso, pasivos contingentes
C17: Indicación de incertidumbres de importes o calendario de salidas, pasivos contingentes

Sheet Hoja28
B2: Indice
B3: Archivo: | C3: I:\Proyectos2025\proyecto_niif\_backup_legacy\Grupo1_Individual_Directo_ID20037_2024-12-31.xbrl
B4: Empresa: | C4: 20037
B5: Vista: | C5: [831150] Notas - Ingresos de actividades ordinarias procedentes de contratos con clientes - Costos
B6: Eje X: | C6: N/A
B7: Eje Y: | C7: N/A
B8: Eje Z: | C8: N/A
D10: Periodo Actual
B11: Información a revelar de activos reconocidos por costos para obtener o cumplir contratos con clientes [partida de los estados financieros]
C12: Activos reconocidos por costos para obtener o cumplir contratos con clientes
C13: Amortización, activos reconocidos por costos incurridos para obtener o cumplir contratos con clientes
C14: Pérdidas por deterioro de valor, activos reconocidos por costos incurridos para obtener o cumplir contratos con clientes

Sheet Hoja29
B2: Indice
B3: Archivo: | C3: I:\Proyectos2025\proyecto_niif\_backup_legacy\Grupo1_Individual_Directo_ID20037_2024-12-31.xbrl
B4: Empresa: | C4: 20037
B5: Vista: | C5: [832410] Notas - Deterioro del valor de activos - Información descriptiva
B6: Eje X: | C6: N/A
B7: Eje Y: | C7: N/A
B8: Eje Z: | C8: N/A
D10: Periodo Actual
B11: Información a revelar sobre deterioro de valor de activos [bloque de texto]
C12: Información a revelar sobre pérdidas por deterioro del valor y reversión de las pérdidas por deterioro del valor [bloque de texto]
C13: Explicación de los principales eventos y circunstancias que han llevado al reconocimiento de pérdidas por deterioro del valor y reversiones de pérdidas por deterioro del valor
C14: Explicación de las principales clases de activos afectados por pérdidas por deterioro de valor o reversiones de pérdidas por deterioros de valor

Sheet Hoja30
B2: Indice
B3: Archivo: | C3: I:\Proyectos2025\proyecto_niif\_backup_legacy\Grupo1_Individual_Directo_ID20037_2024-12-31.xbrl
B4: Empresa: | C4: 20037
B5: Vista: | C5: [832410a] Notas - Deterioro del valor de activos
B6: Eje X: | C6: N/A
B7: Eje Y: | C7: N/A
B8: Eje Z: | C8: Periodo Actual
D10: Activos [miembro]
D11: Propiedades, planta y equipo [miembro] | E11: Activos intangibles distintos de la plusvalía [miembro] | F11: Plusvalía [miembro] | G11: Inversiones contabilizadas utilizando el método de la participación [miembro] | H11: Otros activos con su valor deteriorado [miembro]
B12: Información a revelar sobre pérdidas por deterioro del valor y reversión de las pérdidas por deterioro del valor [partidas]
C13: Pérdidas por deterioro de valor reconocidas en el resultado del periodo
C14: Descripción de la partida o partidas del estado del resultado integral en las que se incluyen las pérdidas por deterioro de valor reconocidas en el resultado del periodo
C15: Reversión de pérdidas por deterioro de valor reconocidas en el resultado del periodo
C16: Descripción de la partida o partidas del estado del resultado integral en las que se revierten las pérdidas por deterioro de valor reconocidas en el resultado del periodo
C17: Pérdidas por deterioro de valor reconocidas en otro resultado integral
C18: Reversión de pérdidas por deterioro de valor reconocidas en otro resultado integral

Sheet Hoja31
B2: Indice
B3: Archivo: | C3: I:\Proyectos2025\proyecto_niif\_backup_legacy\Grupo1_Individual_Directo_ID20037_2024-12-31.xbrl
B4: Empresa: | C4: 20037
B5: Vista: | C5: [832610] Notas - Arrendamientos - Información detallada a revelar
B6: Eje X: | C6: N/A
B7: Eje Y: | C7: N/A
B8: Eje Z: | C8: N/A
E10: Periodo Actual
B11: Información a revelar sobre arrendamientos [bloque de texto]
C12: Activos por derecho de uso que no cumplen la definición de propiedades de inversión
C13: Descripción de las partidas en el estado de situación financiera que incluyen activos por derecho de uso [texto]
C14: Pasivos por arrendamiento [resúmen]
D15: Pasivo por arrendamiento corriente
D16: Pasivo por arrendamientos no corrientes
D17: Total pasivos por arrendamientos | E17: =E15+E16
C18: Descripción de las partidas en el estado de situación financiera que incluyen pasivos por arrendamientos

Sheet Hoja32
B2: Indice
B3: Archivo: | C3: I:\Proyectos2025\proyecto_niif\_backup_legacy\Grupo1_Individual_Directo_ID20037_2024-12-31.xbrl
B4: Empresa: | C4: 20037
B5: Vista: | C5: [832900] Notas - Acuerdos de concesión de servicios públicos
B6: Eje X: | C6: N/A
B7: Eje Y: | C7: N/A
B8: Eje Z: | C8: N/A
E10: Periodo Actual
B11: Información a revelar sobre acuerdos de concesión de servicios [bloque de texto]
C12: Información a revelar detallada sobre acuerdos de concesión de servicios públicos [bloque de texto]
D13: Descripción del acuerdo de concesión de servicios
D14: Explicación de las condiciones significativas del acuerdo de concesión de servicios que pueden afectar al importe, calendario y certeza de los flujos de efectivo futuros
D15: Explicación de la naturaleza y alcance de derecho a utilizar activos específicos
D16: Explicación de la naturaleza y alcance de las obligaciones de proporcionar o derecho a esperar una prestación de servicios
D17: Explicación de la naturaleza y alcance de las obligaciones para adquirir o construir elementos de propiedades, planta y equipo
D18: Explicación de la naturaleza y alcance de las obligaciones de proporcionar o derechos a recibir activos especificados al final de periodo de concesión
D19: Explicación de la naturaleza y alcance de las opciones de renovación y terminación
D20: Explicación de la naturaleza y alcance de otros derechos y obligaciones
D21: Descripción de cambios en el acuerdo de concesión de servicios
D22: Explicación de la forma en que se ha clasificado un acuerdo de concesión de servicio público
D23: Ingresos de actividades ordinarias por servicios de construcción intercambiados por activos financieros
D24: Ingresos de actividades ordinarias por servicios de construcción intercambiados por activos intangibles
... D26: Ganancia (pérdida) reconocida por servicios de construcción intercambiados por activos intangibles

Sheet Hoja33
B2: Indice
B3: Archivo: | C3: I:\Proyectos2025\proyecto_niif\_backup_legacy\Grupo1_Individual_Directo_ID20037_2024-12-31.xbrl
B4: Empresa: | C4: 20037
B5: Vista: | C5: [834480] Notas - Beneficios a los empleados
B6: Eje X: | C6: N/A
B7: Eje Y: | C7: N/A
B8: Eje Z: | C8: N/A
E10: Periodo Actual
B11: Información a revelar sobre beneficios a los empleados [bloque de texto]
C12: Información a revelar sobre planes de beneficios definidos [bloque de texto]
D13: Información a revelar sobre pasivos (activos) por beneficios definidos netos [bloque de texto]

Sheet Hoja34
B2: Indice
B3: Archivo: | C3: I:\Proyectos2025\proyecto_niif\_backup_legacy\Grupo1_Individual_Directo_ID20037_2024-12-31.xbrl
B4: Empresa: | C4: 20037
B5: Vista: | C5: [835110] Notas - Impuestos a las ganancias
B6: Eje X: | C6: N/A
B7: Eje Y: | C7: N/A
B8: Eje Z: | C8: N/A
F10: Periodo Actual
B11: Información a revelar sobre impuestos a las ganancias [bloque de texto]
C12: Principales componentes del gasto (ingreso) por impuestos [resumen]
D13: Gasto (ingreso) por impuestos corriente y ajustes por impuestos corrientes de periodos anteriores [resumen]
E14: Gasto (ingreso) por impuesto corriente
E15: Ajustes por impuestos corrientes de periodos anteriores
E16: Total gastos (ingresos) por impuestos corrientes y ajustes a impuestos corrientes de periodos anteriores | F16: =F14+F15
D17: Gasto (ingreso) por impuestos diferidos relacionado con el nacimiento y reversión de diferencias temporarias
D18: Gasto (ingreso) por impuestos diferidos relacionado con cambios en las tasas fiscales o con la imposición de nuevos impuestos
D19: Beneficios de carácter fiscal, procedentes de pérdidas fiscales, créditos fiscales o diferencias temporarias no reconocidos en periodos anteriores utilizadas para reducir el gasto por impuestos del periodo corriente
D20: Beneficios de carácter fiscal, procedentes de pérdidas fiscales, créditos fiscales o diferencias temporarias no reconocidos en periodos anteriores utilizadas para reducir el gasto por impuestos diferido
D21: Gasto por impuestos diferidos surgido de la baja o la reversión de la baja de activos por impuestos diferidos
D22: Gasto (ingreso) por impuestos relacionado con cambios en políticas contables y errores incluidos en el resultado del periodo
D23: Ajustes por impuestos diferidos de periodos anteriores
D24: Otros componentes del gasto (ingreso) por impuestos diferido
D25: Total de gasto (ingreso) por impuestos | F25: =SUM(F16:F18)-F19-F20+SUM(F21:F24)
C26: Impuestos corrientes y diferidos, relativos a partidas cargadas o acreditadas directamente a patrimonio [resumen]
D27: Impuestos corrientes relacionados con partidas acreditadas (cargadas) directamente a patrimonio
D28: Impuestos diferidos relacionados con partidas acreditadas (cargadas) directamente a patrimonio
D29: Impuestos corrientes y diferidos acumulados relacionados con partidas acreditadas (cargadas) directamente a patrimonio | F29: =F27+F28
C30: Impuesto a las ganancias relacionado con otro resultado integral [resumen]
D31: Impuesto a las ganancias relacionado con diferencias de cambio en conversiones de negocios en el extranjero incluido en otro resultado integral | F31: =Hoja4!H82
D32: Impuesto a las ganancias relacionado con diferencias de cambio en conversiones distintas de las procedentes de negocios en el extranjero incluidos en otro resultado integral | F32: =Hoja4!H75
D33: Impuesto a las ganancias relacionado con coberturas de flujos de efectivo de otro resultado integral | F33: =Hoja4!H84
D34: Impuesto a las ganancias relativo a las variaciones de las superávit de revaluación de propiedades, planta y equipo, de los activos por derecho de uso y de los activos intangibles incluidos en otro resultado integral | F34: =Hoja4!H73
D35: Impuesto a las ganancias relativo a nuevas mediciones de planes de beneficios definidos de otro resultado integral | F35: =Hoja4!H74
D36: Impuesto a las ganancias relativos a inversiones en instrumentos de patrimonio de otro resultado integral | F36: =Hoja4!H72
D37: Impuesto a las ganancias relativos a coberturas de inversiones netas en negocios en el extranjero de otro resultado integral | F37: =Hoja4!H85
D38: Impuesto a las ganancias relacionado con cambios en el valor razonable de pasivos financieros atribuibles a cambios en el riesgo crediticio del pasivo de otro resultado integral | F38: =Hoja4!H76
D39: Impuesto a las ganancias relacionados con coberturas de inversiones en instrumentos de patrimonio de otro resultado integral | F39: =Hoja4!H77
D40: Impuesto a las ganancias relacionado con cambios en el valor temporal del dinero de opciones de otro resultado integral | F40: =Hoja4!H86
D41: Impuesto a las ganancias relacionado con ingresos (gastos) financieros por seguros de contratos de seguro emitidos incluido en otro resultado integral que se reclasificará al resultado del periodo | F41: =Hoja4!H90
D42: Impuesto a las ganancias relacionado con ingresos (gastos) financieros por seguros de contratos de seguro emitidos incluido en otro resultado integral que no se reclasificará al resultado del periodo | F42: =Hoja4!H78
D43: Impuesto a las ganancias relacionado con ingresos (gastos) financieros por contratos de reaseguro mantenidos incluido en otro resultado integral | F43: =Hoja4!H91
D44: Suma de impuestos a las ganancias relacionados con componentes de otro resultado integral | F44: =SUM(F31:F43)
C45: Impuesto a las ganancias relacionado con la participación en el otro resultado integral de asociadas y negocios conjuntos que se contabilicen mediante el método de la participación
C46: Gasto por impuestos de operaciones discontinuadas [resumen]
D47: Gasto por impuestos relacionado con ganancias (pérdidas) derivadas de la discontinuación
D48: Gasto por impuestos relacionado con ganancias (pérdidas) procedentes de actividades ordinarias de operaciones discontinuadas
C49: Explicación sobre cambios en tasas impositivas aplicables a periodos contables anteriores
C50: Descripción de la fecha de caducidad de las diferencias temporarias deducibles, pérdidas fiscales no utilizadas y créditos fiscales no utilizados
C51: Diferencias temporarias deducibles por las que no se reconoce activo por impuestos diferidos
C52: Pérdidas fiscales no utilizadas para las que no se han reconocido activos por impuestos diferidos
C53: Créditos fiscales no utilizados para los que no se han reconocido activos por impuestos diferidos
C54: Diferencias temporarias relacionadas con inversiones en subsidiarias, sucursales y asociadas, y con participaciones en acuerdos conjuntos, para los cuales no se han reconocido pasivos por impuestos diferidos
C55: Conciliación de la ganancia contable multiplicada por las tasas impositivas aplicables [resumen]
D56: Ganancia contable
D57: Total de gasto (ingreso) por impuestos a la tasa impositiva aplicable
D58: Efecto fiscal de ingresos de actividades ordinarias exentos de tributación
D59: Efecto fiscal de gastos no deducibles para la determinación de la ganancia (pérdida) tributable
D60: Efecto fiscal del deterioro del valor de la plusvalía
D61: Efecto fiscal de pérdidas fiscales
D62: Efecto fiscal de tasas impositivas soportadas en el extranjero
D63: Efecto fiscal procedente de cambios en las tasas impositivas
D64: Otros efectos fiscales por conciliación entre la ganancia contable y gasto por impuestos (ingreso)
D65: Total de gasto (ingreso) por impuestos | F65: =SUM(F16:F18)-F19-F20+SUM(F21:F24)
C66: Conciliación de la tasa impositiva media efectiva y la tasa impositiva aplicable [resumen]
D67: Ganancia contable | F67: =F56
D68: Tasa impositiva aplicable
D69: Efecto de la tasa impositiva de ingresos de actividades ordinarias exentos de tributación
D70: Efecto de la tasa impositiva de gastos no deducibles para la determinación de la ganancia (pérdida) tributable
D71: Efecto en la tasa impositiva del deterioro del valor de la plusvalía
D72: Efecto de la tasa impositiva de pérdidas fiscales
D73: Efecto de la tasa impositiva de tasas impositivas soportadas en el extranjero
D74: Efecto de la tasa impositiva procedente de cambios en la tasa impositiva
D75: Efecto de la tasa impositiva de ajustes a impuestos corrientes de periodos anteriores
D76: Otros efectos de la tasa impositiva por conciliación entre la ganancia contable y gasto por impuestos (ingreso)
D77: Total de tasa impositiva media efectiva

Sheet Hoja35
B2: Indice
B3: Archivo: | C3: I:\Proyectos2025\proyecto_niif\_backup_legacy\Grupo1_Individual_Directo_ID20037_2024-12-31.xbrl
B4: Empresa: | C4: 20037
B5: Vista: | C5: [836200] Notas - Costos por préstamos
B6: Eje X: | C6: N/A
B7: Eje Y: | C7: N/A
B8: Eje Z: | C8: N/A
E10: Periodo Actual
B11: Información a revelar sobre costos por préstamos [bloque de texto]
C12: Costos por préstamos [resumen]
D13: Costos por préstamos capitalizados
D14: Costos por préstamos reconocidos como gasto
D15: Total costos por préstamos incurridos | E15: =E13+E14
C16: Costos por intereses [resumen]
D17: Costos por intereses capitalizados
D18: Gastos por intereses
D19: Total costos por intereses incurridos | E19: =E17+E18
C20: Tasa de capitalización de costos por préstamos susceptibles de capitalización

Sheet Hoja36
B2: Indice
B3: Archivo: | C3: I:\Proyectos2025\proyecto_niif\_backup_legacy\Grupo1_Individual_Directo_ID20037_2024-12-31.xbrl
B4: Empresa: | C4: 20037
B5: Vista: | C5: [842000] Notas - Efectos de las variaciones en las tasas de cambio de la moneda extranjera
B6: Eje X: | C6: N/A
B7: Eje Y: | C7: N/A
B8: Eje Z: | C8: N/A
E10: Periodo Actual
B11: Información a revelar sobre el efecto de las variaciones en las tasas de cambio de la moneda extranjera [bloque de texto]
C12: Cuál es la moneda funcional
C13: Descripción de la moneda de presentación
C14: Descripción de la razón por la que la moneda de presentación es diferente de la moneda funcional
C15: Descripción de la razón para introducir cambios en la moneda funcional
C16: Descripción de la moneda en la que se facilita información complementaria
C17: Descripción de los métodos de conversión utilizados para determinar la información complementaria
C18: Ganancias (pérdidas) de cambio en moneda extranjera
C19: Ganancia neta por moneda extranjera
C20: Pérdida neta por moneda extranjera
C21: Reserva de diferencias de cambio por conversión
C22: Tasas de cambio de moneda extranjera [resumen]
D23: Tasa de cambio de moneda extranjera de cierre.
D24: Promedio de tasa de cambio de moneda extranjera

Sheet Hoja37
B2: Indice
B3: Archivo: | C3: I:\Proyectos2025\proyecto_niif\_backup_legacy\Grupo1_Individual_Directo_ID20037_2024-12-31.xbrl
B4: Empresa: | C4: 20037
B5: Vista: | C5: [900010] Notas - Información a revelar sobre los responsables de la información financiera e información del AEGR
B6: Eje X: | C6: N/A
B7: Eje Y: | C7: N/A
B8: Eje Z: | C8: Periodo Actual
D10: Detalle [resumen]
D11: Nombres | E11: Apellidos | F11: Tipo de documento | G11: Número de documento | H11: Email | I11: Tarjeta profesional | J11: Si la persona natural actua como miembro de una persona jurídica, indique la razón social | K11: Si la persona natural actua como miembro de una persona jurídica, indique el NIT | L11: Tipo de norma de auditoría aplicada y tipo de dictamen
B12: Relación [miembro]
C13: Representante legal [miembro]
C14: Contador [miembro]
C15: Jefe de la oficina de control interno [miembro]
C16: Revisor fiscal [miembro]
C17: AEGR [miembro]

Sheet Hoja38
B2: Indice
B3: Archivo: | C3: I:\Proyectos2025\proyecto_niif\_backup_legacy\Grupo1_Individual_Directo_ID20037_2024-12-31.xbrl
B4: Empresa: | C4: 20037
B5: Vista: | C5: [900017a] FC01-1 - Gastos de servicios públicos - Acueducto
B6: Eje X: | C6: N/A
B7: Eje Y: | C7: N/A
B8: Eje Z: | C8: Periodo Actual
E10: Acueducto [miembro]
E11: Gasto administrativo - Acueducto [miembro] | F11: Gasto operativo - Acueducto [miembro]
B12: Gastos [resumen]
C13: Beneficios a empleados
C14: Honorarios
C15: Impuestos, Tasas y Contribuciones (No incluye impuesto de renta)
C16: Generales
C17: Deterioro
C18: Depreciación
C19: Amortización
C20: Provisiones [resumen]
D21: Litigios y demandas
D22: Garantías
D23: Diversas
D24: Total gastos de provisiones | E24: =SUM(E21:E23) | F24: =SUM(F21:F23) | G24: =SUM(G21:G23)
C25: Arrendamientos
C26: Otros Gastos [resumen]
D27: Comisiones
D28: Ajuste por diferencia en cambio
D29: Financieros
D30: Pérdidas por aplicación del método de participación patrimonial
D31: Gastos diversos
D32: Donaciones
D33: Total otros gastos | E33: =SUM(E27:E32) | F33: =SUM(F27:F32) | G33: =SUM(G27:G32)
C34: Impuesto a las ganancias corrientes
C35: Impuesto a las ganancias diferido
C36: Bienes y servicios públicos para la venta [resumen]
D37: Compras en bloque y/o a largo plazo
D38: Compras en bolsa y/o a corto plazo
D39: Gastos por suministro de agua potable (agua en bloque)
D40: Gastos de conexión
D41: Uso de Líneas, redes y ductos
D42: Gastos de distribución y/o comercialización de gas combustible por redes
D43: Manejo comercial y financiero del servicio
D44: Gastos de distribución y/o comercialización de gas licuado de petróleo – GLP
D45: Contrato de explotación
D46: Gastos asociados a las transacciones en el mercado mayorista
D47: Contrato de concesión
D48: Otros gastos bienes y servicios públicos para la venta
D49: Gastos asociados a las transacciones en el mercado minorista
D50: Total de bienes y servicios públicos para la venta | E50: =SUM(E37:E49) | F50: =SUM(F37:F49) | G50: =SUM(G37:G49)
C51: Licencias, contribuciones y regalías [resumen]
D52: Secretaría Distrital del Medio Ambiente
D53: Ley 56 de 1981
D54: Medio Ambiente – Ley 99 de 1993
D55: Regalías
D56: Licencia De Operación Del Servicio
D57: FAZNI
D58: FAER
D59: Cuota de Fomento de gas
D60: Comité De Estratificación –Ley 505 De 1999
D61: Art 25 - Ley 142 - Concesiones, y permisos ambientales y sanitarios
D62: Otras licencias Ley 142 de 1994
D63: Total licencias, contribuciones y regalías | E63: =SUM(E52:E62) | F63: =SUM(F52:F62) | G63: =SUM(G52:G62)
C64: Consumo de Insumos Directos [resumen]
D65: Productos Químicos
D66: Gas Combustible
D67: Carbón Mineral
D68: Energía
D69: ACPM, Fuel Oil
D70: Otros Elementos de Consumo de Insumos Directos
D71: Total consumo de insumos directos | E71: =SUM(E65:E70) | F71: =SUM(F65:F70) | G71: =SUM(G65:G70)
C72: Ordenes y contratos de mantenimiento y reparaciones
C73: Peajes terrestres
C74: Disposición final
C75: Peajes por interconexión de acueductos
C76: Peajes por interconexión de alcantarillado
C77: Servicios públicos
C78: Materiales y otros gastos de operación
C79: Pérdidas en prestación del servicio de acueducto
C80: Seguros
C81: Órdenes y contratos por otros servicios
C82: Total gastos | E82: =SUM(E13:E19)+E24+E25+SUM(E33:E35)+E50+E63+SUM(E71:E81) | F82: =SUM(F13:F19)+F24+F25+SUM(F33:F35)+F50+F63+SUM(F71:F81) | G82: =SUM(G13:G19)+G24+G25+SUM(G33:G35)+G50+G63+SUM(G71:G81)

Sheet Hoja39
B2: Indice
B3: Archivo: | C3: I:\Proyectos2025\proyecto_niif\_backup_legacy\Grupo1_Individual_Directo_ID20037_2024-12-31.xbrl
B4: Empresa: | C4: 20037
B5: Vista: | C5: [900017b] FC01-2 - Gastos de servicios públicos - Alcantarillado
B6: Eje X: | C6: N/A
B7: Eje Y: | C7: N/A
B8: Eje Z: | C8: Periodo Actual
E10: Alcantarillado [miembro]
E11: Gasto administrativo - Alcantarillado [miembro] | F11: Gasto operativo - Alcantarillado [miembro]
B12: Gastos [resumen]
C13: Beneficios a empleados
C14: Honorarios
C15: Impuestos, Tasas y Contribuciones (No incluye impuesto de renta)
C16: Generales
C17: Deterioro
C18: Depreciación
C19: Amortización
C20: Provisiones [resumen]
D21: Litigios y demandas
D22: Garantías
D23: Diversas
D24: Total gastos de provisiones | E24: =SUM(E21:E23) | F24: =SUM(F21:F23) | G24: =SUM(G21:G23)
C25: Arrendamientos
C26: Otros Gastos [resumen]
D27: Comisiones
D28: Ajuste por diferencia en cambio
D29: Financieros
D30: Pérdidas por aplicación del método de participación patrimonial
D31: Gastos diversos
D32: Donaciones
D33: Total otros gastos | E33: =SUM(E27:E32) | F33: =SUM(F27:F32) | G33: =SUM(G27:G32)
C34: Impuesto a las ganancias corrientes
C35: Impuesto a las ganancias diferido
C36: Bienes y servicios públicos para la venta [resumen]
D37: Compras en bloque y/o a largo plazo
D38: Compras en bolsa y/o a corto plazo
D39: Gastos por suministro de agua potable (agua en bloque)
D40: Gastos de conexión
D41: Uso de Líneas, redes y ductos
D42: Gastos de distribución y/o comercialización de gas combustible por redes
D43: Manejo comercial y financiero del servicio
D44: Gastos de distribución y/o comercialización de gas licuado de petróleo – GLP
D45: Contrato de explotación
D46: Gastos asociados a las transacciones en el mercado mayorista
D47: Contrato de concesión
D48: Otros gastos bienes y servicios públicos para la venta
D49: Gastos asociados a las transacciones en el mercado minorista
D50: Total de bienes y servicios públicos para la venta | E50: =SUM(E37:E49) | F50: =SUM(F37:F49) | G50: =SUM(G37:G49)
C51: Licencias, contribuciones y regalías [resumen]
D52: Secretaría Distrital del Medio Ambiente
D53: Ley 56 de 1981
D54: Medio Ambiente – Ley 99 de 1993
D55: Regalías
D56: Licencia De Operación Del Servicio
D57: FAZNI
D58: FAER
D59: Cuota de Fomento de gas
D60: Comité De Estratificación –Ley 505 De 1999
D61: Art 25 - Ley 142 - Concesiones, y permisos ambientales y sanitarios
D62: Otras licencias Ley 142 de 1994
D63: Total licencias, contribuciones y regalías | E63: =SUM(E52:E62) | F63: =SUM(F52:F62) | G63: =SUM(G52:G62)
C64: Consumo de Insumos Directos [resumen]
D65: Productos Químicos
D66: Gas Combustible
D67: Carbón Mineral
D68: Energía
D69: ACPM, Fuel Oil
D70: Otros Elementos de Consumo de Insumos Directos
D71: Total consumo de insumos directos | E71: =SUM(E65:E70) | F71: =SUM(F65:F70) | G71: =SUM(G65:G70)
C72: Ordenes y contratos de mantenimiento y reparaciones
C73: Peajes terrestres
C74: Disposición final
C75: Peajes por interconexión de acueductos
C76: Peajes por interconexión de alcantarillado
C77: Servicios públicos
C78: Materiales y otros gastos de operación
C79: Pérdidas en prestación del servicio de acueducto
C80: Seguros
C81: Órdenes y contratos por otros servicios
C82: Total gastos | E82: =SUM(E13:E19)+E24+E25+SUM(E33:E35)+E50+E63+SUM(E71:E81) | F82: =SUM(F13:F19)+F24+F25+SUM(F33:F35)+F50+F63+SUM(F71:F81) | G82: =SUM(G13:G19)+G24+G25+SUM(G33:G35)+G50+G63+SUM(G71:G81)

Sheet Hoja40
B2: Indice
B3: Archivo: | C3: I:\Proyectos2025\proyecto_niif\_backup_legacy\Grupo1_Individual_Directo_ID20037_2024-12-31.xbrl
B4: Empresa: | C4: 20037
B5: Vista: | C5: [900017c] FC01-3 - Gastos de servicios públicos - Aseo
B6: Eje X: | C6: N/A
B7: Eje Y: | C7: N/A
B8: Eje Z: | C8: Periodo Actual
E10: Aseo [miembro]
E11: Gasto administrativo - Aseo [miembro] | F11: Gasto operativo - Aseo [miembro]
B12: Gastos [resumen]
C13: Beneficios a empleados
C14: Honorarios
C15: Impuestos, Tasas y Contribuciones (No incluye impuesto de renta)
C16: Generales
C17: Deterioro
C18: Depreciación
C19: Amortización
C20: Provisiones [resumen]
D21: Litigios y demandas
D22: Garantías
D23: Diversas
D24: Total gastos de provisiones | E24: =SUM(E21:E23) | F24: =SUM(F21:F23) | G24: =SUM(G21:G23)
C25: Arrendamientos
C26: Otros Gastos [resumen]
D27: Comisiones
D28: Ajuste por diferencia en cambio
D29: Financieros
D30: Pérdidas por aplicación del método de participación patrimonial
D31: Gastos diversos
D32: Donaciones
D33: Total otros gastos | E33: =SUM(E27:E32) | F33: =SUM(F27:F32) | G33: =SUM(G27:G32)
C34: Impuesto a las ganancias corrientes
C35: Impuesto a las ganancias diferido
C36: Bienes y servicios públicos para la venta [resumen]
D37: Compras en bloque y/o a largo plazo
D38: Compras en bolsa y/o a corto plazo
D39: Gastos por suministro de agua potable (agua en bloque)
D40: Gastos de conexión
D41: Uso de Líneas, redes y ductos
D42: Gastos de distribución y/o comercialización de gas combustible por redes
D43: Manejo comercial y financiero del servicio
D44: Gastos de distribución y/o comercialización de gas licuado de petróleo – GLP
D45: Contrato de explotación
D46: Gastos asociados a las transacciones en el mercado mayorista
D47: Contrato de concesión
D48: Otros gastos bienes y servicios públicos para la venta
D49: Gastos asociados a las transacciones en el mercado minorista
D50: Total de bienes y servicios públicos para la venta | E50: =SUM(E37:E49) | F50: =SUM(F37:F49) | G50: =SUM(G37:G49)
C51: Licencias, contribuciones y regalías [resumen]
D52: Secretaría Distrital del Medio Ambiente
D53: Ley 56 de 1981
D54: Medio Ambiente – Ley 99 de 1993
D55: Regalías
D56: Licencia De Operación Del Servicio
D57: FAZNI
D58: FAER
D59: Cuota de Fomento de gas
D60: Comité De Estratificación –Ley 505 De 1999
D61: Art 25 - Ley 142 - Concesiones, y permisos ambientales y sanitarios
D62: Otras licencias Ley 142 de 1994
D63: Total licencias, contribuciones y regalías | E63: =SUM(E52:E62) | F63: =SUM(F52:F62) | G63: =SUM(G52:G62)
C64: Consumo de Insumos Directos [resumen]
D65: Productos Químicos
D66: Gas Combustible
D67: Carbón Mineral
D68: Energía
D69: ACPM, Fuel Oil
D70: Otros Elementos de Consumo de Insumos Directos
D71: Total consumo de insumos directos | E71: =SUM(E65:E70) | F71: =SUM(F65:F70) | G71: =SUM(G65:G70)
C72: Ordenes y contratos de mantenimiento y reparaciones
C73: Peajes terrestres
C74: Disposición final
C75: Peajes por interconexión de acueductos
C76: Peajes por interconexión de alcantarillado
C77: Servicios públicos
C78: Materiales y otros gastos de operación
C79: Pérdidas en prestación del servicio de acueducto
C80: Seguros
C81: Órdenes y contratos por otros servicios
C82: Total gastos | E82: =SUM(E13:E19)+E24+E25+SUM(E33:E35)+E50+E63+SUM(E71:E81) | F82: =SUM(F13:F19)+F24+F25+SUM(F33:F35)+F50+F63+SUM(F71:F81) | G82: =SUM(G13:G19)+G24+G25+SUM(G33:G35)+G50+G63+SUM(G71:G81)

Sheet Hoja41
B2: Indice
B3: Archivo: | C3: I:\Proyectos2025\proyecto_niif\_backup_legacy\Grupo1_Individual_Directo_ID20037_2024-12-31.xbrl
B4: Empresa: | C4: 20037
B5: Vista: | C5: [900017d] FC01-4 - Gastos de servicios públicos - Energía
B6: Eje X: | C6: N/A
B7: Eje Y: | C7: N/A
B8: Eje Z: | C8: Periodo Actual
E10: Energía Eléctrica [miembro]
E11: ENERGIA - SIN [miembro] | T11: ENERGIA - ZNI [miembro] | AF11: Gasto administrativo - Energía eléctrica [miembro] | AG11: Gasto operativo - Energía Eléctrica [miembro]
E12: Generación [miembro] | H12: Transmisión [miembro] | K12: Distribución [miembro] | N12: Comercialización [miembro] | Q12: Gasto administrativo - Energía Eléctrica SIN [miembro] | R12: Gasto operativo - Energía Eléctrica SIN [miembro] | T12: Generación [miembro] | W12: Distribución [miembro] | Z12: Comercialización [miembro] | AC12: Gasto administrativo - Energía Eléctrica ZNI [miembro] | AD12: Gasto operativo - Energía Eléctrica ZNI [miembro]
E13: Gasto administrativo - Energía Eléctrica SIN - Generación [miembro] | F13: Gasto operativo - Energía Eléctrica SIN - Generación [miembro] | H13: Gasto administrativo - Energía Eléctrica SIN - Transmisión [miembro] | I13: Gasto operativo - Energía Eléctrica SIN - Transmisión [miembro] | K13: Gasto administrativo - Energía Eléctrica SIN - Distribución [miembro] | L13: Gasto operativo - Energía Eléctrica SIN - Distribución [miembro] | N13: Gasto administrativo - Energía Eléctrica SIN - Comercialización [miembro] | O13: Gasto operativo - Energía Eléctrica SIN - Comercialización [miembro] | T13: Gasto administrativo - Energía Eléctrica ZNI - Generación [miembro] | U13: Gasto operativo - Energía Eléctrica ZNI - Generación [miembro] | W13: Gasto administrativo - Energía Eléctrica ZNI - Distribución [miembro] | X13: Gasto operativo - Energía Eléctrica ZNI - Distribución [miembro] | Z13: Gasto administrativo - Energía Eléctrica ZNI - Comercialización [miembro] | AA13: Gasto operativo - Energía Eléctrica ZNI - Comercialización [miembro]
B14: Gastos [resumen]
C15: Beneficios a empleados
C16: Honorarios
C17: Impuestos, Tasas y Contribuciones (No incluye impuesto de renta)
C18: Generales
C19: Deterioro
C20: Depreciación
C21: Amortización
C22: Provisiones [resumen]
D23: Litigios y demandas
D24: Garantías
D25: Diversas
D26: Total gastos de provisiones | E26: =SUM(E23:E25) | F26: =SUM(F23:F25) | G26: =SUM(G23:G25) | H26: =SUM(H23:H25) | I26: =SUM(I23:I25) | J26: =SUM(J23:J25) | K26: =SUM(K23:K25) | L26: =SUM(L23:L25) | ... AH26: =SUM(AH23:AH25)
C27: Arrendamientos
C28: Otros Gastos [resumen]
D29: Comisiones
D30: Ajuste por diferencia en cambio
D31: Financieros
D32: Pérdidas por aplicación del método de participación patrimonial
D33: Gastos diversos
D34: Donaciones
D35: Total otros gastos | E35: =SUM(E29:E34) | F35: =SUM(F29:F34) | G35: =SUM(G29:G34) | H35: =SUM(H29:H34) | I35: =SUM(I29:I34) | J35: =SUM(J29:J34) | K35: =SUM(K29:K34) | L35: =SUM(L29:L34) | ... AH35: =SUM(AH29:AH34)
C36: Impuesto a las ganancias corrientes
C37: Impuesto a las ganancias diferido
C38: Bienes y servicios públicos para la venta [resumen]
D39: Compras en bloque y/o a largo plazo
D40: Compras en bolsa y/o a corto plazo
D41: Gastos por suministro de agua potable (agua en bloque)
D42: Gastos de conexión
D43: Uso de Líneas, redes y ductos
D44: Gastos de distribución y/o comercialización de gas combustible por redes
D45: Manejo comercial y financiero del servicio
D46: Gastos de distribución y/o comercialización de gas licuado de petróleo – GLP
D47: Contrato de explotación
D48: Gastos asociados a las transacciones en el mercado mayorista
D49: Contrato de concesión
D50: Otros gastos bienes y servicios públicos para la venta
D51: Gastos asociados a las transacciones en el mercado minorista
D52: Total de bienes y servicios públicos para la venta | E52: =SUM(E39:E51) | F52: =SUM(F39:F51) | G52: =SUM(G39:G51) | H52: =SUM(H39:H51) | I52: =SUM(I39:I51) | J52: =SUM(J39:J51) | K52: =SUM(K39:K51) | L52: =SUM(L39:L51) | ... AH52: =SUM(AH39:AH51)
C53: Licencias, contribuciones y regalías [resumen]
D54: Secretaría Distrital del Medio Ambiente
D55: Ley 56 de 1981
D56: Medio Ambiente – Ley 99 de 1993
D57: Regalías
D58: Licencia De Operación Del Servicio
D59: FAZNI
D60: FAER
D61: Cuota de Fomento de gas
D62: Comité De Estratificación –Ley 505 De 1999
D63: Art 25 - Ley 142 - Concesiones, y permisos ambientales y sanitarios
D64: Otras licencias Ley 142 de 1994
D65: Total licencias, contribuciones y regalías | E65: =SUM(E54:E64) | F65: =SUM(F54:F64) | G65: =SUM(G54:G64) | H65: =SUM(H54:H64) | I65: =SUM(I54:I64) | J65: =SUM(J54:J64) | K65: =SUM(K54:K64) | L65: =SUM(L54:L64) | ... AH65: =SUM(AH54:AH64)
C66: Consumo de Insumos Directos [resumen]
D67: Productos Químicos
D68: Gas Combustible
D69: Carbón Mineral
D70: Energía
D71: ACPM, Fuel Oil
D72: Otros Elementos de Consumo de Insumos Directos
D73: Total consumo de insumos directos | E73: =SUM(E67:E72) | F73: =SUM(F67:F72) | G73: =SUM(G67:G72) | H73: =SUM(H67:H72) | I73: =SUM(I67:I72) | J73: =SUM(J67:J72) | K73: =SUM(K67:K72) | L73: =SUM(L67:L72) | ... AH73: =SUM(AH67:AH72)
C74: Ordenes y contratos de mantenimiento y reparaciones
C75: Peajes terrestres
C76: Disposición final
C77: Peajes por interconexión de acueductos
C78: Peajes por interconexión de alcantarillado
C79: Servicios públicos
C80: Materiales y otros gastos de operación
C81: Pérdidas en prestación del servicio de acueducto
C82: Seguros
C83: Órdenes y contratos por otros servicios
C84: Total gastos | E84: =SUM(E15:E21)+E26+E27+SUM(E35:E37)+E52+E65+SUM(E73:E83) | F84: =SUM(F15:F21)+F26+F27+SUM(F35:F37)+F52+F65+SUM(F73:F83) | G84: =SUM(G15:G21)+G26+G27+SUM(G35:G37)+G52+G65+SUM(G73:G83) | H84: =SUM(H15:H21)+H26+H27+SUM(H35:H37)+H52+H65+SUM(H73:H83) | I84: =SUM(I15:I21)+I26+I27+SUM(I35:I37)+I52+I65+SUM(I73:I83) | J84: =SUM(J15:J21)+J26+J27+SUM(J35:J37)+J52+J65+SUM(J73:J83) | K84: =SUM(K15:K21)+K26+K27+SUM(K35:K37)+K52+K65+SUM(K73:K83) | L84: =SUM(L15:L21)+L26+L27+SUM(L35:L37)+L52+L65+SUM(L73:L83) | ... AH84: =SUM(AH15:AH21)+AH26+AH27+SUM(AH35:AH37)+AH52+AH65+SUM(AH73:AH83)

Sheet Hoja42
B2: Indice
B3: Archivo: | C3: I:\Proyectos2025\proyecto_niif\_backup_legacy\Grupo1_Individual_Directo_ID20037_2024-12-31.xbrl
B4: Empresa: | C4: 20037
B5: Vista: | C5: [900017e] FC01-5 - Gastos de servicios públicos - Gas combustible por redes
B6: Eje X: | C6: N/A
B7: Eje Y: | C7: N/A
B8: Eje Z: | C8: Periodo Actual
E10: Gas combustible por redes [miembro]
E11: Producción, comercialización [miembro] | H11: Transporte [miembro] | K11: Distribución [miembro] | N11: Comercialización [miembro] | Q11: Comercialización de gas importado [miembro] | T11: Regasificación [miembro] | W11: Gasto administrativo - Gas Combustible por redes [miembro] | X11: Gasto operativo - Gas Combustible por redes [miembro]
E12: Gasto administrativo - Gas Combustible por redes - Producción [miembro] | F12: Gasto operativo - Gas Combustible por redes - Producción [miembro] | H12: Gasto administrativo - Gas Combustible por redes - Transporte [miembro] | I12: Gasto operativo - Gas Combustible por redes - Transporte [miembro] | K12: Gasto administrativo - Gas Combustible por redes - Distribución [miembro] | L12: Gasto operativo - Gas Combustible por redes - Distribución [miembro] | N12: Gasto administrativo - Gas Combustible por redes - Comercialización [miembro] | O12: Gasto operativo - Gas Combustible por redes - Comercialización [miembro] | Q12: Gasto administrativo - Gas Combustible por redes - Comercialización de gas importado [miembro] | R12: Gasto operativo - Gas Combustible por redes - Comercialización de gas importado[miembro] | T12: Gasto administrativo - Gas Combustible por redes - Regasificación [miembro] | U12: Gasto operativo - Gas Combustible por redes - Regasificación [miembro]
B13: Gastos [resumen]
C14: Beneficios a empleados
C15: Honorarios
C16: Impuestos, Tasas y Contribuciones (No incluye impuesto de renta)
C17: Generales
C18: Deterioro
C19: Depreciación
C20: Amortización
C21: Provisiones [resumen]
D22: Litigios y demandas
D23: Garantías
D24: Diversas
D25: Total gastos de provisiones | E25: =SUM(E22:E24) | F25: =SUM(F22:F24) | G25: =SUM(G22:G24) | H25: =SUM(H22:H24) | I25: =SUM(I22:I24) | J25: =SUM(J22:J24) | K25: =SUM(K22:K24) | L25: =SUM(L22:L24) | ... Y25: =SUM(Y22:Y24)
C26: Arrendamientos
C27: Otros Gastos [resumen]
D28: Comisiones
D29: Ajuste por diferencia en cambio
D30: Financieros
D31: Pérdidas por aplicación del método de participación patrimonial
D32: Gastos diversos
D33: Donaciones
D34: Total otros gastos | E34: =SUM(E28:E33) | F34: =SUM(F28:F33) | G34: =SUM(G28:G33) | H34: =SUM(H28:H33) | I34: =SUM(I28:I33) | J34: =SUM(J28:J33) | K34: =SUM(K28:K33) | L34: =SUM(L28:L33) | ... Y34: =SUM(Y28:Y33)
C35: Impuesto a las ganancias corrientes
C36: Impuesto a las ganancias diferido
C37: Bienes y servicios públicos para la venta [resumen]
D38: Compras en bloque y/o a largo plazo
D39: Compras en bolsa y/o a corto plazo
D40: Gastos por suministro de agua potable (agua en bloque)
D41: Gastos de conexión
D42: Uso de Líneas, redes y ductos
D43: Gastos de distribución y/o comercialización de gas combustible por redes
D44: Manejo comercial y financiero del servicio
D45: Gastos de distribución y/o comercialización de gas licuado de petróleo – GLP
D46: Contrato de explotación
D47: Gastos asociados a las transacciones en el mercado mayorista
D48: Contrato de concesión
D49: Otros gastos bienes y servicios públicos para la venta
D50: Gastos asociados a las transacciones en el mercado minorista
D51: Total de bienes y servicios públicos para la venta | E51: =SUM(E38:E50) | F51: =SUM(F38:F50) | G51: =SUM(G38:G50) | H51: =SUM(H38:H50) | I51: =SUM(I38:I50) | J51: =SUM(J38:J50) | K51: =SUM(K38:K50) | L51: =SUM(L38:L50) | ... Y51: =SUM(Y38:Y50)
C52: Licencias, contribuciones y regalías [resumen]
D53: Secretaría Distrital del Medio Ambiente
D54: Ley 56 de 1981
D55: Medio Ambiente – Ley 99 de 1993
D56: Regalías
D57: Licencia De Operación Del Servicio
D58: FAZNI
D59: FAER
D60: Cuota de Fomento de gas
D61: Comité De Estratificación –Ley 505 De 1999
D62: Art 25 - Ley 142 - Concesiones, y permisos ambientales y sanitarios
D63: Otras licencias Ley 142 de 1994
D64: Total licencias, contribuciones y regalías | E64: =SUM(E53:E63) | F64: =SUM(F53:F63) | G64: =SUM(G53:G63) | H64: =SUM(H53:H63) | I64: =SUM(I53:I63) | J64: =SUM(J53:J63) | K64: =SUM(K53:K63) | L64: =SUM(L53:L63) | ... Y64: =SUM(Y53:Y63)
C65: Consumo de Insumos Directos [resumen]
D66: Productos Químicos
D67: Gas Combustible
D68: Carbón Mineral
D69: Energía
D70: ACPM, Fuel Oil
D71: Otros Elementos de Consumo de Insumos Directos
D72: Total consumo de insumos directos | E72: =SUM(E66:E71) | F72: =SUM(F66:F71) | G72: =SUM(G66:G71) | H72: =SUM(H66:H71) | I72: =SUM(I66:I71) | J72: =SUM(J66:J71) | K72: =SUM(K66:K71) | L72: =SUM(L66:L71) | ... Y72: =SUM(Y66:Y71)
C73: Ordenes y contratos de mantenimiento y reparaciones
C74: Peajes terrestres
C75: Disposición final
C76: Peajes por interconexión de acueductos
C77: Peajes por interconexión de alcantarillado
C78: Servicios públicos
C79: Materiales y otros gastos de operación
C80: Pérdidas en prestación del servicio de acueducto
C81: Seguros
C82: Órdenes y contratos por otros servicios
C83: Total gastos | E83: =SUM(E14:E20)+E25+E26+SUM(E34:E36)+E51+E64+SUM(E72:E82) | F83: =SUM(F14:F20)+F25+F26+SUM(F34:F36)+F51+F64+SUM(F72:F82) | G83: =SUM(G14:G20)+G25+G26+SUM(G34:G36)+G51+G64+SUM(G72:G82) | H83: =SUM(H14:H20)+H25+H26+SUM(H34:H36)+H51+H64+SUM(H72:H82) | I83: =SUM(I14:I20)+I25+I26+SUM(I34:I36)+I51+I64+SUM(I72:I82) | J83: =SUM(J14:J20)+J25+J26+SUM(J34:J36)+J51+J64+SUM(J72:J82) | K83: =SUM(K14:K20)+K25+K26+SUM(K34:K36)+K51+K64+SUM(K72:K82) | L83: =SUM(L14:L20)+L25+L26+SUM(L34:L36)+L51+L64+SUM(L72:L82) | ... Y83: =SUM(Y14:Y20)+Y25+Y26+SUM(Y34:Y36)+Y51+Y64+SUM(Y72:Y82)

Sheet Hoja43
B2: Indice
B3: Archivo: | C3: I:\Proyectos2025\proyecto_niif\_backup_legacy\Grupo1_Individual_Directo_ID20037_2024-12-31.xbrl
B4: Empresa: | C4: 20037
B5: Vista: | C5: [900017f] FC01-6 - Gastos de servicios públicos - Gas licuado del petroleo
B6: Eje X: | C6: N/A
B7: Eje Y: | C7: N/A
B8: Eje Z: | C8: Periodo Actual
E10: Gas Licuado de Petróleo [miembro]
E11: Comercialización Mayorista [miembro] | H11: Distribución Inversionista [miembro] | K11: Comercialización Minorista [miembro] | N11: Transporte [miembro] | Q11: Gasto administrativo - GLP [miembro] | R11: Gasto operativo - GLP [miembro]
E12: Gasto administrativo - GLP - Comercialización mayorista [miembro] | F12: Gasto operativo - GLP - Comercialización mayorista [miembro] | H12: Gasto administrativo - GLP - Distribución inversionista [miembro] | I12: Gasto operativo - GLP - Distribución inversionista [miembro] | K12: Gasto administrativo - GLP - Comercialización minorista [miembro] | L12: Gasto operativo - GLP - Comercialización minorista [miembro] | N12: Gasto administrativo - GLP - Transporte [miembro] | O12: Gasto operativo - GLP - Transporte [miembro]
B13: Gastos [resumen]
C14: Beneficios a empleados
C15: Honorarios
C16: Impuestos, Tasas y Contribuciones (No incluye impuesto de renta)
C17: Generales
C18: Deterioro
C19: Depreciación
C20: Amortización
C21: Provisiones [resumen]
D22: Litigios y demandas
D23: Garantías
D24: Diversas
D25: Total gastos de provisiones | E25: =SUM(E22:E24) | F25: =SUM(F22:F24) | G25: =SUM(G22:G24) | H25: =SUM(H22:H24) | I25: =SUM(I22:I24) | J25: =SUM(J22:J24) | K25: =SUM(K22:K24) | L25: =SUM(L22:L24) | ... S25: =SUM(S22:S24)
C26: Arrendamientos
C27: Otros Gastos [resumen]
D28: Comisiones
D29: Ajuste por diferencia en cambio
D30: Financieros
D31: Pérdidas por aplicación del método de participación patrimonial
D32: Gastos diversos
D33: Donaciones
D34: Total otros gastos | E34: =SUM(E28:E33) | F34: =SUM(F28:F33) | G34: =SUM(G28:G33) | H34: =SUM(H28:H33) | I34: =SUM(I28:I33) | J34: =SUM(J28:J33) | K34: =SUM(K28:K33) | L34: =SUM(L28:L33) | ... S34: =SUM(S28:S33)
C35: Impuesto a las ganancias corrientes
C36: Impuesto a las ganancias diferido
C37: Bienes y servicios públicos para la venta [resumen]
D38: Compras en bloque y/o a largo plazo
D39: Compras en bolsa y/o a corto plazo
D40: Gastos por suministro de agua potable (agua en bloque)
D41: Gastos de conexión
D42: Uso de Líneas, redes y ductos
D43: Gastos de distribución y/o comercialización de gas combustible por redes
D44: Manejo comercial y financiero del servicio
D45: Gastos de distribución y/o comercialización de gas licuado de petróleo – GLP
D46: Contrato de explotación
D47: Gastos asociados a las transacciones en el mercado mayorista
D48: Contrato de concesión
D49: Otros gastos bienes y servicios públicos para la venta
D50: Gastos asociados a las transacciones en el mercado minorista
D51: Total de bienes y servicios públicos para la venta | E51: =SUM(E38:E50) | F51: =SUM(F38:F50) | G51: =SUM(G38:G50) | H51: =SUM(H38:H50) | I51: =SUM(I38:I50) | J51: =SUM(J38:J50) | K51: =SUM(K38:K50) | L51: =SUM(L38:L50) | ... S51: =SUM(S38:S50)
C52: Licencias, contribuciones y regalías [resumen]
D53: Secretaría Distrital del Medio Ambiente
D54: Ley 56 de 1981
D55: Medio Ambiente – Ley 99 de 1993
D56: Regalías
D57: Licencia De Operación Del Servicio
D58: FAZNI
D59: FAER
D60: Cuota de Fomento de gas
D61: Comité De Estratificación –Ley 505 De 1999
D62: Art 25 - Ley 142 - Concesiones, y permisos ambientales y sanitarios
D63: Otras licencias Ley 142 de 1994
D64: Total licencias, contribuciones y regalías | E64: =SUM(E53:E63) | F64: =SUM(F53:F63) | G64: =SUM(G53:G63) | H64: =SUM(H53:H63) | I64: =SUM(I53:I63) | J64: =SUM(J53:J63) | K64: =SUM(K53:K63) | L64: =SUM(L53:L63) | ... S64: =SUM(S53:S63)
C65: Consumo de Insumos Directos [resumen]
D66: Productos Químicos
D67: Gas Combustible
D68: Carbón Mineral
D69: Energía
D70: ACPM, Fuel Oil
D71: Otros Elementos de Consumo de Insumos Directos
D72: Total consumo de insumos directos | E72: =SUM(E66:E71) | F72: =SUM(F66:F71) | G72: =SUM(G66:G71) | H72: =SUM(H66:H71) | I72: =SUM(I66:I71) | J72: =SUM(J66:J71) | K72: =SUM(K66:K71) | L72: =SUM(L66:L71) | ... S72: =SUM(S66:S71)
C73: Ordenes y contratos de mantenimiento y reparaciones
C74: Peajes terrestres
C75: Disposición final
C76: Peajes por interconexión de acueductos
C77: Peajes por interconexión de alcantarillado
C78: Servicios públicos
C79: Materiales y otros gastos de operación
C80: Pérdidas en prestación del servicio de acueducto
C81: Seguros
C82: Órdenes y contratos por otros servicios
C83: Total gastos | E83: =SUM(E14:E20)+E25+E26+SUM(E34:E36)+E51+E64+SUM(E72:E82) | F83: =SUM(F14:F20)+F25+F26+SUM(F34:F36)+F51+F64+SUM(F72:F82) | G83: =SUM(G14:G20)+G25+G26+SUM(G34:G36)+G51+G64+SUM(G72:G82) | H83: =SUM(H14:H20)+H25+H26+SUM(H34:H36)+H51+H64+SUM(H72:H82) | I83: =SUM(I14:I20)+I25+I26+SUM(I34:I36)+I51+I64+SUM(I72:I82) | J83: =SUM(J14:J20)+J25+J26+SUM(J34:J36)+J51+J64+SUM(J72:J82) | K83: =SUM(K14:K20)+K25+K26+SUM(K34:K36)+K51+K64+SUM(K72:K82) | L83: =SUM(L14:L20)+L25+L26+SUM(L34:L36)+L51+L64+SUM(L72:L82) | ... S83: =SUM(S14:S20)+S25+S26+SUM(S34:S36)+S51+S64+SUM(S72:S82)

Sheet Hoja44
B2: Indice
B3: Archivo: | C3: I:\Proyectos2025\proyecto_niif\_backup_legacy\Grupo1_Individual_Directo_ID20037_2024-12-31.xbrl
B4: Empresa: | C4: 20037
B5: Vista: | C5: [900017g] FC01-7 - Gastos de servicios públicos - Total servicios públicos y actividades no vigiladas
B6: Eje X: | C6: N/A
B7: Eje Y: | C7: N/A
B8: Eje Z: | C8: Periodo Actual
E10: Total Periodo [miembro]
E11: Total prestación servicios públicos nacionales [miembro] | H11: Operador del sistema y Administrador del mercado de energia (XM) [miembro] | K11: Otras actividades no vigiladas por la SSPD [miembro] | N11: Gasto administrativo - Total del periodo [miembro] | O11: Gasto operativo - Total del periodo [miembro]
E12: Gasto administrativo - Total de servicios públicos [miembro] | F12: Gasto operativo - Total de servicios públicos [miembro] | H12: Gasto administrativo - XM [miembro] | I12: Gasto operativo - XM [miembro] | K12: Gasto administrativo - Otras actividades no vigiladas [miembro] | L12: Gasto operativo - Otras actividades no vigiladas [miembro]
B13: Gastos [resumen]
C14: Beneficios a empleados
C15: Honorarios
C16: Impuestos, Tasas y Contribuciones (No incluye impuesto de renta)
C17: Generales
C18: Deterioro
C19: Depreciación
C20: Amortización
C21: Provisiones [resumen]
D22: Litigios y demandas
D23: Garantías
D24: Diversas
D25: Total gastos de provisiones | E25: =SUM(E22:E24) | F25: =SUM(F22:F24) | G25: =SUM(G22:G24) | H25: =SUM(H22:H24) | I25: =SUM(I22:I24) | J25: =SUM(J22:J24) | K25: =SUM(K22:K24) | L25: =SUM(L22:L24) | ... P25: =SUM(P22:P24)
C26: Arrendamientos
C27: Otros Gastos [resumen]
D28: Comisiones
D29: Ajuste por diferencia en cambio
D30: Financieros
D31: Pérdidas por aplicación del método de participación patrimonial
D32: Gastos diversos
D33: Donaciones
D34: Total otros gastos | E34: =SUM(E28:E33) | F34: =SUM(F28:F33) | G34: =SUM(G28:G33) | H34: =SUM(H28:H33) | I34: =SUM(I28:I33) | J34: =SUM(J28:J33) | K34: =SUM(K28:K33) | L34: =SUM(L28:L33) | ... P34: =SUM(P28:P33)
C35: Impuesto a las ganancias corrientes
C36: Impuesto a las ganancias diferido
C37: Bienes y servicios públicos para la venta [resumen]
D38: Compras en bloque y/o a largo plazo
D39: Compras en bolsa y/o a corto plazo
D40: Gastos por suministro de agua potable (agua en bloque)
D41: Gastos de conexión
D42: Uso de Líneas, redes y ductos
D43: Gastos de distribución y/o comercialización de gas combustible por redes
D44: Manejo comercial y financiero del servicio
D45: Gastos de distribución y/o comercialización de gas licuado de petróleo – GLP
D46: Contrato de explotación
D47: Gastos asociados a las transacciones en el mercado mayorista
D48: Contrato de concesión
D49: Otros gastos bienes y servicios públicos para la venta
D50: Gastos asociados a las transacciones en el mercado minorista
D51: Total de bienes y servicios públicos para la venta | E51: =SUM(E38:E50) | F51: =SUM(F38:F50) | G51: =SUM(G38:G50) | H51: =SUM(H38:H50) | I51: =SUM(I38:I50) | J51: =SUM(J38:J50) | K51: =SUM(K38:K50) | L51: =SUM(L38:L50) | ... P51: =SUM(P38:P50)
C52: Licencias, contribuciones y regalías [resumen]
D53: Secretaría Distrital del Medio Ambiente
D54: Ley 56 de 1981
D55: Medio Ambiente – Ley 99 de 1993
D56: Regalías
D57: Licencia De Operación Del Servicio
D58: FAZNI
D59: FAER
D60: Cuota de Fomento de gas
D61: Comité De Estratificación –Ley 505 De 1999
D62: Art 25 - Ley 142 - Concesiones, y permisos ambientales y sanitarios
D63: Otras licencias Ley 142 de 1994
D64: Total licencias, contribuciones y regalías | E64: =SUM(E53:E63) | F64: =SUM(F53:F63) | G64: =SUM(G53:G63) | H64: =SUM(H53:H63) | I64: =SUM(I53:I63) | J64: =SUM(J53:J63) | K64: =SUM(K53:K63) | L64: =SUM(L53:L63) | ... P64: =SUM(P53:P63)
C65: Consumo de Insumos Directos [resumen]
D66: Productos Químicos
D67: Gas Combustible
D68: Carbón Mineral
D69: Energía
D70: ACPM, Fuel Oil
D71: Otros Elementos de Consumo de Insumos Directos
D72: Total consumo de insumos directos | E72: =SUM(E66:E71) | F72: =SUM(F66:F71) | G72: =SUM(G66:G71) | H72: =SUM(H66:H71) | I72: =SUM(I66:I71) | J72: =SUM(J66:J71) | K72: =SUM(K66:K71) | L72: =SUM(L66:L71) | ... P72: =SUM(P66:P71)
C73: Ordenes y contratos de mantenimiento y reparaciones
C74: Peajes terrestres
C75: Disposición final
C76: Peajes por interconexión de acueductos
C77: Peajes por interconexión de alcantarillado
C78: Servicios públicos
C79: Materiales y otros gastos de operación
C80: Pérdidas en prestación del servicio de acueducto
C81: Seguros
C82: Órdenes y contratos por otros servicios
C83: Total gastos | E83: =SUM(E14:E20)+E25+E26+SUM(E34:E36)+E51+E64+SUM(E72:E82) | F83: =SUM(F14:F20)+F25+F26+SUM(F34:F36)+F51+F64+SUM(F72:F82) | G83: =SUM(G14:G20)+G25+G26+SUM(G34:G36)+G51+G64+SUM(G72:G82) | H83: =SUM(H14:H20)+H25+H26+SUM(H34:H36)+H51+H64+SUM(H72:H82) | I83: =SUM(I14:I20)+I25+I26+SUM(I34:I36)+I51+I64+SUM(I72:I82) | J83: =SUM(J14:J20)+J25+J26+SUM(J34:J36)+J51+J64+SUM(J72:J82) | K83: =SUM(K14:K20)+K25+K26+SUM(K34:K36)+K51+K64+SUM(K72:K82) | L83: =SUM(L14:L20)+L25+L26+SUM(L34:L36)+L51+L64+SUM(L72:L82) | ... P83: =SUM(P14:P20)+P25+P26+SUM(P34:P36)+P51+P64+SUM(P72:P82)

Sheet Hoja45
B2: Indice
B3: Archivo: | C3: I:\Proyectos2025\proyecto_niif\_backup_legacy\Grupo1_Individual_Directo_ID20037_2024-12-31.xbrl
B4: Empresa: | C4: 20037
B5: Vista: | C5: [900019] FC02 - Complementario ingresos
B6: Eje X: | C6: N/A
B7: Eje Y: | C7: N/A
B8: Eje Z: | C8: Periodo Actual
I10: Ingresos, devoluciones, rebajas y descuentos [miembro]
I11: Ingresos brutos [miembro] | J11: Devoluciones, rebajas y descuentos [miembro] | K11: Ingresos netos [miembro]
B12: Información a revelar sobre ingresos y devoluciones [resumen]
C13: Información a revelar sobre ingresos [resumen]
D14: Acueducto [resumen]
E15: Abastecimiento
E16: Distribución
E17: Comercialización
E18: Subtotal Ingresos Acueducto | I18: =SUM(I15:I17)
D19: Alcantarillado [resumen]
E20: Recolección y transporte
E21: Tratamiento de aguas residuales
E22: Comercialización
E23: Subtotal Ingresos Alcantarillado | I23: =SUM(I20:I22)
D24: Aseo [resumen]
E25: Recolección y transporte de residuos no aprovechables
E26: Disposición final
E27: Tratamiento de lixiviados
E28: Comercialización
E29: Corte de césped
E30: Poda de arboles
E31: Limpieza y lavado de áreas públicas
E32: Limpieza de playa costeras y rivereñas
E33: Suministro e Instalación de cestas en vías y áreas públicas
E34: Mantenimiento de cestas en vías y áreas públicas
E35: Barrido y Limpieza
E36: Transferencia
... E39: Otros ingresos servicio aseo
E40: Subtotal Ingresos Aseo | I40: =SUM(I25:I39)
D41: Energía Eléctrica [resumen]
E42: ENERGIA - SIN [resumen]
F43: Generación [resumen]
G44: Ventas de contratos bilaterales
G45: Transacciones de energía en bolsa [resumen]
H46: Arranques y paradas
H47: Desviaciones positivas
H48: Cargo por confiabilidad
H49: Servicio AGC
H50: Restricciones
H51: Ventas en bolsa
H52: Subtotal Transacciones de energía en bolsa | I52: =SUM(I46:I51) | J52: =SUM(J46:J51) | K52: =SUM(K46:K51)
G53: Otros ingresos de generación
G54: Subtotal Ingresos Generación | I54: =I44+I52+I53 | J54: =J44+J52+J53 | K54: =K44+K52+K53
F55: Transmisión
F56: Distribución
F57: Comercialización [resumen]
G58: Ventas contratos bilaterales
G59: Ventas energía en bolsa
G60: Subtotal Comercialización | I60: =I58+I59 | J60: =J58+J59 | K60: =K58+K59
F61: Subtotal Energia - SIN | I61: =SUM(I54:I56)+I60 | J61: =SUM(J54:J56)+J60 | K61: =SUM(K54:K56)+K60
E62: ENERGIA - ZNI [resumen]
F63: Generación
F64: Distribución
F65: Comercialización
F66: Subtotal Energia - ZNI | I66: =SUM(I63:I65) | J66: =SUM(J63:J65) | K66: =SUM(K63:K65)
E67: Subtotal Energia Eléctrica | I67: =I61+I66 | J67: =J61+J66 | K67: =K61+K66
D68: Gas combustible por redes [resumen]
E69: Producción, comercialización [resumen]
F70: Contrato de Suministro en Firme
F71: Contrato de Suministro con Firmeza condicionada
F72: Contrato de Suministro en Firme al 95% - CF95
F73: Contrato de Suministro C1
F74: Contrato de Suministro C2
F75: Contrato de Opción de Compra de Gas
F76: Contrato de Suministro de Contingencia
F77: Contrato de Opción de Compra de Gas contra exportaciones
F78: Contrato con Interrupciones
F79: Contrato de condiciones uniformes
F80: Otros
F81: Subtotal Producción, comercialización | I81: =SUM(I70:I80) | J81: =SUM(J70:J80) | K81: =SUM(K70:K80)
E82: Transporte [resumen]
F83: Contrato de Transporte Firme
F84: Contrato de Opción de Compra de Transporte
F85: Contrato de Transporte de Contingencia
F86: Contrato de Transporte con Firmeza Condicionada
F87: Parqueo Rodante
F88: Otros
F89: Subtotal Transporte | I89: =SUM(I83:I88) | J89: =SUM(J83:J88) | K89: =SUM(K83:K88)
E90: Distribución [resumen]
F91: Ingresos por Distribución de Gas Natural
F92: Ingresos por Distribución de GLP por Redes
F93: Ingresos por Distribución de Aire Propanado
F94: Subtotal Distribución | I94: =SUM(I91:I93) | J94: =SUM(J91:J93) | K94: =SUM(K91:K93)
E95: Comercialización [resumen]
F96: Contrato Firme que garantiza Firmeza de Suministro
F97: Contrato Firme que garantiza Firmeza de Transporte
F98: Contrato de Suministro con Firmeza condicionada
F99: Contrato de Opción de Compra de Gas contra exportaciones
F100: Contrato de Opción de Compra de Transporte
F101: Contrato de Suministro de Contingencia
F102: Contrato de Transporte de Contingencia
F103: Contrato con Interrupciones
F104: Otros
...

Sheet Hoja46
B2: Indice
B3: Archivo: | C3: I:\Proyectos2025\proyecto_niif\_backup_legacy\Grupo1_Individual_Directo_ID20037_2024-12-31.xbrl
B4: Empresa: | C4: 20037
B5: Vista: | C5: [900021] FC03-1 - CXC - Acueducto (Detallado por estrato)
B6: Eje X: | C6: N/A
B7: Eje Y: | C7: N/A
B8: Eje Z: | C8: Periodo Actual
G10: Formato Complementario - Cuentas por cobrar (Acueducto - Detallado por estrato)
G11: Corriente / No corriente [miembro] | J11: Total [miembro]
G12: Corriente [miembro] | H12: No Corriente [miembro] | J12: No vencida [miembro] | K12: Vencida 1 a 30 días [miembro] | L12: Vencida 31 a 60 días [miembro] | M12: Vencida 61 a 90 días [miembro] | N12: Vencida 91 a 120 días [miembro] | O12: Vencida 121 a 150 días [miembro] | P12: Vencida 151 a 180 días [miembro] | Q12: Vencida 181 a 360 días [miembro] | R12: Vencida mayor de 360 días [miembro]
B13: Formato Complementario - Cuentas por cobrar (Acueducto - Detallado por estrato) [partidas]
C14: Detalle Cuentas por cobrar Servicio de Acueducto
D15: Servicio de acueducto [partidas]
E16: Distribución
E17: Otros Servicios
E18: Comercialización [resumen]
F19: Residencial Estrato 1
F20: Residencial Estrato 2
F21: Residencial Estrato 3
F22: Residencial Estrato 4
F23: Residencial Estrato 5
F24: Residencial Estrato 6
F25: No residencial industrial
F26: No residencial comercial
F27: No residencial oficial
F28: No residencial especial
F29: Total Comercialización | G29: =SUM(G19:G28) | H29: =SUM(H19:H28) | I29: =SUM(I19:I28) | J29: =SUM(J19:J28) | K29: =SUM(K19:K28) | L29: =SUM(L19:L28) | M29: =SUM(M19:M28) | N29: =SUM(N19:N28) | ... S29: =SUM(S19:S28)
E30: Cuentas por Cobrar brutas servicio de Acueducto | G30: =G16+G17+G29 | H30: =H16+H17+H29 | I30: =I16+I17+I29 | J30: =J16+J17+J29 | K30: =K16+K17+K29 | L30: =L16+L17+L29 | M30: =M16+M17+M29 | N30: =N16+N17+N29 | ... S30: =S16+S17+S29
C31: Detalle Deterioro cuentas por cobrar Servicio de Acueducto
D32: Deterioro de cuentas por cobrar [partidas]
E33: Distribución
E34: Otros Servicios
E35: Comercialización [resumen]
F36: Residencial Estrato 1
F37: Residencial Estrato 2
F38: Residencial Estrato 3
F39: Residencial Estrato 4
F40: Residencial Estrato 5
F41: Residencial Estrato 6
F42: No Residencial Industrial
F43: No Residencial Comercial
F44: No Residencial Oficial
F45: No Residencial Especial
F46: Total Comercialización | G46: =SUM(G36:G45) | H46: =SUM(H36:H45) | I46: =SUM(I36:I45) | J46: =SUM(J36:J45) | K46: =SUM(K36:K45) | L46: =SUM(L36:L45) | M46: =SUM(M36:M45) | N46: =SUM(N36:N45) | ... S46: =SUM(S36:S45)
E47: Total deterioro cuentas por cobrar Servicio Acueducto | G47: =G33+G34+G46 | H47: =H33+H34+H46 | I47: =I33+I34+I46 | J47: =J33+J34+J46 | K47: =K33+K34+K46 | L47: =L33+L34+L46 | M47: =M33+M34+M46 | N47: =N33+N34+N46 | ... S47: =S33+S34+S46
C48: Cuentas por cobrar netas Servicio Acueducto | G48: =G30-G47 | H48: =H30-H47 | I48: =I30-I47 | J48: =J30-J47 | K48: =K30-K47 | L48: =L30-L47 | M48: =M30-M47 | N48: =N30-N47 | ... S48: =S30-S47

Sheet Hoja47
B2: Indice
B3: Archivo: | C3: I:\Proyectos2025\proyecto_niif\_backup_legacy\Grupo1_Individual_Directo_ID20037_2024-12-31.xbrl
B4: Empresa: | C4: 20037
B5: Vista: | C5: [900022] FC03-2 - CXC - Alcantarillado (Detallado por estrato)
B6: Eje X: | C6: N/A
B7: Eje Y: | C7: N/A
B8: Eje Z: | C8: Periodo Actual
G10: Formato Complementario - Cuentas por cobrar (Alcantarillado - Detallado por estrato)
G11: Corriente / No corriente [miembro] | J11: Total [miembro]
G12: Corriente [miembro] | H12: No Corriente [miembro] | J12: No vencida [miembro] | K12: Vencida 1 a 30 días [miembro] | L12: Vencida 31 a 60 días [miembro] | M12: Vencida 61 a 90 días [miembro] | N12: Vencida 91 a 120 días [miembro] | O12: Vencida 121 a 150 días [miembro] | P12: Vencida 151 a 180 días [miembro] | Q12: Vencida 181 a 360 días [miembro] | R12: Vencida mayor de 360 días [miembro]
B13: Formato Complementario - Cuentas por cobrar (Alcantarillado - Detallado por estrato) [partidas]
C14: Detalle Cuentas por cobrar Servicio de Alcantarillado
D15: Servicio de alcantarillado [resumen]
E16: Recolección
E17: Tratamiento y disposición final
E18: Comercialización [resumen]
F19: Residencial Estrato 1
F20: Residencial Estrato 2
F21: Residencial Estrato 3
F22: Residencial Estrato 4
F23: Residencial Estrato 5
F24: Residencial Estrato 6
F25: No residencial industrial
F26: No residencial comercial
F27: No residencial oficial
F28: No residencial especial
F29: Total Comercialización | G29: =SUM(G19:G28) | H29: =SUM(H19:H28) | I29: =SUM(I19:I28) | J29: =SUM(J19:J28) | K29: =SUM(K19:K28) | L29: =SUM(L19:L28) | M29: =SUM(M19:M28) | N29: =SUM(N19:N28) | ... S29: =SUM(S19:S28)
E30: Cuentas por Cobrar brutas servicio de Alcantarillado | G30: =G16+G17+G29 | H30: =H16+H17+H29 | I30: =I16+I17+I29 | J30: =J16+J17+J29 | K30: =K16+K17+K29 | L30: =L16+L17+L29 | M30: =M16+M17+M29 | N30: =N16+N17+N29 | ... S30: =S16+S17+S29
C31: Detalle Deterioro cuentas por cobrar Servicio de Alcantarillado
D32: Deterioro de cuentas por cobrar [partidas]
E33: Recolección
E34: Tratamiento y disposición final
E35: Comercialización [resumen]
F36: Residencial Estrato 1
F37: Residencial Estrato 2
F38: Residencial Estrato 3
F39: Residencial Estrato 4
F40: Residencial Estrato 5
F41: Residencial Estrato 6
F42: No Residencial Industrial
F43: No Residencial Comercial
F44: No Residencial Oficial
F45: No Residencial Especial
F46: Total Comercialización | G46: =SUM(G36:G45) | H46: =SUM(H36:H45) | I46: =SUM(I36:I45) | J46: =SUM(J36:J45) | K46: =SUM(K36:K45) | L46: =SUM(L36:L45) | M46: =SUM(M36:M45) | N46: =SUM(N36:N45) | ... S46: =SUM(S36:S45)
E47: Total deterioro cuentas por cobrar Servicio Alcantarillado | G47: =G33+G34+G46 | H47: =H33+H34+H46 | I47: =I33+I34+I46 | J47: =J33+J34+J46 | K47: =K33+K34+K46 | L47: =L33+L34+L46 | M47: =M33+M34+M46 | N47: =N33+N34+N46 | ... S47: =S33+S34+S46
C48: Cuentas por cobrar netas Servicio Alcantarillado | G48: =-G47+G30 | H48: =-H47+H30 | I48: =-I47+I30 | J48: =-J47+J30 | K48: =-K47+K30 | L48: =-L47+L30 | M48: =-M47+M30 | N48: =-N47+N30 | ... S48: =-S47+S30

Sheet Hoja48
B2: Indice
B3: Archivo: | C3: I:\Proyectos2025\proyecto_niif\_backup_legacy\Grupo1_Individual_Directo_ID20037_2024-12-31.xbrl
B4: Empresa: | C4: 20037
B5: Vista: | C5: [900023] FC03-3 - CXC - Aseo (Detallado por estrato)
B6: Eje X: | C6: N/A
B7: Eje Y: | C7: N/A
B8: Eje Z: | C8: Periodo Actual
E10: Formato Complementario - Cuentas por cobrar (Aseo - Detallado por estrato)
E11: Corriente / No corriente [miembro] | H11: Total [miembro]
E12: Corriente [miembro] | F12: No Corriente [miembro] | H12: No vencida [miembro] | I12: Vencida 1 a 30 días [miembro] | J12: Vencida 31 a 60 días [miembro] | K12: Vencida 61 a 90 días [miembro] | L12: Vencida 91 a 120 días [miembro] | M12: Vencida 121 a 150 días [miembro] | N12: Vencida 151 a 180 días [miembro] | O12: Vencida 181 a 360 días [miembro] | P12: Vencida mayor de 360 días [miembro]
B13: Formato Complementario - Cuentas por cobrar (Aseo - Detallado por estrato) [partidas]
C14: Cuentas por cobrar Servicio de Aseo
D15: Residencial Estrato 1
D16: Residencial Estrato 2
D17: Residencial Estrato 3
D18: Residencial Estrato 4
D19: Residencial Estrato 5
D20: Residencial Estrato 6
D21: No residencial industrial
D22: No residencial comercial
D23: No residencial oficial
D24: No residencial especial
D25: Aprovechamiento
D26: Total cuentas por cobrar servicio de aseo | E26: =SUM(E15:E25) | F26: =SUM(F15:F25) | G26: =SUM(G15:G25) | H26: =SUM(H15:H25) | I26: =SUM(I15:I25) | J26: =SUM(J15:J25) | K26: =SUM(K15:K25) | L26: =SUM(L15:L25) | ... Q26: =SUM(Q15:Q25)
C27: Deterioro cuentas por cobrar Servicio de Aseo
D28: Residencial Estrato 1
D29: Residencial Estrato 2
D30: Residencial Estrato 3
D31: Residencial Estrato 4
D32: Residencial Estrato 5
D33: Residencial Estrato 6
D34: No Residencial Industrial
D35: No Residencial Comercial
D36: No Residencial Oficial
D37: No Residencial Especial
D38: Aprovechamiento
D39: Total deterioro cuentas por cobrar servicio de aseo | E39: =SUM(E28:E38) | F39: =SUM(F28:F38) | G39: =SUM(G28:G38) | H39: =SUM(H28:H38) | I39: =SUM(I28:I38) | J39: =SUM(J28:J38) | K39: =SUM(K28:K38) | L39: =SUM(L28:L38) | ... Q39: =SUM(Q28:Q38)
C40: Cuentas por cobrar netas Servicio Aseo | E40: =E26-E39 | F40: =F26-F39 | G40: =G26-G39 | H40: =H26-H39 | I40: =I26-I39 | J40: =J26-J39 | K40: =K26-K39 | L40: =L26-L39 | ... Q40: =Q26-Q39

Sheet Hoja49
B2: Indice
B3: Archivo: | C3: I:\Proyectos2025\proyecto_niif\_backup_legacy\Grupo1_Individual_Directo_ID20037_2024-12-31.xbrl
B4: Empresa: | C4: 20037
B5: Vista: | C5: [900024] FC03-4 - CXC - Energía (Detallado por estrato)
B6: Eje X: | C6: N/A
B7: Eje Y: | C7: N/A
B8: Eje Z: | C8: Periodo Actual
F10: Formato Complementario - Cuentas por cobrar (Energía Eléctrica - Detallado por estrato)
F11: Corriente / No corriente [miembro] | I11: Total [miembro]
F12: Corriente [miembro] | G12: No Corriente [miembro] | I12: No vencida [miembro] | J12: Vencida 1 a 30 días [miembro] | K12: Vencida 31 a 60 días [miembro] | L12: Vencida 61 a 90 días [miembro] | M12: Vencida 91 a 120 días [miembro] | N12: Vencida 121 a 150 días [miembro] | O12: Vencida 151 a 180 días [miembro] | P12: Vencida 181 a 360 días [miembro] | Q12: Vencida mayor de 360 días [miembro]
B13: Formato Complementario - Cuentas por cobrar (Energía Eléctrica - Detallado por estrato) [partidas]
C14: Cuentas por cobrar Servicio de Energía eléctrica [partidas]
D15: Generación [sinopsis]
E16: Contratos bilaterales empresas del sector
E17: Contratos bilaterales usuarios no regulados
E18: Bolsa de energía
E19: Otros
E20: Total Generación | F20: =SUM(F16:F19) | G20: =SUM(G16:G19) | H20: =SUM(H16:H19) | I20: =SUM(I16:I19) | J20: =SUM(J16:J19) | K20: =SUM(K16:K19) | L20: =SUM(L16:L19) | M20: =SUM(M16:M19) | ... R20: =SUM(R16:R19)
D21: Transmisión [sinopsis]
E22: Ingreso regulado
E23: Cargos por conexión
E24: Otros
E25: Total Transmisión | F25: =SUM(F22:F24) | G25: =SUM(G22:G24) | H25: =SUM(H22:H24) | I25: =SUM(I22:I24) | J25: =SUM(J22:J24) | K25: =SUM(K22:K24) | L25: =SUM(L22:L24) | M25: =SUM(M22:M24) | ... R25: =SUM(R22:R24)
D26: Operador de red [sinopsis]
E27: Cargos por uso de usuarios regulados
E28: Cargos por uso de usuarios no regulados
E29: Ingreso regulado
E30: Otros
E31: Total Operador de red | F31: =SUM(F27:F30) | G31: =SUM(G27:G30) | H31: =SUM(H27:H30) | I31: =SUM(I27:I30) | J31: =SUM(J27:J30) | K31: =SUM(K27:K30) | L31: =SUM(L27:L30) | M31: =SUM(M27:M30) | ... R31: =SUM(R27:R30)
D32: Comercialización [sinopsis]
E33: Residencial Estrato 1
E34: Residencial Estrato 2
E35: Residencial Estrato 3
E36: Residencial Estrato 4
E37: Residencial Estrato 5
E38: Residencial Estrato 6
E39: Comercial
E40: Industrial
E41: Oficial
E42: Alumbrado público
E43: Empresas del sector
E44: Usuarios no regulados
E45: Otros
E46: Total Comercialización | F46: =SUM(F33:F45) | G46: =SUM(G33:G45) | H46: =SUM(H33:H45) | I46: =SUM(I33:I45) | J46: =SUM(J33:J45) | K46: =SUM(K33:K45) | L46: =SUM(L33:L45) | M46: =SUM(M33:M45) | ... R46: =SUM(R33:R45)
D47: Cuentas por Cobrar brutas servicio de Energía | F47: =F20+F25+F31+F46 | G47: =G20+G25+G31+G46 | H47: =H20+H25+H31+H46 | I47: =I20+I25+I31+I46 | J47: =J20+J25+J31+J46 | K47: =K20+K25+K31+K46 | L47: =L20+L25+L31+L46 | M47: =M20+M25+M31+M46 | ... R47: =R20+R25+R31+R46
C48: Deterioro de cuentas por cobrar Servicio de Energía Eléctrica [partidas]
D49: Generación [sinopsis]
E50: Contratos bilaterales empresas del sector
E51: Contratos bilaterales usuarios no regulados
E52: Bolsa de energía
E53: Otros
E54: Total Generación | F54: =SUM(F50:F53) | G54: =SUM(G50:G53) | H54: =SUM(H50:H53) | I54: =SUM(I50:I53) | J54: =SUM(J50:J53) | K54: =SUM(K50:K53) | L54: =SUM(L50:L53) | M54: =SUM(M50:M53) | ... R54: =SUM(R50:R53)
D55: Transmisión [sinopsis]
E56: Ingreso regulado
E57: Cargos por conexión
E58: Otros
E59: Total Transmisión | F59: =SUM(F56:F58) | G59: =SUM(G56:G58) | H59: =SUM(H56:H58) | I59: =SUM(I56:I58) | J59: =SUM(J56:J58) | K59: =SUM(K56:K58) | L59: =SUM(L56:L58) | M59: =SUM(M56:M58) | ... R59: =SUM(R56:R58)
D60: Operador de red [sinopsis]
E61: Cargos por uso de usuarios regulados
E62: Cargos por uso de usuarios no regulados
E63: Ingreso regulado
E64: Otros
E65: Total Operador de red | F65: =SUM(F61:F64) | G65: =SUM(G61:G64) | H65: =SUM(H61:H64) | I65: =SUM(I61:I64) | J65: =SUM(J61:J64) | K65: =SUM(K61:K64) | L65: =SUM(L61:L64) | M65: =SUM(M61:M64) | ... R65: =SUM(R61:R64)
D66: Comercialización [sinopsis]
E67: Residencial Estrato 1
E68: Residencial Estrato 2
E69: Residencial Estrato 3
E70: Residencial Estrato 4
E71: Residencial Estrato 5
E72: Residencial Estrato 6
E73: Comercial
E74: Industrial
E75: Oficial
E76: Alumbrado público
E77: Empresas del sector
E78: Usuarios no regulados
E79: Otros
E80: Total Comercialización | F80: =SUM(F67:F79) | G80: =SUM(G67:G79) | H80: =SUM(H67:H79) | I80: =SUM(I67:I79) | J80: =SUM(J67:J79) | K80: =SUM(K67:K79) | L80: =SUM(L67:L79) | M80: =SUM(M67:M79) | ... R80: =SUM(R67:R79)
D81: Total deterioro cuentas por cobrar Servicio Energía | F81: =F59+F80+F65+F54 | G81: =G59+G80+G65+G54 | H81: =H59+H80+H65+H54 | I81: =I59+I80+I65+I54 | J81: =J59+J80+J65+J54 | K81: =K59+K80+K65+K54 | L81: =L59+L80+L65+L54 | M81: =M59+M80+M65+M54 | ... R81: =R59+R80+R65+R54
C82: Cuentas por cobrar netas Servicio Energía | F82: =F47-F81 | G82: =G47-G81 | H82: =H47-H81 | I82: =I47-I81 | J82: =J47-J81 | K82: =K47-K81 | L82: =L47-L81 | M82: =M47-M81 | ... R82: =R47-R81

Sheet Hoja50
B2: Indice
B3: Archivo: | C3: I:\Proyectos2025\proyecto_niif\_backup_legacy\Grupo1_Individual_Directo_ID20037_2024-12-31.xbrl
B4: Empresa: | C4: 20037
B5: Vista: | C5: [900025] FC03-5 - CXC - Gas combustible por redes (Detallado por estrato)
B6: Eje X: | C6: N/A
B7: Eje Y: | C7: N/A
B8: Eje Z: | C8: Periodo Actual
H10: Formato Complementario - Cuentas por cobrar (Gas combustible por redes - Detallado por estrato)
H11: Corriente / No corriente [miembro] | K11: Total [miembro]
H12: Corriente [miembro] | I12: No Corriente [miembro] | K12: No vencida [miembro] | L12: Vencida 1 a 30 días [miembro] | M12: Vencida 31 a 60 días [miembro] | N12: Vencida 61 a 90 días [miembro] | O12: Vencida 91 a 120 días [miembro] | P12: Vencida 121 a 150 días [miembro] | Q12: Vencida 151 a 180 días [miembro] | R12: Vencida 181 a 360 días [miembro] | S12: Vencida mayor de 360 días [miembro]
B13: Formato Complementario - Cuentas por cobrar Gas combustible por redes - Detallado por estrato [partidas]
C14: Detalle Cuentas por cobrar Servicio de Gas Combustible Por Redes
D15: Servicio de Gas combustible por redes [resumen]
E16: Negocio transporte de gas combustible [resumen]
F17: Empresas del sector
F18: Grandes consumidores
F19: Otros
F20: Total Transporte de gas combustible | H20: =SUM(H17:H19) | I20: =SUM(I17:I19) | J20: =SUM(J17:J19) | K20: =SUM(K17:K19) | L20: =SUM(L17:L19) | M20: =SUM(M17:M19) | N20: =SUM(N17:N19) | O20: =SUM(O17:O19) | ... T20: =SUM(T17:T19)
E21: Negocio distribución de gas combustible [resumen]
F22: Empresas del sector
F23: Grandes consumidores
F24: Otros
F25: Total Distribución de gas combustible | H25: =SUM(H22:H24) | I25: =SUM(I22:I24) | J25: =SUM(J22:J24) | K25: =SUM(K22:K24) | L25: =SUM(L22:L24) | M25: =SUM(M22:M24) | N25: =SUM(N22:N24) | O25: =SUM(O22:O24) | ... T25: =SUM(T22:T24)
E26: Negocio comercializacion de gas combustible [resumen]
F27: Residencial Estrato 1 | H27: =H28+H29 | I27: =I28+I29 | J27: =J28+J29 | K27: =K28+K29 | L27: =L28+L29 | M27: =M28+M29 | N27: =N28+N29 | O27: =O28+O29 | ... T27: =T28+T29
G28: Hogares sustitutos
G29: Otros residencial estrato 1
F30: Residencial Estrato 2
F31: Residencial Estrato 3
F32: Residencial Estrato 4
F33: Residencial Estrato 5
F34: Residencial Estrato 6
F35: Comercial
F36: Industrial
F37: Oficial
F38: Especial Asistencial
F39: Especial Educativo
F40: Grandes consumidores
F41: Empresas del sector
F42: Otros
F43: Total Comercialización de gas combustible | H43: =H27+SUM(H30:H42) | I43: =I27+SUM(I30:I42) | J43: =J27+SUM(J30:J42) | K43: =K27+SUM(K30:K42) | L43: =L27+SUM(L30:L42) | M43: =M27+SUM(M30:M42) | N43: =N27+SUM(N30:N42) | O43: =O27+SUM(O30:O42) | ... T43: =T27+SUM(T30:T42)
E44: Cuentas por Cobrar brutas servicio de Gas Combustible Por Redes | H44: =H43+H20+H25 | I44: =I43+I20+I25 | J44: =J43+J20+J25 | K44: =K43+K20+K25 | L44: =L43+L20+L25 | M44: =M43+M20+M25 | N44: =N43+N20+N25 | O44: =O43+O20+O25 | ... T44: =T43+T20+T25
C45: Detalle Deterioro cuentas por cobrar Servicio de Gas Combustible Por Redes
D46: Deterioro de cuentas por cobrar [resumen]
E47: Negocio transporte de gas combustible [resumen]
F48: Empresas del sector
F49: Grandes consumidores
F50: Otros
F51: Total Transporte de gas combustible | H51: =SUM(H48:H50) | I51: =SUM(I48:I50) | J51: =SUM(J48:J50) | K51: =SUM(K48:K50) | L51: =SUM(L48:L50) | M51: =SUM(M48:M50) | N51: =SUM(N48:N50) | O51: =SUM(O48:O50) | ... T51: =SUM(T48:T50)
E52: Negocio distribución de gas combustible [resumen]
F53: Empresas del sector
F54: Grandes consumidores
F55: Otros
F56: Total Distribución de gas combustible | H56: =SUM(H53:H55) | I56: =SUM(I53:I55) | J56: =SUM(J53:J55) | K56: =SUM(K53:K55) | L56: =SUM(L53:L55) | M56: =SUM(M53:M55) | N56: =SUM(N53:N55) | O56: =SUM(O53:O55) | ... T56: =SUM(T53:T55)
E57: Negocio comercializacion de gas combustible [resumen]
F58: Residencial estrato 1
F59: Residencial Estrato 2
F60: Residencial Estrato 3
F61: Residencial Estrato 4
F62: Residencial Estrato 5
F63: Residencial Estrato 6
F64: Comercial
F65: Industrial
F66: Oficial
F67: Especial Asistencial
F68: Especial Educativo
F69: Grandes consumidores
... F71: Otros
F72: Total Comercialización de gas combustible | H72: =SUM(H58:H71) | I72: =SUM(I58:I71) | J72: =SUM(J58:J71) | K72: =SUM(K58:K71) | L72: =SUM(L58:L71) | M72: =SUM(M58:M71) | N72: =SUM(N58:N71) | O72: =SUM(O58:O71) | ... T72: =SUM(T58:T71)
E73: Total deterioro cuentas por cobrar Servicio Gas Combustible Por Redes | H73: =H72+H51+H56 | I73: =I72+I51+I56 | J73: =J72+J51+J56 | K73: =K72+K51+K56 | L73: =L72+L51+L56 | M73: =M72+M51+M56 | N73: =N72+N51+N56 | O73: =O72+O51+O56 | ... T73: =T72+T51+T56
C74: Cuentas por cobrar netas Servicio Gas Combustible Por Redes | H74: =-H73+H44 | I74: =-I73+I44 | J74: =-J73+J44 | K74: =-K73+K44 | L74: =-L73+L44 | M74: =-M73+M44 | N74: =-N73+N44 | O74: =-O73+O44 | ... T74: =-T73+T44

Sheet Hoja51
B2: Indice
B3: Archivo: | C3: I:\Proyectos2025\proyecto_niif\_backup_legacy\Grupo1_Individual_Directo_ID20037_2024-12-31.xbrl
B4: Empresa: | C4: 20037
B5: Vista: | C5: [900026] FC03-6 - CXC - Gas Licuado del Petróleo (Detallado por estrato)
B6: Eje X: | C6: N/A
B7: Eje Y: | C7: N/A
B8: Eje Z: | C8: Periodo Actual
G10: Formato Complementario - Cuentas por cobrar (Gas Licuado del Petróleo - Detallado por estrato)
G11: Corriente / No corriente [miembro] | J11: Total [miembro]
G12: Corriente [miembro] | H12: No Corriente [miembro] | J12: No vencida [miembro] | K12: Vencida 1 a 30 días [miembro] | L12: Vencida 31 a 60 días [miembro] | M12: Vencida 61 a 90 días [miembro] | N12: Vencida 91 a 120 días [miembro] | O12: Vencida 121 a 150 días [miembro] | P12: Vencida 151 a 180 días [miembro] | Q12: Vencida 181 a 360 días [miembro] | R12: Vencida mayor de 360 días [miembro]
B13: Formato Complementario - Cuentas por cobrar (Gas Licuado del Petróleo - Detallado por estrato) [partidas]
C14: Detalle Cuentas por cobrar Servicio de GLP
D15: Servicio de gas licuado del petróleo [resumen]
E16: Negocio transporte de GLP [resumen]
F17: Empresas del sector
F18: Usuarios No Regulados
F19: Otros
F20: Total Transporte de GLP | G20: =SUM(G17:G19) | H20: =SUM(H17:H19) | I20: =SUM(I17:I19) | J20: =SUM(J17:J19) | K20: =SUM(K17:K19) | L20: =SUM(L17:L19) | M20: =SUM(M17:M19) | N20: =SUM(N17:N19) | ... S20: =SUM(S17:S19)
E21: Negocio comercializacion Mayorista de GLP [resumen]
F22: Distribuidores Inversionistas
F23: Comercializadores Mayoristas
F24: Usuarios No Regulados
F25: Otros
F26: Total Comercializacion Mayorista de GLP | G26: =SUM(G22:G25) | H26: =SUM(H22:H25) | I26: =SUM(I22:I25) | J26: =SUM(J22:J25) | K26: =SUM(K22:K25) | L26: =SUM(L22:L25) | M26: =SUM(M22:M25) | N26: =SUM(N22:N25) | ... S26: =SUM(S22:S25)
E27: Negocio distribución de GLP [resumen]
F28: Comercializadores minoristas
F29: Tanques Estacionarios
F30: Puntos de Venta
F31: Estrato 1 Subsidiado
F32: Estrato 2 Subsidiado
F33: Otros
F34: Total distribución de GLP | G34: =SUM(G28:G33) | H34: =SUM(H28:H33) | I34: =SUM(I28:I33) | J34: =SUM(J28:J33) | K34: =SUM(K28:K33) | L34: =SUM(L28:L33) | M34: =SUM(M28:M33) | N34: =SUM(N28:N33) | ... S34: =SUM(S28:S33)
E35: Negocio comercialización Minorista GLP [resumen]
F36: Estrato 1 Subsidiado
F37: Estrato 2 Subsidiado
F38: Usuario Final
F39: Otros
F40: Total comercialización minorista de GLP | G40: =SUM(G36:G39) | H40: =SUM(H36:H39) | I40: =SUM(I36:I39) | J40: =SUM(J36:J39) | K40: =SUM(K36:K39) | L40: =SUM(L36:L39) | M40: =SUM(M36:M39) | N40: =SUM(N36:N39) | ... S40: =SUM(S36:S39)
E41: Cuentas por Cobrar brutas servicio de GLP | G41: =G26+G20+G40+G34 | H41: =H26+H20+H40+H34 | I41: =I26+I20+I40+I34 | J41: =J26+J20+J40+J34 | K41: =K26+K20+K40+K34 | L41: =L26+L20+L40+L34 | M41: =M26+M20+M40+M34 | N41: =N26+N20+N40+N34 | ... S41: =S26+S20+S40+S34
C42: Detalle Deterioro cuentas por cobrar Servicio de GLP
D43: Deterioro de cuentas por cobrar [resumen]
E44: Negocio transporte de GLP [resumen]
F45: Empresas del sector
F46: Usuarios No Regulados
F47: Otros
F48: Total Transporte de GLP | G48: =SUM(G45:G47) | H48: =SUM(H45:H47) | I48: =SUM(I45:I47) | J48: =SUM(J45:J47) | K48: =SUM(K45:K47) | L48: =SUM(L45:L47) | M48: =SUM(M45:M47) | N48: =SUM(N45:N47) | ... S48: =SUM(S45:S47)
E49: Negocio comercializacion Mayorista de GLP [resumen]
F50: Distribuidores Inversionistas
F51: Comercializadores mayoristas
F52: Usuarios No Regulados
F53: Otros
F54: Total Comercializacion Mayorista de GLP | G54: =SUM(G50:G53) | H54: =SUM(H50:H53) | I54: =SUM(I50:I53) | J54: =SUM(J50:J53) | K54: =SUM(K50:K53) | L54: =SUM(L50:L53) | M54: =SUM(M50:M53) | N54: =SUM(N50:N53) | ... S54: =SUM(S50:S53)
E55: Negocio distribución de GLP [resumen]
F56: Comercializadores minoristas
F57: Tanques Estacionarios
F58: Puntos de Venta
F59: Estrato 1 Subsidiado
F60: Estrato 2 Subsidiado
F61: Otros
F62: Total distribución de GLP | G62: =SUM(G56:G61) | H62: =SUM(H56:H61) | I62: =SUM(I56:I61) | J62: =SUM(J56:J61) | K62: =SUM(K56:K61) | L62: =SUM(L56:L61) | M62: =SUM(M56:M61) | N62: =SUM(N56:N61) | ... S62: =SUM(S56:S61)
E63: Negocio comercializacion Minorista GLP [resumen]
F64: Estrato 1 Subsidiado
F65: Estrato 2 Subsidiado
F66: Usuario Final
F67: Otros
F68: Total comercialización minorista de GLP | G68: =SUM(G64:G67) | H68: =SUM(H64:H67) | I68: =SUM(I64:I67) | J68: =SUM(J64:J67) | K68: =SUM(K64:K67) | L68: =SUM(L64:L67) | M68: =SUM(M64:M67) | N68: =SUM(N64:N67) | ... S68: =SUM(S64:S67)
E69: Total deterioro cuentas por cobrar Servicio GLP | G69: =G54+G48+G62+G68 | H69: =H54+H48+H62+H68 | I69: =I54+I48+I62+I68 | J69: =J54+J48+J62+J68 | K69: =K54+K48+K62+K68 | L69: =L54+L48+L62+L68 | M69: =M54+M48+M62+M68 | N69: =N54+N48+N62+N68 | ... S69: =S54+S48+S62+S68
C70: Cuentas por cobrar netas Servicio GLP | G70: =G41-G69 | H70: =H41-H69 | I70: =I41-I69 | J70: =J41-J69 | K70: =K41-K69 | L70: =L41-L69 | M70: =M41-M69 | N70: =N41-N69 | ... S70: =S41-S69

Sheet Hoja52
B2: Indice
B3: Archivo: | C3: I:\Proyectos2025\proyecto_niif\_backup_legacy\Grupo1_Individual_Directo_ID20037_2024-12-31.xbrl
B4: Empresa: | C4: 20037
B5: Vista: | C5: [900027] FC04 - Información Subsidios y Contribuciones
B6: Eje X: | C6: N/A
B7: Eje Y: | C7: N/A
B8: Eje Z: | C8: Periodo Actual
E10: Total Periodo [miembro]
E11: Acueducto [miembro] | F11: Alcantarillado [miembro] | G11: Aseo [miembro] | H11: Energía Eléctrica [miembro] | I11: Gas combustible por redes [miembro] | J11: Gas Licuado de Petróleo [miembro]
B12: Formato Complementario - Subsidios y Contribuciones [partidas]
C13: Subsidios
D14: Estrato 1
D15: Estrato 2
D16: Estrato 3
D17: Total Subsidios | E17: =SUM(E14:E16) | F17: =SUM(F14:F16) | G17: =SUM(G14:G16) | H17: =SUM(H14:H16) | I17: =SUM(I14:I16) | J17: =SUM(J14:J16) | K17: =SUM(K14:K16)
C18: Contribuciones
D19: Estrato 5
D20: Estrato 6
D21: Comercial
D22: Industrial
D23: Total Contribución | E23: =SUM(E19:E22) | F23: =SUM(F19:F22) | G23: =SUM(G19:G22) | H23: =SUM(H19:H22) | I23: =SUM(I19:I22) | J23: =SUM(J19:J22) | K23: =SUM(K19:K22)
D24: Valor Neto Subsidios vs. Contribuciones | E24: =-E23+E17 | F24: =-F23+F17 | G24: =-G23+G17 | H24: =-H23+H17 | I24: =-I23+I17 | J24: =-J23+J17 | K24: =-K23+K17
C25: Detalle deterioro cartera de municipios
C26: Subsidio FOES
C27: Subsidio FAER
C28: Subsidio FAZNI
C29: Subsidio PRONE
C30: Subsidio Gas combustible por redes
C31: Subsidio GLP

Sheet Hoja53
B2: Indice
B3: Archivo: | C3: I:\Proyectos2025\proyecto_niif\_backup_legacy\Grupo1_Individual_Directo_ID20037_2024-12-31.xbrl
B4: Empresa: | C4: 20037
B5: Vista: | C5: [900027a] FC04a - Detalle de los subsidios por cobrar
B6: Eje X: | C6: N/A
B7: Eje Y: | C7: N/A
B8: Eje Z: | C8: Periodo Actual
C10: Detalle de los subsidios por cobrar
C11: Periodo | E11: Total Corriente / No corriente | H11: Total Subsidios por cobrar | R11: Fecha de cobro | S11: Justificacion desautorización | T11: Gestiones realizadas para lograr el recaudo
C12: Año | D12: Mes | E12: Corriente | G12: No corriente | H12: Subsidios por cobrar no vencidos | J12: Vencidos hasta 30 Días | K12: Vencidos hasta 60 Días | L12: Vencidos hasta 90 Días | M12: Vencidos hasta 120 Días | N12: Vencidos hasta 150 Días | O12: Vencidos hasta 180 Días | P12: Vencidos hasta 360 Días | Q12: Vencidos mayores a 360 Días
B13: Fila Subsidios
B14: Total Subsidio

Sheet Hoja54
B2: Indice
B3: Archivo: | C3: I:\Proyectos2025\proyecto_niif\_backup_legacy\Grupo1_Individual_Directo_ID20037_2024-12-31.xbrl
B4: Empresa: | C4: 20037
B5: Vista: | C5: [900028] FC05 - Acreedores comerciales y otras cuentas por pagar - Bloques de texto
B6: Eje X: | C6: N/A
B7: Eje Y: | C7: N/A
B8: Eje Z: | C8: N/A
D10: Periodo Actual
B11: Formato Complementario - Acreedores comerciales y otras cuentas por pagar [partidas]
C12: Información a revelar sobre obligaciones financieras y cuentas por pagar

Sheet Hoja55
B2: Indice
B3: Archivo: | C3: I:\Proyectos2025\proyecto_niif\_backup_legacy\Grupo1_Individual_Directo_ID20037_2024-12-31.xbrl
B4: Empresa: | C4: 20037
B5: Vista: | C5: [900028b] FC05b - Clase de pasivo por edades de vencimiento - Revelaciones
B6: Eje X: | C6: N/A
B7: Eje Y: | C7: N/A
B8: Eje Z: | C8: Periodo Actual
D10: Formato Complementario - Detalle de Pasivos [partidas]
D11: Total Corriente / No corriente | G11: Total pasivos por bandas de tiempo | P11: Incluya las revelaciones asociadas a las edades de los pasivos por cada clase
D12: Corriente | F12: No corriente | G12: Pasivos no vencidos | I12: Total pasivos vencidos
I13: Vencidos hasta 30 Días | K13: Vencidos hasta 60 Días | L13: Vencidos hasta 90 Días | M13: Vencidos hasta 180 Días | N13: Vencidos hasta 360 Días | O13: Vencidos mayores a 360 Días
B14: Formato Complementario - Detalle de pasivos [miembro]
C15: Nómina por pagar
C16: Prestaciones sociales por pagar
C17: Cuentas comerciales por pagar por adquisición de bienes y servicios
C18: Impuestos por pagar
C19: Cuentas por pagar a partes relacionadas y asociadas
C20: Obligaciones financieras por pagar
C21: Ingresos recibidos por anticipado e ingresos diferidos
C22: Pasivos por impuestos diferidos
C23: Provisiones
C24: Tasas ambientales y tasas de uso por pagar
C25: Otras tasas y contribuciones por pagar
C26: Pasivos pretoma (Solo intervenidas)
... C30: TOTAL

Sheet Hoja56
B2: Indice
B3: Archivo: | C3: I:\Proyectos2025\proyecto_niif\_backup_legacy\Grupo1_Individual_Directo_ID20037_2024-12-31.xbrl
B4: Empresa: | C4: 20037
B5: Vista: | C5: [900029] FC06 - Depósitos en Garantía de GLP - Distribuidores Inversionistas
B6: Eje X: | C6: N/A
B7: Eje Y: | C7: N/A
B8: Eje Z: | C8: Periodo Actual
D10: Trimestres [miembro]
D11: Trimestre Enero - Marzo [miembro] | E11: Trimestre Abril - Junio [miembro] | F11: Trimestre Julio - Septiembre [miembro] | G11: Trimestre Octubre - Diciembre [miembro]
B12: Formato Complementario - Depósitos en Garantía de GLP - Distribuidores Inversionistas [partidas]
C13: Valor de la Fiducia
C14: Valor Depósitos en Garantía
C15: PORCENTAJE

Sheet Hoja57
B2: Indice
B3: Archivo: | C3: I:\Proyectos2025\proyecto_niif\_backup_legacy\Grupo1_Individual_Directo_ID20037_2024-12-31.xbrl
B4: Empresa: | C4: 20037
B5: Vista: | C5: [900030] FC07 - Información sobre el cálculo actuarial
B6: Eje X: | C6: N/A
B7: Eje Y: | C7: N/A
B8: Eje Z: | C8: N/A
E10: Periodo Actual
B11: Formato Complementario 07 – Información sobre el cálculo actuarial
C12: Solicitud cálculo actuarial
D13: Representante legal
D14: NIT
D15: Domicilio
D16: Dirección
D17: Administración regional de impuestos que le corresponde
D18: Grandes contribuyentes (SI o NO)
C19: Nota técnica
D20: Nombre del actuario
D21: Identificacion
D22: Profesion
D23: Matrícula profesional de la persona natural o jurídica que elaboró el cálculo actuarial, matriculado como actuario
D24: Si pertenece a una persona Jurídica indique la Razón Social
D25: Si pertenece a una persona Jurídica indique el NIT
C26: Certificación
D27: Valor del cálculo actuarial
D28: Metodologia
D29: Procedimiento empleado
D30: Incremento del porcentaje acumulado de amortización respecto del año anterior
D31: Incremento del porcentaje anual de amortización respecto del año anterior

Sheet Hoja58
B2: Indice
B3: Archivo: | C3: I:\Proyectos2025\proyecto_niif\_backup_legacy\Grupo1_Individual_Directo_ID20037_2024-12-31.xbrl
B4: Empresa: | C4: 20037
B5: Vista: | C5: [900031] FC08 - Conciliación de ingresos
B6: Eje X: | C6: N/A
B7: Eje Y: | C7: N/A
B8: Eje Z: | C8: Periodo Actual
G10: Diligenciar en este formulario, en los conceptos que el PSPD considere, los valores que a su criterio conforman los ingresos de actividades ordinarias en desarrollo de su objeto social.
G11: Servicios [miembro]
G12: Acueducto [miembro] | H12: Alcantarillado [miembro] | I12: Aseo [miembro] | J12: Energía Eléctrica [miembro] | K12: Gas combustible por redes [miembro] | L12: Gas Licuado de Petróleo [miembro] | M12: Operador del sistema y Administrador del mercado de energia (XM) [miembro]
B13: Conciliación de ingresos [partidas]
C14: Ingresos de actividades ordinarias [sinopsis]
D15: Ingresos de actividades ordinarias procedentes de la venta de bienes [resumen]
E16: Ingresos de actividades ordinarias por venta de energía, gas natural, gas licuado de petróleo, agua
E17: Ingresos de actividades ordinarias por venta de aire propanado, combustibles, hidrocarburos, derivados de petróleo
E18: Ingresos de actividades ordinarias por venta de equipos de medición de servicios públicos domiciliarios
E19: Ingresos de actividades ordinarias por venta de redes internas o partes de ellas
E20: Ingresos de actividades ordinarias por venta de electrodomésticos
E21: Ingresos de actividades ordinarias por venta de equipos y materiales
E22: Ingresos de actividades ordinarias por venta de bienes diferentes a los descritos anteriormente
F23: Si reporta ingresos de actividades ordinarias por venta de otros bienes indique cuales [bloque de texto]
E24: Total ingresos de actividades ordinarias por venta de bienes | G24: =SUM(G16:G22) | H24: =SUM(H16:H22) | I24: =SUM(I16:I22) | J24: =SUM(J16:J22) | K24: =SUM(K16:K22) | L24: =SUM(L16:L22) | M24: =SUM(M16:M22)
D25: Ingresos de actividades ordinarias procedentes de la prestación de servicios [resumen]
E26: Ingresos de actividades ordinarias por prestación de servicios públicos domiciliarios
E27: Ingresos de actividades ordinarias por prestación de servicios de instalación de redes internas
E28: Ingresos de actividades ordinarias por prestación de servicios de mantenimiento de redes internas
E29: Ingresos de actividades ordinarias por prestación de servicios de asistencia técnica en servicios públicos domiciliarios
E30: Ingresos de actividades ordinarias por prestación de servicios de obras civiles relacionados con servicios públicos domiciliarios
E31: Ingresos de actividades ordinarias por cargo de conexión
E32: Ingresos de actividades ordinarias por honorarios, asesorías o comisiones por franquicias
E33: Ingresos de actividades ordinarias por cargo de confiabilidad
E34: Ingresos de actividades ordinarias por reconexiones
E35: Ingresos por almacenamiento relacionados con servicios públicos domiciliarios
E36: Ingresos de actividades ordinarias por arrendamientos relacionados con servicios públicos domiciliarios
E37: Ingresos de actividades ordinarias por reinstalaciones
... E44: Ingresos de actividades ordinarias por prestación de servicios diferentes a los descritos anteriormente
F45: Si reporta ingresos de actividades ordinarias por prestación de otros servicios indique cuales [bloque de texto]
E46: Total ingresos de actividades ordinarias por prestación de servicios | G46: =SUM(G26:G40)+G44 | H46: =SUM(H26:H40)+H44 | I46: =SUM(I26:I40)+I44 | J46: =SUM(J26:J40)+J44 | K46: =SUM(K26:K40)+K44 | L46: =SUM(L26:L40)+L44 | M46: =SUM(M26:M44)
D47: Ingresos de actividades ordinarias por intereses [resumen]
E48: Ingresos de actividades ordinarias por intereses de financiación
E49: Ingresos de actividades ordinarias por intereses de mora
E50: Total de ingresos de actividades ordinarias por intereses | G50: =G48+G49 | H50: =H48+H49 | I50: =I48+I49 | J50: =J48+J49 | K50: =K48+K49 | L50: =L48+L49 | M50: =M48+M49
D51: Ingresos de actividades ordinarias por dividendos
D52: Utilidad de actividades ordinarias en venta de propiedad, planta y equipo (Redes, cables, plantas, y otros directamente relacionados con el servicio público domiciliario)
D53: Ingresos de actividades ordinarias por contratos de operación
D54: Ingresos de actividades ordinarias por contratos de concesión
D55: Ingresos de actividades ordinarias por contratos de cuentas en participación
D56: Ingresos de actividades ordinarias por publicidad
D57: Otros ingresos de actividades ordinarias
E58: Si reporta otros ingresos de actividades ordinarias indique cuáles [bloque de texto]
D59: Total de ingresos de actividades ordinarias | G59: =G24+G46+SUM(G50:G57) | H59: =H24+H46+SUM(H50:H57) | I59: =I24+I46+SUM(I50:I57) | J59: =J24+J46+SUM(J50:J57) | K59: =K24+K46+SUM(K50:K57) | L59: =L24+L46+SUM(L50:L57) | M59: =M24+M46+SUM(M50:M57)
C60: Ingresos que no son considerados de actividades ordinarias [sinopsis]
D61: Ingresos que no son considerados de actividades ordinarias
C62: Total Ingresos | G62: =G59+G61 | H62: =H59+H61 | I62: =I59+I61 | J62: =J59+J61 | K62: =K59+K61 | L62: =L59+L61 | M62: =M59+M61

Sheet Hoja59
B2: Indice
B3: Archivo: | C3: I:\Proyectos2025\proyecto_niif\_backup_legacy\Grupo1_Individual_Directo_ID20037_2024-12-31.xbrl
B4: Empresa: | C4: 20037
B5: Vista: | C5: [900032] FC09 - Detalle de costo de ventas
B6: Eje X: | C6: N/A
B7: Eje Y: | C7: N/A
B8: Eje Z: | C8: Periodo Actual
F10: Diligencie en este formulario la composición del Costo de Ventas, solo sì el detalle del gasto operativo del formulario FC01 es diferente del costo de ventas en el estado de resultados.
F11: Servicios [miembro]
F12: Acueducto [miembro] | G12: Alcantarillado [miembro] | H12: Aseo [miembro] | I12: Energía Eléctrica [miembro] | J12: Gas combustible por redes [miembro] | K12: Gas Licuado de Petróleo [miembro] | L12: Operador del sistema y Administrador del mercado de energia (XM) [miembro]
B13: Conciliación entre gastos por función y por naturaleza [partidas]
C14: Gastos por función [resumen]
D15: Costo de ventas
C16: Gastos [resumen]
D17: Beneficios a empleados
D18: Honorarios
D19: Impuestos, Tasas y Contribuciones (No incluye impuesto de renta)
D20: Generales
D21: Deterioro
D22: Depreciación
D23: Amortización
D24: Provisiones [resumen]
E25: Litigios y demandas
E26: Garantías
E27: Diversas
E28: Total gastos de provisiones | F28: =SUM(F25:F27) | G28: =SUM(G25:G27) | H28: =SUM(H25:H27) | I28: =SUM(I25:I27) | J28: =SUM(J25:J27) | K28: =SUM(K25:K27) | L28: =SUM(L25:L27)
D29: Arrendamientos
D30: Otros Gastos [resumen]
E31: Comisiones
E32: Ajuste por diferencia en cambio
E33: Financieros
E34: Pérdidas por aplicación del método de participación patrimonial
E35: Gastos diversos
E36: Donaciones
E37: Total otros gastos | F37: =SUM(F31:F36) | G37: =SUM(G31:G36) | H37: =SUM(H31:H36) | I37: =SUM(I31:I36) | J37: =SUM(J31:J36) | K37: =SUM(K31:K36) | L37: =SUM(L31:L36)
D38: Impuesto a las ganancias corrientes
D39: Impuesto a las ganancias diferido
D40: Bienes y servicios públicos para la venta [resumen]
E41: Compras en bloque y/o a largo plazo
E42: Compras en bolsa y/o a corto plazo
E43: Gastos por suministro de agua potable (agua en bloque)
E44: Gastos de conexión
E45: Uso de Líneas, redes y ductos
E46: Gastos de distribución y/o comercialización de gas combustible por redes
E47: Manejo comercial y financiero del servicio
E48: Gastos de distribución y/o comercialización de gas licuado de petróleo – GLP
E49: Contrato de explotación
E50: Gastos asociados a las transacciones en el mercado mayorista
E51: Contrato de concesión
E52: Otros gastos bienes y servicios públicos para la venta
E53: Gastos asociados a las transacciones en el mercado minorista
E54: Total de bienes y servicios públicos para la venta | F54: =SUM(F41:F53) | G54: =SUM(G41:G53) | H54: =SUM(H41:H53) | I54: =SUM(I41:I53) | J54: =SUM(J41:J53) | K54: =SUM(K41:K53) | L54: =SUM(L41:L53)
D55: Licencias, contribuciones y regalías [resumen]
E56: Secretaría Distrital del Medio Ambiente
E57: Ley 56 de 1981
E58: Medio Ambiente – Ley 99 de 1993
E59: Regalías
E60: Licencia De Operación Del Servicio
E61: FAZNI
E62: FAER
E63: Cuota de Fomento de gas
E64: Comité De Estratificación –Ley 505 De 1999
E65: Art 25 - Ley 142 - Concesiones, y permisos ambientales y sanitarios
E66: Otras licencias Ley 142 de 1994
E67: Total licencias, contribuciones y regalías | F67: =SUM(F56:F66) | G67: =SUM(G56:G66) | H67: =SUM(H56:H66) | I67: =SUM(I56:I66) | J67: =SUM(J56:J66) | K67: =SUM(K56:K66) | L67: =SUM(L56:L66)
D68: Consumo de Insumos Directos [resumen]
E69: Productos Químicos
E70: Gas Combustible
E71: Carbón Mineral
E72: Energía
E73: ACPM, Fuel Oil
E74: Otros Elementos de Consumo de Insumos Directos
E75: Total consumo de insumos directos | F75: =SUM(F69:F74) | G75: =SUM(G69:G74) | H75: =SUM(H69:H74) | I75: =SUM(I69:I74) | J75: =SUM(J69:J74) | K75: =SUM(K69:K74) | L75: =SUM(L69:L74)
D76: Ordenes y contratos de mantenimiento y reparaciones
D77: Peajes terrestres
D78: Disposición final
D79: Peajes por interconexión de acueductos
D80: Peajes por interconexión de alcantarillado
D81: Servicios públicos
D82: Materiales y otros gastos de operación
D83: Pérdidas en prestación del servicio de acueducto
D84: Seguros
D85: Órdenes y contratos por otros servicios
D86: Total gastos | F86: =SUM(F17:F23)+F28+F29+SUM(F37:F39)+F54+F67+SUM(F75:F85) | G86: =SUM(G17:G23)+G28+G29+SUM(G37:G39)+G54+G67+SUM(G75:G85) | H86: =SUM(H17:H23)+H28+H29+SUM(H37:H39)+H54+H67+SUM(H75:H85) | I86: =SUM(I17:I23)+I28+I29+SUM(I37:I39)+I54+I67+SUM(I75:I85) | J86: =SUM(J17:J23)+J28+J29+SUM(J37:J39)+J54+J67+SUM(J75:J85) | K86: =SUM(K17:K23)+K28+K29+SUM(K37:K39)+K54+K67+SUM(K75:K85) | L86: =SUM(L17:L23)+L28+L29+SUM(L37:L39)+L54+L67+SUM(L75:L85)

Sheet Hoja60
B2: Indice
B3: Archivo: | C3: I:\Proyectos2025\proyecto_niif\_backup_legacy\Grupo1_Individual_Directo_ID20037_2024-12-31.xbrl
B4: Empresa: | C4: 20037
B5: Vista: | C5: [900040] FC15 - Información sobre el cálculo del IUS
B6: Eje X: | C6: N/A
B7: Eje Y: | C7: N/A
B8: Eje Z: | C8: Periodo Actual
E10: La información contenida en el presente formato es en cumplimiento de lo establecido en la Resolución CRA 906 de 2019 para el cálculo del IUS, para los prestadores de acueducto y/o alcantarillado
E11: Servicios [miembro] | H11: Información adicional [miembro]
E12: Acueducto [miembro] | F12: Alcantarillado [miembro] | G12: Total Empresa [miembro]
B13: Información sobre el cálculo del IUS
C14: Caracterización
D15: Clasifique su empresa de acuerdo al segmento establecido en la resolución CRA 906 de 2019
D16: ¿Tiene calificación crediticia con grado de inversión AAA a largo plazo, emitida por una calificadora de riesgo para el periodo de reporte? Seleccione de la lista, Sí o No.
C17: Variables
D18: RI: Recaudo en el periodo de evaluación
D19: If: Ingresos facturados en el periodo de evaluación
D20: CGGS: Costos y gastos totales destinados a la gestión social
D21: ICMI: Ingreso causado por concepto de Costo Medio de Inversión - CMI derivados del POIR para el servicio público
D22: ICMO: Ingreso causado por concepto de Costo Medio de Operación - CMO: por APS, durante el periodo de evaluación, para el servicio público
D23: ICMA: Ingreso causado por concepto de Costo Medio de Administración - CMA: por APS, durante el periodo de evaluación, para el servicio público
D24: TUR_AC: Gasto por concepto de Tasa de uso de agua
D25: TUR_AL: Gasto por concepto de Tasa retributiva
D26: COA: Costos operativos y gastos de administración
D27: SDNC: Servicio de deuda no corriente

Sheet Hoja61
B2: Indice
B3: Archivo: | C3: I:\Proyectos2025\proyecto_niif\_backup_legacy\Grupo1_Individual_Directo_ID20037_2024-12-31.xbrl
B4: Empresa: | C4: 20037
B5: Vista: | C5: [900080] FC30 - Ingreso por tarifa y comercialización de aprovechamiento
B6: Eje X: | C6: N/A
B7: Eje Y: | C7: N/A
B8: Eje Z: | C8: Periodo Actual
D10: La información contenida en el presente formato debe ser diligenciada de acuerdo a la información reportada mes a mes
D11: Aprovechamiento [miembro]
D12: Ingreso por tarifa [miembro] | E12: Ingreso por comercialización de material [miembro]
B13: Información detallada por tarifa y comercialización de aprovechamiento
C14: Del 1 al 31 de Enero
C15: Del 1 al 28 de Febrero
C16: Del 1 al 31 de Marzo
C17: Del 1 al 30 de Abril
C18: Del 1 al 31 de Mayo
C19: Del 1 al 30 de Junio
C20: Del 1 al 31 de Julio
C21: Del 1 al 31 de Agosto
C22: Del 1 al 30 de Septiembre
C23: Del 1 al 31 de Octubre
C24: Del 1 al 30 de Noviembre
C25: Del 1 al 31 de Diciembre

Sheet Hoja62
B2: Indice
B3: Archivo: | C3: I:\Proyectos2025\proyecto_niif\_backup_legacy\Grupo1_Individual_Directo_ID20037_2024-12-31.xbrl
B4: Empresa: | C4: 20037
B5: Vista: | C5: [900090] FC40 - Pagos tarifa de aprovechamiento a recicladores
B6: Eje X: | C6: N/A
B7: Eje Y: | C7: N/A
B8: Eje Z: | C8: Periodo Actual
D10: La información contenida en el presente formato debe ser diligenciada de acuerdo a la información reportada mes a mes
D11: Aprovechamiento [miembro]
D12: Pago mensual a recicladores [miembro]
B13: Información detallada de pagos a recicladores por tarifa de aprovechamiento
C14: Del 1 al 31 de Enero
C15: Del 1 al 28 de Febrero
C16: Del 1 al 31 de Marzo
C17: Del 1 al 30 de Abril
C18: Del 1 al 31 de Mayo
C19: Del 1 al 30 de Junio
C20: Del 1 al 31 de Julio
C21: Del 1 al 31 de Agosto
C22: Del 1 al 30 de Septiembre
C23: Del 1 al 31 de Octubre
C24: Del 1 al 30 de Noviembre
C25: Del 1 al 31 de Diciembre

Sheet Hoja63
B2: Indice
B3: Archivo: | C3: I:\Proyectos2025\proyecto_niif\_backup_legacy\Grupo1_Individual_Directo_ID20037_2024-12-31.xbrl
B4: Empresa: | C4: 20037
B5: Vista: | C5: [900100] FC50 - Detalle de ventas a comercializadores de materiales aprovechables
B6: Eje X: | C6: N/A
B7: Eje Y: | C7: N/A
B8: Eje Z: | C8: Periodo Actual
C10: Detalle de ventas a comercializadores de materiales de aprovechamiento [Resumen]
C11: Tipo de identificación del comercializador | D11: Nit del comercializador | E11: Nombre o Razón social del comercializador | F11: Del 1 al 31 de Enero | G11: Del 1 al 28 de Febrero | H11: Del 1 al 31 de Marzo | I11: Del 1 al 30 de Abril | J11: Del 1 al 31 de Mayo | K11: Del 1 al 30 de Junio | L11: Del 1 al 31 de Julio | M11: Del 1 al 31 de Agosto | N11: Del 1 al 30 de Septiembre | O11: Del 1 al 31 de Octubre | P11: Del 1 al 30 de Noviembre | Q11: Del 1 al 31 de Diciembre
B12: # Fila comercializador de materiales

Sheet Hoja64
B2: Indice
B3: Archivo: | C3: I:\Proyectos2025\proyecto_niif\_backup_legacy\Grupo1_Individual_Directo_ID20037_2024-12-31.xbrl
B4: Empresa: | C4: 20037
B5: Vista: | C5: [900110] FC60 - Porcentaje de provisión de la tarifa de aprovechamiento
B6: Eje X: | C6: N/A
B7: Eje Y: | C7: N/A
B8: Eje Z: | C8: Periodo Actual
D10: Información detallada del porcentaje de provisión por tarifa de aprovechamiento
D11: Año | E11: Porcentaje de provisión que aplicó con respecto al valor de la tarifa de aprovechamiento (%) | F11: Valor en pesos de la provisión que aplicó
B12: Fase de progresividad:
C13: Fase de progresividad cinco: 5
C14: Fase de progresividad seis: 6
C15: Fase de progresividad siete: 7
C16: Fase de progresividad ocho: 8
