Workbook
Name sspdtipos_TipoNaturalezaEEFF414IndSep: Lists!$B$3:$B$4
Name sspdtipos_TipoGradoRedondeo: Lists!$D$3:$D$6
Name sspdtipos_TipoSiNo: Lists!$F$3:$F$4
Name sspdtipos_TipoPeriodoDeReexpresion: Lists!$H$3:$H$5
Name sspdtipos_TipoIdentificacionResponsablesInformacion: Lists!$J$3:$J$5
Name sspdtipos_TipoDeDictamenDeAuditoria: Lists!$L$3:$L$10
Name sspdtipos_TipoClasificacionEmpresarialSegunResolucionCRA906Del2019: Lists!$N$3:$N$6
Name sspdtipos_TipoPeriodoFaseDeProgresividad: Lists!$P$3:$P$15

Sheet Indice
B2: Tabla de contenidos
B3: [110000] Información general sobre estados financieros
B4: [210000] Estado de situación financiera
B5: [310000] Estado de resultados
B6: [420000] Estado del resultado Integral, Componentes otro resultado integral, Antes de impuestos, individual
B7: [510000] Estado de flujos de efectivo, método directo, individual
B8: [610000] Estado de cambios en el patrimonio
B9: [800100] Notas - Subclasificaciones de activos, pasivos y patrimonios
B10: [800200] Notas - Análisis de ingresos y gastos
B11: [800500] Notas - Lista de Notas
B12: [800600] Notas - Lista de Políticas
B13: [810000] Notas - Información de la entidad y declaración de cumplimiento con el marco normativo
... B43: [900110] FC60 - Porcentaje de provisión de la tarifa de aprovechamiento

Sheet Hoja1
B2: Indice
B3: Archivo: | C3: I:\Proyectos2025\proyecto_niif\_backup_legacy\R414\R414Ind_ID20037_2024-12-31.xbrl
B4: Empresa: | C4: 20037
B5: Vista: | C5: [110000] Información general sobre estados financieros
B6: Eje X: | C6: N/A
B7: Eje Y: | C7: N/A
B8: Eje Z: | C8: N/A
E10: Periodo Actual
B11: Información a revelar sobre información general sobre los estados financieros [bloque de texto]
C12: Nombre de la entidad que informa u otras formas de identificación
C13: Identificación de la Empresa (ID RUPS)
C14: NIT
C15: Descripción de la naturaleza de los estados financieros
C16: Información a revelar sobre la naturaleza del negocio
C17: Fecha de inicio de operaciones (o fecha de constitución si no ha iniciado la prestación de servicios)
C18: Fecha de cierre del periodo sobre el que se informa
C19: Grado de redondeo utilizado en los estados financieros
C20: Detalle sobre este Informe
D21: ¿Estos estados financieros presentan información reexpresada?
D22: Periodo para el cual se presenta información reexpresada

Sheet Lists
B3: 1. Individual | D3: 1 - Pesos | F3: 1. Si | H3: 1. Reexpresión del patrimonio al inicio del periodo actual (Del patrimonio del periodo anterior) | J3: 01 - CÉDULA DE CIUDADANÍA | L3: NAGAS - 1. Limpio | N3: 1 - Grandes Prestadores | P3: 2018
B4: 2. Separado | D4: 2 - Miles de pesos | F4: 2. No | H4: 2. Reexpresión del patrimonio al inicio del periodo anterior (Del patrimonio de dos periodos atrás) | J4: 02 - CÉDULA DE EXTRANJERÍA | L4: NAGAS - 2. Con salvedad | N4: 2 - Pequeños Prestadores | P4: 2019
D5: 3 - Millones de pesos | H5: 3. Reexpresión del patrimonio al inicio de los periodos actual y anterior (Del patrimonio del periodo anterior y de dos periodos atrás) | J5: 03 - PASAPORTE | L5: NAGAS - 3. Negativo | N5: 3 - Prestadores Rurales | P5: 2020
D6: 4 - Pesos redondeada a miles | L6: NAGAS - 4. Abstención de opinión | N6: 4 - Esquema Diferencial | P6: 2021
L7: NIAS - 1. No modificada | P7: 2022
L8: NIAS - 2. Modificada; opinión con salvedades | P8: 2023
L9: NIAS - 3. Modificada; opinión desfavorable o adversa | P9: 2024
L10: NIAS - 4. Modificada; denegación o abstención de opinión | P10: 2025
P11: 2026
P12: 2027
P13: 2028
P14: 2029
P15: 2030

Sheet Hoja2
B2: Indice
B3: Archivo: | C3: I:\Proyectos2025\proyecto_niif\_backup_legacy\R414\R414Ind_ID20037_2024-12-31.xbrl
B4: Empresa: | C4: 20037
B5: Vista: | C5: [210000] Estado de situación financiera
B6: Eje X: | C6: N/A
B7: Eje Y: | C7: N/A
B9: Eje Z: | C9: Periodo Actual
I10: Total ESF por servicios
I11: Acueducto [miembro] | J11: Alcantarillado [miembro] | K11: Aseo [miembro] | L11: Energía Eléctrica [miembro] | M11: Gas combustible por redes [miembro] | N11: Gas Licuado de Petróleo [miembro] | O11: Otras actividades no vigiladas por la SSPD [miembro]
B12: Estado de situación financiera por servicio [partidas]
C13: Activos [resumen]
D14: Activos corrientes [resumen]
E15: Efectivo y equivalentes al efectivo | P15: =Hoja7!F53+Hoja7!F58+Hoja7!F59
F16: Efectivo y equivalentes al efectivo de uso restringido corriente
E17: Cuentas comerciales por cobrar y otras cuentas por cobrar corrientes [Resumen]
F18: Cuentas comerciales por cobrar por prestación de servicios públicos corrientes [Resumen]
G19: Cuentas comerciales por cobrar corrientes por prestación de servicios públicos corrientes (Sin incluir subsidios ni actividades de aprovechamiento)
G20: Cuentas comerciales por cobrar por subsidios corrientes
H21: Cuentas comerciales por cobrar corrientes del servicio público al Ministerio de Minas por concepto de subsidios
G22: Cuentas comerciales por cobrar por actividad de aprovechamiento corrientes
G23: Total cuentas comerciales por cobrar por prestación de servicios públicos corrientes | I23: =I19+I20 | J23: =J19+J20 | K23: =K19+K20+K22 | L23: =L19+L20 | M23: =M19+M20 | N23: =N19+N20 | P23: =P19+P20+P22
F24: Cuentas comerciales por cobrar por venta de bienes corrientes
F25: Cuentas por cobrar corrientes a partes relacionadas
F26: Otras cuentas por cobrar corrientes
F27: Total cuentas comerciales por cobrar y otras cuentas por cobrar corrientes | I27: =SUM(I23:I26) | J27: =SUM(J23:J26) | K27: =SUM(K23:K26) | L27: =SUM(L23:L26) | M27: =SUM(M23:M26) | N27: =SUM(N23:N26) | O27: =SUM(O23:O26) | P27: =SUM(P23:P26)
E28: Inventarios corrientes
E29: Activo por impuesto a las ganancias corriente
E30: Otros activos financieros corrientes
E31: Otros activos no financieros corrientes
E32: Activos corrientes totales | I32: =I15+SUM(I27:I31) | J32: =J15+SUM(J27:J31) | K32: =K15+SUM(K27:K31) | L32: =L15+SUM(L27:L31) | M32: =M15+SUM(M27:M31) | N32: =N15+SUM(N27:N31) | O32: =O15+SUM(O27:O31) | P32: =P15+SUM(P27:P31)
D33: Activos no corrientes [resumen]
E34: Propiedades, planta y equipo | P34: =Hoja7!F31-Hoja7!F32-Hoja7!F33
E35: Efectivo y equivalentes al efectivo - Efectivo de uso restringido
E36: Inversiones en controladas, negocios conjuntos y asociadas [resumen]
F37: Inversiones en asociadas
F38: Inversiones en negocios conjuntos
F39: Inversiones en controladas
F40: Total de Inversiones en controladas, negocios conjuntos y asociadas | I40: =SUM(I37:I39) | J40: =SUM(J37:J39) | K40: =SUM(K37:K39) | L40: =SUM(L37:L39) | M40: =SUM(M37:M39) | N40: =SUM(N37:N39) | O40: =SUM(O37:O39) | P40: =SUM(P37:P39)
E41: Cuentas comerciales por cobrar y otras cuentas por cobrar no corrientes [Resumen]
F42: Cuentas comerciales por cobrar por prestación de servicios públicos no corrientes [Resumen]
G43: Cuentas comerciales por cobrar no corrientes por prestación de servicios públicos corrientes (Sin incluir subsidios ni actividades de aprovechamiento)
G44: Cuentas comerciales por cobrar por subsidios no corrientes
H45: Cuentas comerciales por cobrar no corrientes del servicio público al Ministerio de Minas por concepto de subsidios
G46: Cuentas comerciales por cobrar por actividad de aprovechamiento no corrientes
G47: Total cuentas comerciales por cobrar por prestación de servicios públicos no corrientes | I47: =I43+I44 | J47: =J43+J44 | K47: =K43+K44+K46 | L47: =L43+L44 | M47: =M43+M44 | N47: =N43+N44 | P47: =P43+P44+P46
F48: Cuentas comerciales por cobrar por venta de bienes no corrientes
F49: Cuentas por cobrar no corrientes debidas por partes relacionadas
F50: Otras cuentas comerciales por cobrar no corrientes
F51: Total cuentas comerciales por cobrar y otras cuentas por cobrar no corrientes | I51: =SUM(I47:I50) | J51: =SUM(J47:J50) | K51: =SUM(K47:K50) | L51: =SUM(L47:L50) | M51: =SUM(M47:M50) | N51: =SUM(N47:N50) | O51: =SUM(O47:O50) | P51: =SUM(P47:P50)
E52: Inventarios no corrientes
E53: Activos por impuestos diferidos
E54: Detalle Otros activos no corrientes [resumen]
F55: Planes de activos
F56: Bienes y servicios pagados por anticipado
F57: Propiedad de inversión
F58: Bienes de arte y cultura
F59: Activos intangibles
F60: Activos biológicos no corrientes
F61: Otros activos
F62: Total Otros activos no corrientes | I62: =SUM(I55:I61) | J62: =SUM(J55:J61) | K62: =SUM(K55:K61) | L62: =SUM(L55:L61) | M62: =SUM(M55:M61) | N62: =SUM(N55:N61) | O62: =SUM(O55:O61) | P62: =SUM(P55:P61)
E63: Total de activos no corrientes | I63: =I34+I35+I40+SUM(I51:I53)+I62 | J63: =J34+J35+J40+SUM(J51:J53)+J62 | K63: =K34+K35+K40+SUM(K51:K53)+K62 | L63: =L34+L35+L40+SUM(L51:L53)+L62 | M63: =M34+M35+M40+SUM(M51:M53)+M62 | N63: =N34+N35+N40+SUM(N51:N53)+N62 | O63: =O34+O35+O40+SUM(O51:O53)+O62 | P63: =P34+P35+P40+SUM(P51:P53)+P62
D64: Total de activos | I64: =I63+I32 | J64: =J63+J32 | K64: =K63+K32 | L64: =L63+L32 | M64: =M63+M32 | N64: =N63+N32 | O64: =O63+O32 | P64: =P63+P32
C65: Patrimonio y pasivos [resumen]
D66: Pasivos [resumen]
E67: Pasivos corrientes [resumen]
F68: Disposiciones actuales [resumen]
G69: Provisiones corrientes por beneficios a los empleados
G70: Otras provisiones corrientes
G71: Total provisiones corrientes | I71: =I69+I70 | J71: =J69+J70 | K71: =K69+K70 | L71: =L69+L70 | M71: =M69+M70 | N71: =N69+N70 | O71: =O69+O70 | P71: =P69+P70
F72: Cuentas por pagar comerciales y otras cuentas por pagar corrientes [Resumen]
G73: Cuentas comerciales por pagar por adquisición de servicios orrientes
G74: Cuentas comerciales por pagar por adquisición de bienes corrientes
G75: Cuentas por pagar corrientes a partes relacionadas
G76: Otras cuentas comerciales por pagar corrientes
G77: Total cuentas comerciales por pagar y otras cuentas por pagar corrientes | I77: =SUM(I73:I76) | J77: =SUM(J73:J76) | K77: =SUM(K73:K76) | L77: =SUM(L73:L76) | M77: =SUM(M73:M76) | N77: =SUM(N73:N76) | O77: =SUM(O73:O76) | P77: =SUM(P73:P76)
F78: Emisión y colocación de títulos de deuda corrientes
F79: Préstamos por pagar
F80: Pasivo por impuesto a las ganancias corriente
F81: Detalle Otros pasivos corrientes [resumen]
G82: Ingresos recibidos por anticipado corrientes
G83: Pasivos por impuestos diferidos corrientes
G84: Otros pasivos diferidos corrientes
G85: Total Otros pasivos corrientes | I85: =SUM(I82:I84) | J85: =SUM(J82:J84) | K85: =SUM(K82:K84) | L85: =SUM(L82:L84) | M85: =SUM(M82:M84) | N85: =SUM(N82:N84) | O85: =SUM(O82:O84) | P85: =SUM(P82:P84)
F86: Otros pasivos financieros corrientes
F87: Otros pasivos no financieros corrientes
F88: Pasivos corrientes totales | I88: =I71+SUM(I77:I80)+SUM(I85:I87) | J88: =J71+SUM(J77:J80)+SUM(J85:J87) | K88: =K71+SUM(K77:K80)+SUM(K85:K87) | L88: =L71+SUM(L77:L80)+SUM(L85:L87) | M88: =M71+SUM(M77:M80)+SUM(M85:M87) | N88: =N71+SUM(N77:N80)+SUM(N85:N87) | O88: =O71+SUM(O77:O80)+SUM(O85:O87) | P88: =P71+SUM(P77:P80)+SUM(P85:P87)
E89: Pasivos no corrientes [resumen]
F90: Provisiones no corrientes [resumen]
G91: Provisiones no corrientes por beneficios a los empleados
G92: Otras provisiones no corrientes
G93: Total provisiones no corrientes | I93: =I91+I92 | J93: =J91+J92 | K93: =K91+K92 | L93: =L91+L92 | M93: =M91+M92 | N93: =N91+N92 | O93: =O91+O92 | P93: =P91+P92
F94: Cuentas por pagar comerciales y otras cuentas por pagar no corrientes [Resumen]
G95: Cuentas comerciales por pagar por adquisición de bienes no corrientes
G96: Cuentas comerciales por pagar por adquisición de servicios no corrientes
G97: Cuentas por pagar partes relacionadas no corrientes
G98: Otras cuentas comerciales por pagar no corrientes
G99: Total cuentas comerciales por pagar y otras cuentas por pagar no corrientes | I99: =SUM(I95:I98) | J99: =SUM(J95:J98) | K99: =SUM(K95:K98) | L99: =SUM(L95:L98) | M99: =SUM(M95:M98) | N99: =SUM(N95:N98) | O99: =SUM(O95:O98) | P99: =SUM(P95:P98)
F100: Emisión y colocación de títulos de deuda no corrientes
F101: Pasivos por préstamos por pagar
F102: Pasivo por impuestos corriente, no corriente
...

Sheet Hoja3
B2: Indice
B3: Archivo: | C3: I:\Proyectos2025\proyecto_niif\_backup_legacy\R414\R414Ind_ID20037_2024-12-31.xbrl
B4: Empresa: | C4: 20037
B5: Vista: | C5: [310000] Estado de resultados
B6: Eje X: | C6: N/A
B7: Eje Y: | C7: N/A
B9: Eje Z: | C9: Periodo Actual
E10: Total ER por servicios
E11: Acueducto [miembro] | F11: Alcantarillado [miembro] | G11: Aseo [miembro] | H11: Energía Eléctrica [miembro] | I11: Gas combustible por redes [miembro] | J11: Gas Licuado de Petróleo [miembro] | K11: Otras actividades no vigiladas por la SSPD [miembro]
B12: Estado de resultados por servicio [partidas]
C13: Ganancia (pérdida) [resumen]
D14: Ingresos de actividades ordinarias
D15: Costo de ventas
D16: Ganancia bruta | E16: =-E15+E14 | F16: =-F15+F14 | G16: =-G15+G14 | H16: =-H15+H14 | I16: =-I15+I14 | J16: =-J15+J14 | K16: =-K15+K14 | L16: =-L15+L14
D17: Otros ingresos
D18: Gastos de administración, operación y ventas
D19: Ingresos financieros
D20: Costos financieros
D21: Perdida por aplicación del método de participación patrimonial
D22: Otros gastos
D23: Otras ganancias (pérdidas)
D24: Ganancia (pérdida), antes de impuestos | E24: =E16+E17-E18+E19-SUM(E20:E22)+E23 | F24: =F16+F17-F18+F19-SUM(F20:F22)+F23 | G24: =G16+G17-G18+G19-SUM(G20:G22)+G23 | H24: =H16+H17-H18+H19-SUM(H20:H22)+H23 | I24: =I16+I17-I18+I19-SUM(I20:I22)+I23 | J24: =J16+J17-J18+J19-SUM(J20:J22)+J23 | K24: =K16+K17-K18+K19-SUM(K20:K22)+K23 | L24: =L16+L17-L18+L19-SUM(L20:L22)+L23
D25: Gasto / Ingreso impuesto a las ganancias corriente
D26: Gasto / Ingreso impuesto a las ganancias diferido
D27: Ganancia (pérdida) | E27: =E24-E25-E26 | F27: =F24-F25-F26 | G27: =G24-G25-G26 | H27: =H24-H25-H26 | I27: =I24-I25-I26 | J27: =J24-J25-J26 | K27: =K24-K25-K26 | L27: =L24-L25-L26
B29: Eje Z: | C29: Periodo Anterior
E30: Total ER por servicios
E31: Acueducto [miembro] | F31: Alcantarillado [miembro] | G31: Aseo [miembro] | H31: Energía Eléctrica [miembro] | I31: Gas combustible por redes [miembro] | J31: Gas Licuado de Petróleo [miembro] | K31: Otras actividades no vigiladas por la SSPD [miembro]
B32: Estado de resultados por servicio [partidas]
C33: Ganancia (pérdida) [resumen]
D34: Ingresos de actividades ordinarias
D35: Costo de ventas
D36: Ganancia bruta | E36: =-E35+E34 | F36: =-F35+F34 | G36: =-G35+G34 | H36: =-H35+H34 | I36: =-I35+I34 | J36: =-J35+J34 | K36: =-K35+K34 | L36: =-L35+L34
D37: Otros ingresos
D38: Gastos de administración, operación y ventas
D39: Ingresos financieros
D40: Costos financieros
D41: Perdida por aplicación del método de participación patrimonial
D42: Otros gastos
D43: Otras ganancias (pérdidas)
D44: Ganancia (pérdida), antes de impuestos | E44: =E36+E37-E38+E39-SUM(E40:E42)+E43 | F44: =F36+F37-F38+F39-SUM(F40:F42)+F43 | G44: =G36+G37-G38+G39-SUM(G40:G42)+G43 | H44: =H36+H37-H38+H39-SUM(H40:H42)+H43 | I44: =I36+I37-I38+I39-SUM(I40:I42)+I43 | J44: =J36+J37-J38+J39-SUM(J40:J42)+J43 | K44: =K36+K37-K38+K39-SUM(K40:K42)+K43 | L44: =L36+L37-L38+L39-SUM(L40:L42)+L43
D45: Gasto / Ingreso impuesto a las ganancias corriente
D46: Gasto / Ingreso impuesto a las ganancias diferido
D47: Ganancia (pérdida) | E47: =E44-E45-E46 | F47: =F44-F45-F46 | G47: =G44-G45-G46 | H47: =H44-H45-H46 | I47: =I44-I45-I46 | J47: =J44-J45-J46 | K47: =K44-K45-K46 | L47: =L44-L45-L46

Sheet Hoja4
B2: Indice
B3: Archivo: | C3: I:\Proyectos2025\proyecto_niif\_backup_legacy\R414\R414Ind_ID20037_2024-12-31.xbrl
B4: Empresa: | C4: 20037
B5: Vista: | C5: [420000] Estado del resultado Integral, Componentes otro resultado integral, Antes de impuestos, individual
B6: Eje X: | C6: N/A
B7: Eje Y: | C7: N/A
B8: Eje Z: | C8: N/A
G10: Periodo Actual | H10: Periodo Anterior
B11: Resultado de periodo [resumen]
C12: Ganancia (pérdida) | G12: =Hoja3!L24-Hoja3!L25-Hoja3!L26 | H12: =Hoja3!L44-Hoja3!L45-Hoja3!L46
D13: Otro resultado integral [resumen]
E14: Otro Resultado Integral | G14: =G38+G26 | H14: =H38+H26
F15: Ganancias o pérdidas actuariales y el rendimiento de los activos del plan de beneficios
F16: Total otro resultado integral que no se reclasificará al resultado del periodo, antes de impuestos | G16: =G15 | H16: =H15
E17: Componentes de otro resultado integral que se reclasificarán al resultado del periodo, antes de impuestos [resumen]
F18: Ganancias o pérdidas en inversiones de administracion de liquidez a valor razonable con cambios en el otro resultado integral acumuladas
F19: Ganancias o pérdidas por coberturas de flujos de efectivo acumuladas
F20: Ganancias o pérdidas por cobertura de una inversión neta de un negocio en el extranjero acumuladas
F21: Ganancias o pérdidas por conversión de estados financieros acumuladas
F22: Total otro resultado integral que se reclasificará al resultado del periodo, antes de impuestos | G22: =SUM(G18:G21) | H22: =SUM(H18:H21)
E23: Ganancias o pérdidas por la aplicación del método de participación patrimonial de inversiones en controladas acumuladas
E24: Ganancias o pérdidas por la aplicación del método de participación patrimonial de inversiones en asociadas acumuladas
E25: Ganancias o pérdidas por la aplicación del método de participación patrimonial de inversiones en negocios conjuntos acumuladas
D26: Resultado integral total, antes de impuestos | G26: =G16+SUM(G22:G25) | H26: =H16+SUM(H22:H25)
E27: Impuestos a las ganancias relativos a componentes de otro resultado integral que no se reclasificará al resultado del periodo [resumen]
F28: Impuestos a las ganancias relativos a ganancias (pérdidas) actuariales y el rendimiento de los activos del plan de beneficios
F29: Total impuestos a las ganancias relativos a componentes de otro resultado integral que no se reclasificará al resultado del periodo | G29: =G28 | H29: =H28
D30: Impuestos a las ganancias relativos a componentes de otro resultado integral que se reclasificará al resultado del periodo [resumen]
E31: Impuestos a las ganancias relativos a Ganancias o pérdidas en inversiones de administracion de liquidez a valor razonable con cambios en el otro resultado integral acumuladas
E32: Impuestos a las ganancias relativos a Ganancias o pérdidas por coberturas de flujos de efectivo acumuladas
E33: Ganancias o pérdidas por cobertura de una inversión neta de un negocio Impuestos a las ganancias relativos a en el extranjero acumuladas
E34: Impuestos a las ganancias relativos a Ganancias o pérdidas por conversión de estados financieros acumuladas
E35: Total impuestos a las ganancias relativos a componentes de otro resultado integral que se reclasificará al resultado del periodo | G35: =SUM(G31:G34) | H35: =SUM(H31:H34)
D36: Impuestos a las ganancias relativo a Ganancias o pérdidas por la aplicación del método de participación patrimonial de inversiones en controladas acumuladas
D37: Impuestos a las ganancias relativo a Ganancias o pérdidas por la aplicación del método de participación patrimonial de inversiones en asociadas acumuladas
D38: Total impuestos | G38: =G29+SUM(G35:G37) | H38: =H29+SUM(H35:H37)
D39: Otro Resultado Integral | G39: =G38+G26 | H39: =H38+H26
C40: Resultado integral total | G40: =G14+G12 | H40: =H14+H12

Sheet Hoja5
B2: Indice
B3: Archivo: | C3: I:\Proyectos2025\proyecto_niif\_backup_legacy\R414\R414Ind_ID20037_2024-12-31.xbrl
B4: Empresa: | C4: 20037
B5: Vista: | C5: [510000] Estado de flujos de efectivo, método directo, individual
B6: Eje X: | C6: N/A
B7: Eje Y: | C7: N/A
B9: Eje Z: | C9: Periodo Actual
F10: Total EFE
F11: Acueducto [miembro] | G11: Alcantarillado [miembro] | H11: Aseo [miembro] | I11: Energía Eléctrica [miembro] | J11: Gas combustible por redes [miembro] | K11: Gas Licuado de Petróleo [miembro] | L11: Otras actividades no vigiladas por la SSPD [miembro]
B12: Estado de Flujo de Efectivo por Servicio [partidas]
C13: Flujos de efectivo procedentes de (utilizados en) actividades de operación [resumen]
D14: Clases de cobros por actividades de operación [resumen]
E15: Cobros procedentes de las ventas de bienes y prestación de servicios
E16: Cobros procedentes de regalías, cuotas, comisiones y otros ingresos de actividades ordinarias
E17: Cobros derivados de contratos mantenidos para intermediación o para negociar con ellos
E18: Cobros procedentes de primas y prestaciones, anualidades y otros beneficios de pólizas suscritas
E19: Cobros por rentas y ventas posteriores de activos mantenidos para arrendar a terceros y posteriormente mantenidos para la venta
E20: Otros cobros por actividades de operación
D21: Clases de pagos en efectivo procedentes de actividades de operación [resumen]
E22: Pagos a proveedores por el suministro de bienes y servicios
E23: Pagos procedentes de contratos mantenidos para intermediación o para negociar
E24: Pagos a y por cuenta de los empleados
E25: Pagos por primas y prestaciones, anualidades y otras obligaciones derivadas de las pólizas suscritas
E26: Pagos por producir o adquirir activos mantenidos para arrendar a terceros y posteriormente mantenidos para la venta
E27: Pagos y devoluciones de impuestos sobre las ganancias (a menos que puedan clasificarse específicamente dentro de las actividades de inversión o financiación)
E28: Otros pagos por actividades de operación
D29: Flujos de efectivo netos procedentes (utilizados en) operaciones. | F29: =SUM(F15:F20)-SUM(F22:F28) | G29: =SUM(G15:G20)-SUM(G22:G28) | H29: =SUM(H15:H20)-SUM(H22:H28) | I29: =SUM(I15:I20)-SUM(I22:I28) | J29: =SUM(J15:J20)-SUM(J22:J28) | K29: =SUM(K15:K20)-SUM(K22:K28) | L29: =SUM(L15:L20)-SUM(L22:L28) | M29: =SUM(M15:M20)-SUM(M22:M28)
D30: Otros dividendos pagados
D31: Dividendos recibidos (solo para empresas financieras)
D32: Intereses pagados (solo para empresas financieras)
D33: Intereses recibidos (solo para empresas financieras)
D34: Impuestos a las ganancias reembolsados (pagados)
D35: Otras entradas (salidas) de efectivo, actividades de operación
D36: Flujos de efectivo netos procedentes de (utilizados en) actividades de operación | F36: =-F32+F29-F34-F30+F33+F31+F35 | G36: =-G32+G29-G34-G30+G33+G31+G35 | H36: =-H32+H29-H34-H30+H33+H31+H35 | I36: =-I32+I29-I34-I30+I33+I31+I35 | J36: =-J32+J29-J34-J30+J33+J31+J35 | K36: =-K32+K29-K34-K30+K33+K31+K35 | L36: =-L32+L29-L34-L30+L33+L31+L35 | M36: =-M32+M29-M34-M30+M33+M31+M35
C37: Flujos de efectivo procedentes de (utilizados en) actividades de inversión [resumen]
D38: Flujos de efectivo procedentes de la pérdida de control de subsidiarias u otros negocios
D39: Flujos de efectivo utilizados para obtener el control de subsidiarias u otros negocios
D40: Otros cobros por la venta y reembolsos de patrimonio o instrumentos de deuda de otras entidades
D41: Pagos por la adquisición de instrumentos de pasivo o patrimonio, emitidos por otras entidades
D42: Otros cobros por la venta de participaciones en negocios conjuntos
D43: Otros pagos para adquirir participaciones en negocios conjuntos
D44: Cobros por ventas de propiedades, planta y equipo y de otros activos a largo plazo
D45: Pagos por la adquisición de propiedades, planta y equipo
D46: Pagos por la adquisición de activos intangibles y de otros activos a largo plazo, incluidos aquellos relacionados con los costos de desarrollo capitalizados y la propiedades, planta y equipo construídas por la empresa para sí misma)
D47: Importes procedentes de ventas de activos intangibles
D48: Recursos por ventas de otros activos a largo plazo
D49: Importes procedentes de subvenciones del gobierno
... D58: Otras entradas (salidas) de efectivo en inversión
D59: Flujos de efectivo netos procedentes de (utilizados en) actividades de inversión | F59: =F38-F39+F40-F41+F42-F43+F44-F45-F46+SUM(F47:F49)-F50+F51-F52+F53+F54-F55+F56-F57+F58 | G59: =G38-G39+G40-G41+G42-G43+G44-G45-G46+SUM(G47:G49)-G50+G51-G52+G53+G54-G55+G56-G57+G58 | H59: =H38-H39+H40-H41+H42-H43+H44-H45-H46+SUM(H47:H49)-H50+H51-H52+H53+H54-H55+H56-H57+H58 | I59: =I38-I39+I40-I41+I42-I43+I44-I45-I46+SUM(I47:I49)-I50+I51-I52+I53+I54-I55+I56-I57+I58 | J59: =J38-J39+J40-J41+J42-J43+J44-J45-J46+SUM(J47:J49)-J50+J51-J52+J53+J54-J55+J56-J57+J58 | K59: =K38-K39+K40-K41+K42-K43+K44-K45-K46+SUM(K47:K49)-K50+K51-K52+K53+K54-K55+K56-K57+K58 | L59: =L38-L39+L40-L41+L42-L43+L44-L45-L46+SUM(L47:L49)-L50+L51-L52+L53+L54-L55+L56-L57+L58 | M59: =M38-M39+M40-M41+M42-M43+M44-M45-M46+SUM(M47:M49)-M50+M51-M52+M53+M54-M55+M56-M57+M58
C60: Flujos de efectivo procedentes de (utilizados en) actividades de financiación [resumen]
D61: Recursos por cambios en las participaciones en la propiedad en subsidiarias que no dan lugar a la pérdida de control
D62: Pagos por cambios en las participaciones en la propiedad en subsidiarias que no dan lugar a la pérdida de control
D63: Importes procedentes de la emisión de acciones
D64: Importes procedentes de la emisión de otros instrumentos de patrimonio
D65: Pagos por adquirir o rescatar las acciones de la entidad
D66: Pagos por otras participaciones en el patrimonio
D67: Importes procedentes de préstamos, emisión de obligaciones sin garantía, bonos y otros fondos tomados en préstamo, ya sea a corto o largo plazo
D68: Reembolsos de los fondos tomados en préstamos
D69: Pagos realizados por el arrendatario para reducir la deuda pendiente procedente de un arrendamiento financiero
D70: Importes procedentes de subvenciones del gobierno
D71: Otros intereses recibidos
D72: Intereses pagados (solo para empresas no financieras)
... D76: Otras entradas (salidas) de efectivo por actividades de financiación
D77: Flujos de efectivo netos procedentes de (utilizados en) actividades de financiación | F77: =F61-F62+F63+F64-F65-F66+F67-F68-F69+F70+F71-F72+F73-F74-F75+F76 | G77: =G61-G62+G63+G64-G65-G66+G67-G68-G69+G70+G71-G72+G73-G74-G75+G76 | H77: =H61-H62+H63+H64-H65-H66+H67-H68-H69+H70+H71-H72+H73-H74-H75+H76 | I77: =I61-I62+I63+I64-I65-I66+I67-I68-I69+I70+I71-I72+I73-I74-I75+I76 | J77: =J61-J62+J63+J64-J65-J66+J67-J68-J69+J70+J71-J72+J73-J74-J75+J76 | K77: =K61-K62+K63+K64-K65-K66+K67-K68-K69+K70+K71-K72+K73-K74-K75+K76 | L77: =L61-L62+L63+L64-L65-L66+L67-L68-L69+L70+L71-L72+L73-L74-L75+L76 | M77: =M61-M62+M63+M64-M65-M66+M67-M68-M69+M70+M71-M72+M73-M74-M75+M76
C78: Incremento (disminución) neto de efectivo y equivalentes al efectivo, antes del efecto de los cambios en la tasa de cambio | F78: =F77+F36+F59 | G78: =G77+G36+G59 | H78: =H77+H36+H59 | I78: =I77+I36+I59 | J78: =J77+J36+J59 | K78: =K77+K36+K59 | L78: =L77+L36+L59 | M78: =M77+M36+M59
C79: Efectos de la variación en la tasa de cambio sobre el efectivo y equivalentes al efectivo [resumen]
D80: Efectos de la variación en la tasa de cambio sobre el efectivo y equivalentes al efectivo
C81: Incremento (disminución) neto de efectivo y equivalentes al efectivo | F81: =F80+F78 | G81: =G80+G78 | H81: =H80+H78 | I81: =I80+I78 | J81: =J80+J78 | K81: =K80+K78 | L81: =L80+L78 | M81: =M80+M78
C82: Efectivo y equivalentes al efectivo al comienzo del periodo | M82: =Hoja2!P141
C83: Efectivo y equivalentes al efectivo al final del periodo | M83: =Hoja7!F53+Hoja7!F58+Hoja7!F59
B85: Eje Z: | C85: Periodo Anterior
F86: Total EFE
F87: Acueducto [miembro] | G87: Alcantarillado [miembro] | H87: Aseo [miembro] | I87: Energía Eléctrica [miembro] | J87: Gas combustible por redes [miembro] | K87: Gas Licuado de Petróleo [miembro] | L87: Otras actividades no vigiladas por la SSPD [miembro]
B88: Estado de Flujo de Efectivo por Servicio [partidas]
C89: Flujos de efectivo procedentes de (utilizados en) actividades de operación [resumen]
D90: Clases de cobros por actividades de operación [resumen]
E91: Cobros procedentes de las ventas de bienes y prestación de servicios
E92: Cobros procedentes de regalías, cuotas, comisiones y otros ingresos de actividades ordinarias
E93: Cobros derivados de contratos mantenidos para intermediación o para negociar con ellos
E94: Cobros procedentes de primas y prestaciones, anualidades y otros beneficios de pólizas suscritas
E95: Cobros por rentas y ventas posteriores de activos mantenidos para arrendar a terceros y posteriormente mantenidos para la venta
E96: Otros cobros por actividades de operación
D97: Clases de pagos en efectivo procedentes de actividades de operación [resumen]
E98: Pagos a proveedores por el suministro de bienes y servicios
E99: Pagos procedentes de contratos mantenidos para intermediación o para negociar
E100: Pagos a y por cuenta de los empleados
E101: Pagos por primas y prestaciones, anualidades y otras obligaciones derivadas de las pólizas suscritas
E102: Pagos por producir o adquirir activos mantenidos para arrendar a terceros y posteriormente mantenidos para la venta
E103: Pagos y devoluciones de impuestos sobre las ganancias (a menos que puedan clasificarse específicamente dentro de las actividades de inversión o financiación)
E104: Otros pagos por actividades de operación
D105: Flujos de efectivo netos procedentes (utilizados en) operaciones. | F105: =SUM(F91:F96)-SUM(F98:F104) | G105: =SUM(G91:G96)-SUM(G98:G104) | H105: =SUM(H91:H96)-SUM(H98:H104) | I105: =SUM(I91:I96)-SUM(I98:I104) | J105: =SUM(J91:J96)-SUM(J98:J104) | K105: =SUM(K91:K96)-SUM(K98:K104) | L105: =SUM(L91:L96)-SUM(L98:L104) | M105: =SUM(M91:M96)-SUM(M98:M104)
D106: Otros dividendos pagados
D107: Dividendos recibidos (solo para empresas financieras)
D108: Intereses pagados (solo para empresas financieras)
D109: Intereses recibidos (solo para empresas financieras)
D110: Impuestos a las ganancias reembolsados (pagados)
D111: Otras entradas (salidas) de efectivo, actividades de operación
D112: Flujos de efectivo netos procedentes de (utilizados en) actividades de operación | F112: =-F108+F105-F110-F106+F109+F107+F111 | G112: =-G108+G105-G110-G106+G109+G107+G111 | H112: =-H108+H105-H110-H106+H109+H107+H111 | I112: =-I108+I105-I110-I106+I109+I107+I111 | J112: =-J108+J105-J110-J106+J109+J107+J111 | K112: =-K108+K105-K110-K106+K109+K107+K111 | L112: =-L108+L105-L110-L106+L109+L107+L111 | M112: =-M108+M105-M110-M106+M109+M107+M111
C113: Flujos de efectivo procedentes de (utilizados en) actividades de inversión [resumen]
D114: Flujos de efectivo procedentes de la pérdida de control de subsidiarias u otros negocios
...

Sheet Hoja6
B2: Indice
B3: Archivo: | C3: I:\Proyectos2025\proyecto_niif\_backup_legacy\R414\R414Ind_ID20037_2024-12-31.xbrl
B4: Empresa: | C4: 20037
B5: Vista: | C5: [610000] Estado de cambios en el patrimonio
B6: Eje X: | C6: N/A
B7: Eje Y: | C7: N/A
B9: Eje Z: | C9: Periodo Actual
F10: Patrimonio [miembro]
F11: Aportes sociales [miembro] | G11: Capital suscrito y pagado [miembro] | H11: Capital fiscal [miembro] | I11: Prima en colocación de acciones cuotas o partes de interés social [miembro] | J11: Reserva Legal [miembro] | K11: Otras reservas [miembro] | L11: Dividendos y participaciones decretadas en especie [miembro] | M11: Ganancias acumuladas[miembro] | N11: Impactos por la transición al nuevo marco de regulación [miembro] | O11: Otras partidas patrimoniales (ORI) [miembro]
O12: Reservas actuariales y el rendimiento de los activos del plan de beneficios [miembro] | P12: Reserva de inversiones de administracion de liquidez a valor razonable con cambios en el otro resultado integral [miembro] | Q12: Reserva por coberturas de flujos de efectivo [miembro] | R12: Reserva por cobertura de una inversión neta de un negocio en el extranjero en el extranjero [miembro] | S12: Reserva por conversión de estados financieros [miembro] | T12: Reserva por la aplicación del método de participación patrimonial de inversiones en controladas [miembro] | U12: Reserva por la aplicación del método de participación patrimonial de inversiones en asociadas [miembro] | V12: Reserva por la aplicación del método de participación patrimonial de inversiones en negocios conjuntos [miembro]
B13: Estado de cambios en el patrimonio [partidas]
C14: Patrimonio al comienzo del periodo | X14: =SUM(Hoja2!P239:P247)+Hoja2!P257
C15: Incremento (disminución) por cambios en políticas contables
C16: Incremento (disminución) por correcciones de errores
C17: Patrimonio al comienzo del periodo incluyendo reexpresión. (Si la hubo)
C18: Cambios en el patrimonio [resumen]
D19: Resultado del ejercicio [resumen]
E20: Ganancia (pérdida) | X20: =Hoja3!L24-Hoja3!L25-Hoja3!L26
E21: Otro Resultado Integral | X21: =Hoja4!G38+Hoja4!G26
E22: Resultado integral total | F22: =F20+F21 | G22: =G20+G21 | H22: =H20+H21 | I22: =I20+I21 | J22: =J20+J21 | K22: =K20+K21 | L22: =L20+L21 | M22: =M20+M21 | ... X22: =X20+X21
D23: Emisión de patrimonio
D24: Dividendos reconocidos como distribuciones a los propietarios
D25: Incrementos (disminuciones) por otros cambios, patrimonio
D26: Total incremento (disminución) en el patrimonio | F26: =F22+F23-F24+F25 | G26: =G22+G23-G24+G25 | H26: =H22+H23-H24+H25 | I26: =I22+I23-I24+I25 | J26: =J22+J23-J24+J25 | K26: =K22+K23-K24+K25 | L26: =L22+L23-L24+L25 | M26: =M22+M23-M24+M25 | ... X26: =X22+X23-X24+X25
C27: Patrimonio al final del periodo | X27: =SUM(Hoja2!P113:P121)+Hoja2!P131
B29: Eje Z: | C29: Periodo Anterior
F30: Patrimonio [miembro]
F31: Aportes sociales [miembro] | G31: Capital suscrito y pagado [miembro] | H31: Capital fiscal [miembro] | I31: Prima en colocación de acciones cuotas o partes de interés social [miembro] | J31: Reserva Legal [miembro] | K31: Otras reservas [miembro] | L31: Dividendos y participaciones decretadas en especie [miembro] | M31: Ganancias acumuladas[miembro] | N31: Impactos por la transición al nuevo marco de regulación [miembro] | O31: Otras partidas patrimoniales (ORI) [miembro]
O32: Reservas actuariales y el rendimiento de los activos del plan de beneficios [miembro] | P32: Reserva de inversiones de administracion de liquidez a valor razonable con cambios en el otro resultado integral [miembro] | Q32: Reserva por coberturas de flujos de efectivo [miembro] | R32: Reserva por cobertura de una inversión neta de un negocio en el extranjero en el extranjero [miembro] | S32: Reserva por conversión de estados financieros [miembro] | T32: Reserva por la aplicación del método de participación patrimonial de inversiones en controladas [miembro] | U32: Reserva por la aplicación del método de participación patrimonial de inversiones en asociadas [miembro] | V32: Reserva por la aplicación del método de participación patrimonial de inversiones en negocios conjuntos [miembro]
B33: Estado de cambios en el patrimonio [partidas]
C34: Patrimonio al comienzo del periodo
C35: Incremento (disminución) por cambios en políticas contables
C36: Incremento (disminución) por correcciones de errores
C37: Patrimonio al comienzo del periodo incluyendo reexpresión. (Si la hubo)
C38: Cambios en el patrimonio [resumen]
D39: Resultado del ejercicio [resumen]
E40: Ganancia (pérdida) | X40: =Hoja3!L44-Hoja3!L45-Hoja3!L46
E41: Otro Resultado Integral | X41: =Hoja4!H38+Hoja4!H26
E42: Resultado integral total | F42: =F40+F41 | G42: =G40+G41 | H42: =H40+H41 | I42: =I40+I41 | J42: =J40+J41 | K42: =K40+K41 | L42: =L40+L41 | M42: =M40+M41 | ... X42: =X40+X41
D43: Emisión de patrimonio
D44: Dividendos reconocidos como distribuciones a los propietarios
D45: Incrementos (disminuciones) por otros cambios, patrimonio
D46: Total incremento (disminución) en el patrimonio | F46: =F42+F43-F44+F45 | G46: =G42+G43-G44+G45 | H46: =H42+H43-H44+H45 | I46: =I42+I43-I44+I45 | J46: =J42+J43-J44+J45 | K46: =K42+K43-K44+K45 | L46: =L42+L43-L44+L45 | M46: =M42+M43-M44+M45 | ... X46: =X42+X43-X44+X45
C47: Patrimonio al final del periodo | F47: =F14 | G47: =G14 | H47: =H14 | I47: =I14 | J47: =J14 | K47: =K14 | L47: =L14 | M47: =M14 | ... W47: =W14 | X47: =SUM(Hoja2!P239:P247)+Hoja2!P257

Sheet Hoja7
B2: Indice
B3: Archivo: | C3: I:\Proyectos2025\proyecto_niif\_backup_legacy\R414\R414Ind_ID20037_2024-12-31.xbrl
B4: Empresa: | C4: 20037
B5: Vista: | C5: [800100] Notas - Subclasificaciones de activos, pasivos y patrimonios
B6: Eje X: | C6: N/A
B7: Eje Y: | C7: N/A
B8: Eje Z: | C8: N/A
F10: Periodo Actual
B11: Subclasificaciones de activos, pasivos y patrimonios [resumen]
C12: Propiedades, planta y equipo [sinopsis]
D13: Terrenos y construcciones [sinopsis]
E14: Terrenos
E15: Edificios
E16: Total terrenos y edificios | F16: =F14+F15
D17: Maquinaria
D18: Vehículos
D19: Enseres y accesorios
D20: Equipo de oficina
D21: Construcciones en proceso
D22: Propiedades, planta y equipo, información especial [sinopsis]
E23: Vías
E24: Ductos
E25: Plantas
E26: Redes y cables
E27: Relleno sanitario
E28: Activos para generación de energía
E29: Total propiedades, planta y equipo, información especial | F29: =SUM(F23:F28)
D30: Otras propiedades, planta y equipo
D31: Total propiedades, planta y equipo, importe en libros en términos brutos | F31: =SUM(F16:F21)+F29+F30
D32: Depreciación acumulada propiedades, planta y equipo
D33: Deterioro de valor acumulado propiedades, planta y equipo
D34: Total de propiedades, planta y equipo | F34: =F31-F32-F33
C35: Activos intangibles y plusvalía [resumen]
D36: Activos intangibles distintos de la plusvalía [sinopsis]
E37: Marcas comerciales
E38: activos intangibles para exploración y evaluación
E39: Programas de computador
E40: Licencias y franquicias
E41: Derechos de propiedad intelectual, patentes y otros derechos de propiedad industrial, servicio y derechos de explotación
E42: Activos intangibles en desarrollo
E43: Otros activos intangibles
E44: Total de activos intangibles distintos de la plusvalía | F44: =SUM(F37:F43)
D45: Plusvalía
D46: Amortización acumulada activos intangibles y plusvalía
D47: Deterioro de valor acumulado activos intangibles y plusvalía
D48: Total activos intangibles y plusvalía | F48: =F44+F45-F46-F47
C49: Efectivo y equivalentes al efectivo [sinopsis]
D50: Efectivo [sinopsis]
E51: Efectivo en caja
E52: Saldos en bancos
E53: Total efectivo | F53: =F51+F52
D54: Equivalentes al efectivo [sinopsis]
E55: Depósitos a corto plazo, clasificados como equivalentes al efectivo
E56: Inversiones a corto plazo, clasificados como equivalentes al efectivo
E57: Otros acuerdos bancarios, clasificados como equivalentes al efectivo
E58: Total equivalentes al efectivo | F58: =SUM(F55:F57)
D59: Otro efectivo y equivalentes al efectivo
D60: Total efectivo y equivalentes al efectivo | F60: =F53+F58+F59
C61: Clases de otras provisiones [resumen]
D62: Provisiones por litigios y demandas [resumen]
E63: Provisiones por litigios y demandas no corriente
E64: Provisiones por litigios y demandas corriente
E65: Total de Provisiones por litigios y demandas | F65: =F63+F64
D66: Provisiones por contratos onerosos [resumen]
E67: Provisión por contratos onerosos no corriente
E68: Provisión corriente por contratos onerosos
E69: Total de provisiones por contratos onerosos | F69: =F67+F68
D70: Provisiones por costos de dejar fuera de servicio, restauración y rehabilitación [resumen]
E71: Provisión no corriente para costos de desmantelamiento, restauración y rehabilitación
E72: Provisión corriente para costos de desmantelamiento, restauración y rehabilitación
E73: Total de provisiones por costos de dejar fuera de servicio, restauración y rehabilitación | F73: =F71+F72
C74: Otras provisiones [resumen]
D75: Otras provisiones no corrientes | F75: =Hoja2!P92
D76: Otras provisiones corrientes | F76: =Hoja2!P70
D77: Total otras provisiones | F77: =F75+F76
C78: Beneficios a Empleados [resumen]
D79: Beneficios a Empleados a corto plazo
D80: Beneficios a Empleados a largo plazo
D81: Beneficios por terminación del vínculo laboral o contractual
D82: Beneficios posempleo
D83: Total Beneficios a empleados | F83: =SUM(F79:F82)

Sheet Hoja8
B2: Indice
B3: Archivo: | C3: I:\Proyectos2025\proyecto_niif\_backup_legacy\R414\R414Ind_ID20037_2024-12-31.xbrl
B4: Empresa: | C4: 20037
B5: Vista: | C5: [800200] Notas - Análisis de ingresos y gastos
B6: Eje X: | C6: N/A
B7: Eje Y: | C7: N/A
B8: Eje Z: | C8: N/A
E10: Periodo Actual
B11: Clases de gasto de beneficios a los empleados
C12: Beneficios a corto plazo
D13: Sueldos y salarios
C14: Beneficios a largo plazo
D15: Premios o bonificaciones por largo tiempo de servicio
C16: Beneficios por terminación del vínculo laboral o contractual.
D17: Beneficios de Ley
D18: Obligaciones implícitas
D19: Finalización anticipada de contrato
D20: Oferta de beneficios por terminación anticipada
C21: Beneficios posempleo.
D22: Pensiones a cargo de la empresa
D23: Seguros de vida, asistencia médica, cobertura educativa
C24: Total de gastos por beneficios a los empleados | E24: =E21+E12+E14+E16

Sheet Hoja9
B2: Indice
B3: Archivo: | C3: I:\Proyectos2025\proyecto_niif\_backup_legacy\R414\R414Ind_ID20037_2024-12-31.xbrl
B4: Empresa: | C4: 20037
B5: Vista: | C5: [800500] Notas - Lista de Notas
B6: Eje X: | C6: N/A
B7: Eje Y: | C7: N/A
B8: Eje Z: | C8: N/A
E10: Periodo Actual
B11: Información a revelar sobre notas y otra información explicativa [bloque de texto]
C12: Información a revelar sobre juicios y estimaciones contables [bloque de texto]
C13: Información a revelar sobre remuneración de los auditores [bloque de texto]
C14: Información a revelar sobre la autorización de los estados financieros [bloque de texto]
C15: Información a revelar sobre efectivo y equivalentes al efectivo [bloque de texto]
C16: Información a revelar sobre el estado de flujos de efectivo [bloque de texto]
C17: Información a revelar sobre activos contingentes [bloque de texto]
C18: Información a revelar sobre compromisos y pasivos contingentes [bloque de texto]
C19: Información a revelar sobre gastos por depreciación y amortización [bloque de texto]
C20: Información a revelar sobre instrumentos financieros derivados [bloque de texto]
C21: Información a revelar sobre el efecto de las variaciones en las tasas de cambio de la moneda extranjera [bloque de texto]
C22: Información a revelar sobre beneficios a los empleados [bloque de texto]
C23: Información a revelar sobre hechos ocurridos después del periodo sobre el que se informa [bloque de texto]
... C31: Información a revelar sobre subvenciones del gobierno [bloque de texto]
D32: Descripción de la naturaleza y cuantía de las subvenciones reconocidas
D33: Descripción de las condiciones cumplidas, por cumplir y otras contingencias relacionadas con las subvenciones condicionadas que no se hayan reconocido en resultados
D34: Periodos que cubre las subvención, así como los montos amortizados y por amortizar
D35: Descrición de las subvenciones a las que no se les haya podido asignar un valor
D36: Descripción de otro de tipo de ayudas gubernamentales de las cuales se haya beneficiado directamente la empresa
C37: Información a revelar sobre deterioro de valor de activos [bloque de texto]
C38: Información a revelar sobre impuestos a las ganancias [bloque de texto]
C39: Información a revelar sobre empleados [bloque de texto]
C40: Información a revelar sobre personal clave de la gerencia [bloque de texto]
C41: Información a revelar sobre activos intangibles [bloque de texto]
C42: Información a revelar sobre gastos por intereses [bloque de texto]
C43: Información a revelar sobre ingresos por intereses [bloque de texto]
C44: Información a revelar sobre inventarios [bloque de texto]
C45: Información a revelar sobre propiedades de inversión [bloque de texto]
C46: Información a revelar sobre inversiones contabilizadas utilizando el método de la participación [bloque de texto]
C47: Información a revelar sobre inversiones distintas de las contabilizadas utilizando el método de la participación [bloque de texto]
C48: Información a revelar sobre arrendamientos [bloque de texto]
... C67: Información a revelar sobre deudores comerciales y otras cuentas por cobrar [bloque de texto]

Sheet Hoja10
B2: Indice
B3: Archivo: | C3: I:\Proyectos2025\proyecto_niif\_backup_legacy\R414\R414Ind_ID20037_2024-12-31.xbrl
B4: Empresa: | C4: 20037
B5: Vista: | C5: [800600] Notas - Lista de Políticas
B6: Eje X: | C6: N/A
B7: Eje Y: | C7: N/A
B8: Eje Z: | C8: N/A
D10: Periodo Actual
B11: Información a revelar sobre un resumen de las políticas contables significativas [bloque de texto]
C12: Descripción de la política contable de activos financieros disponibles para la venta [bloque de texto]
C13: Descripción de la política contable para costos de financiación [bloque de texto]
C14: Descripción de la política contable para préstamos por pagar [bloque de texto]
C15: Descripción de la política contable para instrumentos financieros derivados [bloque de texto]
C16: Descripción de la política contable para beneficios a los empleados [bloque de texto]
C17: Descripción de la política contable para gastos [bloque de texto]
C18: Descripción de la política contable para conversión de moneda extranjera [bloque de texto]
C19: Descripción de la política contable para la moneda funcional [bloque de texto]
C20: Descripción de la política contable para la plusvalía [bloque de texto]
C21: Descripción de las políticas contables para subvenciones gubernamentales [bloque de texto]
C22: Descripción de la política contable para deterioro del valor de activos [bloque de texto]
C23: Descripción de la política contable para impuestos a las ganancias [bloque de texto]
... C43: Descripción de la política contable para el reconocimiento de ingresos por contratos de construcción [bloque de texto]

Sheet Hoja11
B2: Indice
B3: Archivo: | C3: I:\Proyectos2025\proyecto_niif\_backup_legacy\R414\R414Ind_ID20037_2024-12-31.xbrl
B4: Empresa: | C4: 20037
B5: Vista: | C5: [810000] Notas - Información de la entidad y declaración de cumplimiento con el marco normativo
B6: Eje X: | C6: N/A
B7: Eje Y: | C7: N/A
B8: Eje Z: | C8: N/A
E10: Periodo Actual
B11: Información a revelar sobre notas y otra información explicativa [bloque de texto]
C12: Nombre de la controladora última del grupo
C13: Ciudad donde se encuentra ubicada la sede administrativa
C14: Dirección de la sede administrativa de la entidad
C15: Email institucional
C16: Declaración explícita y sin reservas de cumplimiento del Marco Normativo para Entidades de Gobierno Resolución 414 CGN, el cual hace parte del Régimen de Contabilidad Pública [bloque de texto]
C17: Información a revelar sobre incertidumbres o cambios ordenados que comprometen su continuidad como supresión, fusión, escisión o liquidación
C18: Explicación de porqué no se presume que la actividad se llevara a cabo por tiempo indefinido
C19: Información a revelar sobre finalización de la prestación de los servicios inscritos en RUPS. [Resumen]
D20: Información a revelar sobre incertidumbres sobre la capacidad de dar continuidad a la prestación de uno o más servicios inscritos en RUPS
D21: ¿Durante el periodo sobre el que se informa se finalizó la prestación de uno o más servicios inscritos en RUPS?
D22: Detalle sobre la finalización de la prestación de los servicios inscritos en RUPS. (indicar servicio y fecha de finalización del servicio)
C23: Información a revelar sobre un resumen de las políticas contables significativas [bloque de texto]
D24: Explicación de los criterios de medición utilizados para preparar los estados financieros [bloque de texto]
D25: Descripción de otras políticas contables relevantes para comprender los estados financieros [bloque de texto]
D26: Explicación de supuestos realizados acerca del futuro y otras causas de incertidumbre en las estimaciones realizadas al final del periodo contable, que tengan un riesgo significativo de ocasionar ajustes importantes en el valor en libros de los activos o pasivos dentro del periodo contable siguiente.
C27: Información relacionada con Objetivos de Desarrollo Sostenible impulsadas por la Organización de Naciones Unidas [Abstracto]
D28: La entidad ha implementado programas, prácticas o políticas relacionados con objetivos de desarrollo sostenible?
D29: La entidad prepara reportes de sostenibilidad?
D30: Si lo presenta como reporte a una entidad de supervisión específica, a cuál?
D31: La entidad cuenta con objetivos de desarrollo sostenible para el eje económico?
D32: Mencione que indicadores calcula. Explique los elementos que componen cada indicador.

Sheet Hoja12
B2: Indice
B3: Archivo: | C3: I:\Proyectos2025\proyecto_niif\_backup_legacy\R414\R414Ind_ID20037_2024-12-31.xbrl
B4: Empresa: | C4: 20037
B5: Vista: | C5: [811001] Notas - Políticas contables, cambios en las estimaciones contables y errores
B6: Eje X: | C6: N/A
B7: Eje Y: | C7: N/A
B8: Eje Z: | C8: N/A
C10: Detalle de los cambios en políticas contables, estimaciones contables y errores [Resumen]
C11: Tipo de Cambio por politica, estimación o error | D11: Descripción del cambio en política, estimación o error | E11: Impacto en el activo por cambio por política, estimación o error | F11: Impacto en el pasivo por cambio por política, estimación o error | G11: Impacto en el patrimonio por cambio por política, estimación o error | H11: Impacto en el resultado por cambio por política, estimación o error
B12: # Fila de cambio por política, estimación o error

Sheet Hoja13
B2: Indice
B3: Archivo: | C3: I:\Proyectos2025\proyecto_niif\_backup_legacy\R414\R414Ind_ID20037_2024-12-31.xbrl
B4: Empresa: | C4: 20037
B5: Vista: | C5: [825701] Notas - Información a revelar detallada sobre partes relacionadas
B6: Eje X: | C6: N/A
B7: Eje Y: | C7: N/A
B8: Eje Z: | C8: Periodo Actual
C10: Detalle de la parte relacionada [Resumen]
C11: Tipo de parte relacionada | D11: Nombre de la parte relacionada | E11: NIT de la parte relacionada | F11: ID de Prestador de la parte relacionada (Si está vigilado por la Superservicios) | G11: Ciudad de domicilio de la parte relacionada | H11: País donde está constituida la parte relacionada | I11: Porcentaje de participación en la parte relacionada | J11: Si es asociada y su participación y/o derechos de voto son menores del 20% explique porque hay influencia significativa; si es mayor al 20% y no hay influencia significativa, explique porqué | K11: Valor en libros de la Inversión en parte relacionada | L11: Inversiones contabilizadas utilizando el método de la participación de la parte relacionada | M11: Riesgo asociado con su participación en la parte relacionada | N11: Nombre Controladora última del Grupo | O11: ID Controladora última del Grupo | P11: Nombre Controladora que emite Estados Financieros Consolidados disponible para uso público | Q11: Importe de las Cuentas por Cobrar con la parte relacionada | R11: Importe de las Cuentas por Pagar con la parte relacionada | S11: Importe de los Ingresos con la parte relacionada | T11: Importe de los Costos y Gastos con la parte relacionada | U11: Información a revelar sobre esta parte relacionada
B12: # Fila de parte relacionada

Sheet Hoja14
B2: Indice
B3: Archivo: | C3: I:\Proyectos2025\proyecto_niif\_backup_legacy\R414\R414Ind_ID20037_2024-12-31.xbrl
B4: Empresa: | C4: 20037
B5: Vista: | C5: [835110] Notas - Impuestos a las ganancias
B6: Eje X: | C6: N/A
B7: Eje Y: | C7: N/A
B8: Eje Z: | C8: N/A
F10: Periodo Actual
B11: Información a revelar sobre impuestos a las ganancias [bloque de texto]
C12: Principales componentes del gasto (ingreso) por impuestos [resumen]
D13: Gasto (ingreso) por impuestos corriente y ajustes por impuestos corrientes de periodos anteriores [resumen]
E14: Gasto (ingreso) por impuesto corriente
E15: Ajustes por impuestos corrientes de periodos anteriores
E16: Total gastos (ingresos) por impuestos corrientes y ajustes a impuestos corrientes de periodos anteriores | F16: =F14+F15
D17: Gasto (ingreso) por impuestos diferidos relacionado con el origen y reversión de diferencias temporarias
D18: Gasto (ingreso) por impuestos diferidos relacionado con cambios en las tasas fiscales o con la imposición de nuevos impuestos
D19: Gasto (ingreso) sobre el gasto por impuesto diferido originado por variaciones derivadas de una revisión de las autoridades fiscales
D20: Ajustes sobre el gasto por impuestos diferidos derivados de un cambio en la situación fiscal de la empresa
D21: Otros ajustes realizados, durante el periodo contable, a los activos por impuestos diferidos
D22: Gasto por impuestos relacionado con aplicación retroactiva por efecto de un cambio en política contable y con la reexpresión retroactiva por efecto de una corrección de errores de periodos anteriores
D23: Total de gasto (ingreso) por impuestos | F23: =SUM(F16:F22)

Sheet Hoja15
B2: Indice
B3: Archivo: | C3: I:\Proyectos2025\proyecto_niif\_backup_legacy\R414\R414Ind_ID20037_2024-12-31.xbrl
B4: Empresa: | C4: 20037
B5: Vista: | C5: [900010] Notas - Información a revelar sobre los responsables de la información financiera e información del AEGR
B6: Eje X: | C6: N/A
B7: Eje Y: | C7: N/A
B8: Eje Z: | C8: Periodo Actual
D10: Detalle [resumen]
D11: Nombres | E11: Apellidos | F11: Tipo de documento | G11: Número de documento | H11: Email | I11: Tarjeta profesional | J11: Si la persona natural actua como miembro de una persona jurídica, indique la razón social | K11: Si la persona natural actua como miembro de una persona jurídica, indique el NIT | L11: Tipo de norma de auditoría aplicada y tipo de dictamen
B12: Relación [miembro]
C13: Representante legal [miembro]
C14: Contador [miembro]
C15: Jefe de la oficina de control interno [miembro]
C16: Revisor fiscal [miembro]
C17: AEGR [miembro]

Sheet Hoja16
B2: Indice
B3: Archivo: | C3: I:\Proyectos2025\proyecto_niif\_backup_legacy\R414\R414Ind_ID20037_2024-12-31.xbrl
B4: Empresa: | C4: 20037
B5: Vista: | C5: [900017a] FC01-1 - Gastos de servicios públicos - Acueducto
B6: Eje X: | C6: N/A
B7: Eje Y: | C7: N/A
B8: Eje Z: | C8: Periodo Actual
E10: Acueducto [miembro]
E11: Gasto administrativo - Acueducto [miembro] | F11: Gasto operativo - Acueducto [miembro]
B12: Gastos [resumen]
C13: Beneficios a empleados
C14: Honorarios
C15: Impuestos, Tasas y Contribuciones (No incluye impuesto de renta)
C16: Generales
C17: Deterioro
C18: Depreciación
C19: Amortización
C20: Provisiones [resumen]
D21: Litigios y demandas
D22: Garantías
D23: Diversas
D24: Total gastos de provisiones | E24: =SUM(E21:E23) | F24: =SUM(F21:F23) | G24: =SUM(G21:G23)
C25: Arrendamientos
C26: Otros Gastos [resumen]
D27: Comisiones
D28: Ajuste por diferencia en cambio
D29: Financieros
D30: Pérdidas por aplicación del método de participación patrimonial
D31: Gastos diversos
D32: Donaciones
D33: Total otros gastos | E33: =SUM(E27:E32) | F33: =SUM(F27:F32) | G33: =SUM(G27:G32)
C34: Impuesto a las ganancias corrientes
C35: Impuesto a las ganancias diferido
C36: Bienes y servicios públicos para la venta [resumen]
D37: Compras en bloque y/o a largo plazo
D38: Compras en bolsa y/o a corto plazo
D39: Gastos por suministro de agua potable (agua en bloque)
D40: Gastos de conexión
D41: Uso de Líneas, redes y ductos
D42: Gastos de distribución y/o comercialización de gas combustible por redes
D43: Manejo comercial y financiero del servicio
D44: Gastos de distribución y/o comercialización de gas licuado de petróleo – GLP
D45: Contrato de explotación
D46: Gastos asociados a las transacciones en el mercado mayorista
D47: Contrato de concesión
D48: Otros gastos bienes y servicios públicos para la venta
D49: Gastos asociados a las transacciones en el mercado minorista
D50: Total de bienes y servicios públicos para la venta | E50: =SUM(E37:E49) | F50: =SUM(F37:F49) | G50: =SUM(G37:G49)
C51: Licencias, contribuciones y regalías [resumen]
D52: Secretaría Distrital del Medio Ambiente
D53: Ley 56 de 1981
D54: Medio Ambiente – Ley 99 de 1993
D55: Regalías
D56: Licencia De Operación Del Servicio
D57: FAZNI
D58: FAER
D59: Cuota de Fomento de gas
D60: Comité De Estratificación –Ley 505 De 1999
D61: Art 25 - Ley 142 - Concesiones, y permisos ambientales y sanitarios
D62: Otras licencias Ley 142 de 1994
D63: Total licencias, contribuciones y regalías | E63: =SUM(E52:E62) | F63: =SUM(F52:F62) | G63: =SUM(G52:G62)
C64: Consumo de Insumos Directos [resumen]
D65: Productos Químicos
D66: Gas Combustible
D67: Carbón Mineral
D68: Energía
D69: ACPM, Fuel Oil
D70: Otros Elementos de Consumo de Insumos Directos
D71: Total consumo de insumos directos | E71: =SUM(E65:E70) | F71: =SUM(F65:F70) | G71: =SUM(G65:G70)
C72: Ordenes y contratos de mantenimiento y reparaciones
C73: Peajes terrestres
C74: Disposición final
C75: Peajes por interconexión de acueductos
C76: Peajes por interconexión de alcantarillado
C77: Servicios públicos
C78: Materiales y otros gastos de operación
C79: Pérdidas en prestación del servicio de acueducto
C80: Seguros
C81: Órdenes y contratos por otros servicios
C82: Total gastos | E82: =SUM(E13:E19)+E24+E25+SUM(E33:E35)+E50+E63+SUM(E71:E81) | F82: =SUM(F13:F19)+F24+F25+SUM(F33:F35)+F50+F63+SUM(F71:F81) | G82: =SUM(G13:G19)+G24+G25+SUM(G33:G35)+G50+G63+SUM(G71:G81)

Sheet Hoja17
B2: Indice
B3: Archivo: | C3: I:\Proyectos2025\proyecto_niif\_backup_legacy\R414\R414Ind_ID20037_2024-12-31.xbrl
B4: Empresa: | C4: 20037
B5: Vista: | C5: [900017b] FC01-2 - Gastos de servicios públicos - Alcantarillado
B6: Eje X: | C6: N/A
B7: Eje Y: | C7: N/A
B8: Eje Z: | C8: Periodo Actual
E10: Alcantarillado [miembro]
E11: Gasto administrativo - Alcantarillado [miembro] | F11: Gasto operativo - Alcantarillado [miembro]
B12: Gastos [resumen]
C13: Beneficios a empleados
C14: Honorarios
C15: Impuestos, Tasas y Contribuciones (No incluye impuesto de renta)
C16: Generales
C17: Deterioro
C18: Depreciación
C19: Amortización
C20: Provisiones [resumen]
D21: Litigios y demandas
D22: Garantías
D23: Diversas
D24: Total gastos de provisiones | E24: =SUM(E21:E23) | F24: =SUM(F21:F23) | G24: =SUM(G21:G23)
C25: Arrendamientos
C26: Otros Gastos [resumen]
D27: Comisiones
D28: Ajuste por diferencia en cambio
D29: Financieros
D30: Pérdidas por aplicación del método de participación patrimonial
D31: Gastos diversos
D32: Donaciones
D33: Total otros gastos | E33: =SUM(E27:E32) | F33: =SUM(F27:F32) | G33: =SUM(G27:G32)
C34: Impuesto a las ganancias corrientes
C35: Impuesto a las ganancias diferido
C36: Bienes y servicios públicos para la venta [resumen]
D37: Compras en bloque y/o a largo plazo
D38: Compras en bolsa y/o a corto plazo
D39: Gastos por suministro de agua potable (agua en bloque)
D40: Gastos de conexión
D41: Uso de Líneas, redes y ductos
D42: Gastos de distribución y/o comercialización de gas combustible por redes
D43: Manejo comercial y financiero del servicio
D44: Gastos de distribución y/o comercialización de gas licuado de petróleo – GLP
D45: Contrato de explotación
D46: Gastos asociados a las transacciones en el mercado mayorista
D47: Contrato de concesión
D48: Otros gastos bienes y servicios públicos para la venta
D49: Gastos asociados a las transacciones en el mercado minorista
D50: Total de bienes y servicios públicos para la venta | E50: =SUM(E37:E49) | F50: =SUM(F37:F49) | G50: =SUM(G37:G49)
C51: Licencias, contribuciones y regalías [resumen]
D52: Secretaría Distrital del Medio Ambiente
D53: Ley 56 de 1981
D54: Medio Ambiente – Ley 99 de 1993
D55: Regalías
D56: Licencia De Operación Del Servicio
D57: FAZNI
D58: FAER
D59: Cuota de Fomento de gas
D60: Comité De Estratificación –Ley 505 De 1999
D61: Art 25 - Ley 142 - Concesiones, y permisos ambientales y sanitarios
D62: Otras licencias Ley 142 de 1994
D63: Total licencias, contribuciones y regalías | E63: =SUM(E52:E62) | F63: =SUM(F52:F62) | G63: =SUM(G52:G62)
C64: Consumo de Insumos Directos [resumen]
D65: Productos Químicos
D66: Gas Combustible
D67: Carbón Mineral
D68: Energía
D69: ACPM, Fuel Oil
D70: Otros Elementos de Consumo de Insumos Directos
D71: Total consumo de insumos directos | E71: =SUM(E65:E70) | F71: =SUM(F65:F70) | G71: =SUM(G65:G70)
C72: Ordenes y contratos de mantenimiento y reparaciones
C73: Peajes terrestres
C74: Disposición final
C75: Peajes por interconexión de acueductos
C76: Peajes por interconexión de alcantarillado
C77: Servicios públicos
C78: Materiales y otros gastos de operación
C79: Pérdidas en prestación del servicio de acueducto
C80: Seguros
C81: Órdenes y contratos por otros servicios
C82: Total gastos | E82: =SUM(E13:E19)+E24+E25+SUM(E33:E35)+E50+E63+SUM(E71:E81) | F82: =SUM(F13:F19)+F24+F25+SUM(F33:F35)+F50+F63+SUM(F71:F81) | G82: =SUM(G13:G19)+G24+G25+SUM(G33:G35)+G50+G63+SUM(G71:G81)

Sheet Hoja18
B2: Indice
B3: Archivo: | C3: I:\Proyectos2025\proyecto_niif\_backup_legacy\R414\R414Ind_ID20037_2024-12-31.xbrl
B4: Empresa: | C4: 20037
B5: Vista: | C5: [900017c] FC01-3 - Gastos de servicios públicos - Aseo
B6: Eje X: | C6: N/A
B7: Eje Y: | C7: N/A
B8: Eje Z: | C8: Periodo Actual
E10: Aseo [miembro]
E11: Gasto administrativo - Aseo [miembro] | F11: Gasto operativo - Aseo [miembro]
B12: Gastos [resumen]
C13: Beneficios a empleados
C14: Honorarios
C15: Impuestos, Tasas y Contribuciones (No incluye impuesto de renta)
C16: Generales
C17: Deterioro
C18: Depreciación
C19: Amortización
C20: Provisiones [resumen]
D21: Litigios y demandas
D22: Garantías
D23: Diversas
D24: Total gastos de provisiones | E24: =SUM(E21:E23) | F24: =SUM(F21:F23) | G24: =SUM(G21:G23)
C25: Arrendamientos
C26: Otros Gastos [resumen]
D27: Comisiones
D28: Ajuste por diferencia en cambio
D29: Financieros
D30: Pérdidas por aplicación del método de participación patrimonial
D31: Gastos diversos
D32: Donaciones
D33: Total otros gastos | E33: =SUM(E27:E32) | F33: =SUM(F27:F32) | G33: =SUM(G27:G32)
C34: Impuesto a las ganancias corrientes
C35: Impuesto a las ganancias diferido
C36: Bienes y servicios públicos para la venta [resumen]
D37: Compras en bloque y/o a largo plazo
D38: Compras en bolsa y/o a corto plazo
D39: Gastos por suministro de agua potable (agua en bloque)
D40: Gastos de conexión
D41: Uso de Líneas, redes y ductos
D42: Gastos de distribución y/o comercialización de gas combustible por redes
D43: Manejo comercial y financiero del servicio
D44: Gastos de distribución y/o comercialización de gas licuado de petróleo – GLP
D45: Contrato de explotación
D46: Gastos asociados a las transacciones en el mercado mayorista
D47: Contrato de concesión
D48: Otros gastos bienes y servicios públicos para la venta
D49: Gastos asociados a las transacciones en el mercado minorista
D50: Total de bienes y servicios públicos para la venta | E50: =SUM(E37:E49) | F50: =SUM(F37:F49) | G50: =SUM(G37:G49)
C51: Licencias, contribuciones y regalías [resumen]
D52: Secretaría Distrital del Medio Ambiente
D53: Ley 56 de 1981
D54: Medio Ambiente – Ley 99 de 1993
D55: Regalías
D56: Licencia De Operación Del Servicio
D57: FAZNI
D58: FAER
D59: Cuota de Fomento de gas
D60: Comité De Estratificación –Ley 505 De 1999
D61: Art 25 - Ley 142 - Concesiones, y permisos ambientales y sanitarios
D62: Otras licencias Ley 142 de 1994
D63: Total licencias, contribuciones y regalías | E63: =SUM(E52:E62) | F63: =SUM(F52:F62) | G63: =SUM(G52:G62)
C64: Consumo de Insumos Directos [resumen]
D65: Productos Químicos
D66: Gas Combustible
D67: Carbón Mineral
D68: Energía
D69: ACPM, Fuel Oil
D70: Otros Elementos de Consumo de Insumos Directos
D71: Total consumo de insumos directos | E71: =SUM(E65:E70) | F71: =SUM(F65:F70) | G71: =SUM(G65:G70)
C72: Ordenes y contratos de mantenimiento y reparaciones
C73: Peajes terrestres
C74: Disposición final
C75: Peajes por interconexión de acueductos
C76: Peajes por interconexión de alcantarillado
C77: Servicios públicos
C78: Materiales y otros gastos de operación
C79: Pérdidas en prestación del servicio de acueducto
C80: Seguros
C81: Órdenes y contratos por otros servicios
C82: Total gastos | E82: =SUM(E13:E19)+E24+E25+SUM(E33:E35)+E50+E63+SUM(E71:E81) | F82: =SUM(F13:F19)+F24+F25+SUM(F33:F35)+F50+F63+SUM(F71:F81) | G82: =SUM(G13:G19)+G24+G25+SUM(G33:G35)+G50+G63+SUM(G71:G81)

Sheet Hoja19
B2: Indice
B3: Archivo: | C3: I:\Proyectos2025\proyecto_niif\_backup_legacy\R414\R414Ind_ID20037_2024-12-31.xbrl
B4: Empresa: | C4: 20037
B5: Vista: | C5: [900017d] FC01-4 - Gastos de servicios públicos - Energía
B6: Eje X: | C6: N/A
B7: Eje Y: | C7: N/A
B8: Eje Z: | C8: Periodo Actual
E10: Energía Eléctrica [miembro]
E11: ENERGIA - SIN [miembro] | T11: ENERGIA - ZNI [miembro] | AF11: Gasto administrativo - Energía eléctrica [miembro] | AG11: Gasto operativo - Energía Eléctrica [miembro]
E12: Generación [miembro] | H12: Transmisión [miembro] | K12: Distribución [miembro] | N12: Comercialización [miembro] | Q12: Gasto administrativo - Energía Eléctrica SIN [miembro] | R12: Gasto operativo - Energía Eléctrica SIN [miembro] | T12: Generación [miembro] | W12: Distribución [miembro] | Z12: Comercialización [miembro] | AC12: Gasto administrativo - Energía Eléctrica ZNI [miembro] | AD12: Gasto operativo - Energía Eléctrica ZNI [miembro]
E13: Gasto administrativo - Energía Eléctrica SIN - Generación [miembro] | F13: Gasto operativo - Energía Eléctrica SIN - Generación [miembro] | H13: Gasto administrativo - Energía Eléctrica SIN - Transmisión [miembro] | I13: Gasto operativo - Energía Eléctrica SIN - Transmisión [miembro] | K13: Gasto administrativo - Energía Eléctrica SIN - Distribución [miembro] | L13: Gasto operativo - Energía Eléctrica SIN - Distribución [miembro] | N13: Gasto administrativo - Energía Eléctrica SIN - Comercialización [miembro] | O13: Gasto operativo - Energía Eléctrica SIN - Comercialización [miembro] | T13: Gasto administrativo - Energía Eléctrica ZNI - Generación [miembro] | U13: Gasto operativo - Energía Eléctrica ZNI - Generación [miembro] | W13: Gasto administrativo - Energía Eléctrica ZNI - Distribución [miembro] | X13: Gasto operativo - Energía Eléctrica ZNI - Distribución [miembro] | Z13: Gasto administrativo - Energía Eléctrica ZNI - Comercialización [miembro] | AA13: Gasto operativo - Energía Eléctrica ZNI - Comercialización [miembro]
B14: Gastos [resumen]
C15: Beneficios a empleados
C16: Honorarios
C17: Impuestos, Tasas y Contribuciones (No incluye impuesto de renta)
C18: Generales
C19: Deterioro
C20: Depreciación
C21: Amortización
C22: Provisiones [resumen]
D23: Litigios y demandas
D24: Garantías
D25: Diversas
D26: Total gastos de provisiones | E26: =SUM(E23:E25) | F26: =SUM(F23:F25) | G26: =SUM(G23:G25) | H26: =SUM(H23:H25) | I26: =SUM(I23:I25) | J26: =SUM(J23:J25) | K26: =SUM(K23:K25) | L26: =SUM(L23:L25) | ... AH26: =SUM(AH23:AH25)
C27: Arrendamientos
C28: Otros Gastos [resumen]
D29: Comisiones
D30: Ajuste por diferencia en cambio
D31: Financieros
D32: Pérdidas por aplicación del método de participación patrimonial
D33: Gastos diversos
D34: Donaciones
D35: Total otros gastos | E35: =SUM(E29:E34) | F35: =SUM(F29:F34) | G35: =SUM(G29:G34) | H35: =SUM(H29:H34) | I35: =SUM(I29:I34) | J35: =SUM(J29:J34) | K35: =SUM(K29:K34) | L35: =SUM(L29:L34) | ... AH35: =SUM(AH29:AH34)
C36: Impuesto a las ganancias corrientes
C37: Impuesto a las ganancias diferido
C38: Bienes y servicios públicos para la venta [resumen]
D39: Compras en bloque y/o a largo plazo
D40: Compras en bolsa y/o a corto plazo
D41: Gastos por suministro de agua potable (agua en bloque)
D42: Gastos de conexión
D43: Uso de Líneas, redes y ductos
D44: Gastos de distribución y/o comercialización de gas combustible por redes
D45: Manejo comercial y financiero del servicio
D46: Gastos de distribución y/o comercialización de gas licuado de petróleo – GLP
D47: Contrato de explotación
D48: Gastos asociados a las transacciones en el mercado mayorista
D49: Contrato de concesión
D50: Otros gastos bienes y servicios públicos para la venta
D51: Gastos asociados a las transacciones en el mercado minorista
D52: Total de bienes y servicios públicos para la venta | E52: =SUM(E39:E51) | F52: =SUM(F39:F51) | G52: =SUM(G39:G51) | H52: =SUM(H39:H51) | I52: =SUM(I39:I51) | J52: =SUM(J39:J51) | K52: =SUM(K39:K51) | L52: =SUM(L39:L51) | ... AH52: =SUM(AH39:AH51)
C53: Licencias, contribuciones y regalías [resumen]
D54: Secretaría Distrital del Medio Ambiente
D55: Ley 56 de 1981
D56: Medio Ambiente – Ley 99 de 1993
D57: Regalías
D58: Licencia De Operación Del Servicio
D59: FAZNI
D60: FAER
D61: Cuota de Fomento de gas
D62: Comité De Estratificación –Ley 505 De 1999
D63: Art 25 - Ley 142 - Concesiones, y permisos ambientales y sanitarios
D64: Otras licencias Ley 142 de 1994
D65: Total licencias, contribuciones y regalías | E65: =SUM(E54:E64) | F65: =SUM(F54:F64) | G65: =SUM(G54:G64) | H65: =SUM(H54:H64) | I65: =SUM(I54:I64) | J65: =SUM(J54:J64) | K65: =SUM(K54:K64) | L65: =SUM(L54:L64) | ... AH65: =SUM(AH54:AH64)
C66: Consumo de Insumos Directos [resumen]
D67: Productos Químicos
D68: Gas Combustible
D69: Carbón Mineral
D70: Energía
D71: ACPM, Fuel Oil
D72: Otros Elementos de Consumo de Insumos Directos
D73: Total consumo de insumos directos | E73: =SUM(E67:E72) | F73: =SUM(F67:F72) | G73: =SUM(G67:G72) | H73: =SUM(H67:H72) | I73: =SUM(I67:I72) | J73: =SUM(J67:J72) | K73: =SUM(K67:K72) | L73: =SUM(L67:L72) | ... AH73: =SUM(AH67:AH72)
C74: Ordenes y contratos de mantenimiento y reparaciones
C75: Peajes terrestres
C76: Disposición final
C77: Peajes por interconexión de acueductos
C78: Peajes por interconexión de alcantarillado
C79: Servicios públicos
C80: Materiales y otros gastos de operación
C81: Pérdidas en prestación del servicio de acueducto
C82: Seguros
C83: Órdenes y contratos por otros servicios
C84: Total gastos | E84: =SUM(E15:E21)+E26+E27+SUM(E35:E37)+E52+E65+SUM(E73:E83) | F84: =SUM(F15:F21)+F26+F27+SUM(F35:F37)+F52+F65+SUM(F73:F83) | G84: =SUM(G15:G21)+G26+G27+SUM(G35:G37)+G52+G65+SUM(G73:G83) | H84: =SUM(H15:H21)+H26+H27+SUM(H35:H37)+H52+H65+SUM(H73:H83) | I84: =SUM(I15:I21)+I26+I27+SUM(I35:I37)+I52+I65+SUM(I73:I83) | J84: =SUM(J15:J21)+J26+J27+SUM(J35:J37)+J52+J65+SUM(J73:J83) | K84: =SUM(K15:K21)+K26+K27+SUM(K35:K37)+K52+K65+SUM(K73:K83) | L84: =SUM(L15:L21)+L26+L27+SUM(L35:L37)+L52+L65+SUM(L73:L83) | ... AH84: =SUM(AH15:AH21)+AH26+AH27+SUM(AH35:AH37)+AH52+AH65+SUM(AH73:AH83)

Sheet Hoja20
B2: Indice
B3: Archivo: | C3: I:\Proyectos2025\proyecto_niif\_backup_legacy\R414\R414Ind_ID20037_2024-12-31.xbrl
B4: Empresa: | C4: 20037
B5: Vista: | C5: [900017e] FC01-5 - Gastos de servicios públicos - Gas combustible por redes
B6: Eje X: | C6: N/A
B7: Eje Y: | C7: N/A
B8: Eje Z: | C8: Periodo Actual
E10: Gas combustible por redes [miembro]
E11: Producción [miembro] | H11: Transporte [miembro] | K11: Distribución [miembro] | N11: Comercialización [miembro] | Q11: Comercialización de gas importado [miembro] | T11: Regasificación [miembro] | W11: Gasto administrativo - Gas Combustible por redes [miembro] | X11: Gasto operativo - Gas Combustible por redes [miembro]
E12: Gasto administrativo - Gas Combustible por redes - Producción [miembro] | F12: Gasto operativo - Gas Combustible por redes - Producción [miembro] | H12: Gasto administrativo - Gas Combustible por redes - Transporte [miembro] | I12: Gasto operativo - Gas Combustible por redes - Transporte [miembro] | K12: Gasto administrativo - Gas Combustible por redes - Distribución [miembro] | L12: Gasto operativo - Gas Combustible por redes - Distribución [miembro] | N12: Gasto administrativo - Gas Combustible por redes - Comercialización [miembro] | O12: Gasto operativo - Gas Combustible por redes - Comercialización [miembro] | Q12: Gasto administrativo - Gas Combustible por redes - Comercialización de gas importado [miembro] | R12: Gasto operativo - Gas Combustible por redes - Comercialización de gas importado[miembro] | T12: Gasto administrativo - Gas Combustible por redes - Regasificación [miembro] | U12: Gasto operativo - Gas Combustible por redes - Regasificación [miembro]
B13: Gastos [resumen]
C14: Beneficios a empleados
C15: Honorarios
C16: Impuestos, Tasas y Contribuciones (No incluye impuesto de renta)
C17: Generales
C18: Deterioro
C19: Depreciación
C20: Amortización
C21: Provisiones [resumen]
D22: Litigios y demandas
D23: Garantías
D24: Diversas
D25: Total gastos de provisiones | E25: =SUM(E22:E24) | F25: =SUM(F22:F24) | G25: =SUM(G22:G24) | H25: =SUM(H22:H24) | I25: =SUM(I22:I24) | J25: =SUM(J22:J24) | K25: =SUM(K22:K24) | L25: =SUM(L22:L24) | ... Y25: =SUM(Y22:Y24)
C26: Arrendamientos
C27: Otros Gastos [resumen]
D28: Comisiones
D29: Ajuste por diferencia en cambio
D30: Financieros
D31: Pérdidas por aplicación del método de participación patrimonial
D32: Gastos diversos
D33: Donaciones
D34: Total otros gastos | E34: =SUM(E28:E33) | F34: =SUM(F28:F33) | G34: =SUM(G28:G33) | H34: =SUM(H28:H33) | I34: =SUM(I28:I33) | J34: =SUM(J28:J33) | K34: =SUM(K28:K33) | L34: =SUM(L28:L33) | ... Y34: =SUM(Y28:Y33)
C35: Impuesto a las ganancias corrientes
C36: Impuesto a las ganancias diferido
C37: Bienes y servicios públicos para la venta [resumen]
D38: Compras en bloque y/o a largo plazo
D39: Compras en bolsa y/o a corto plazo
D40: Gastos por suministro de agua potable (agua en bloque)
D41: Gastos de conexión
D42: Uso de Líneas, redes y ductos
D43: Gastos de distribución y/o comercialización de gas combustible por redes
D44: Manejo comercial y financiero del servicio
D45: Gastos de distribución y/o comercialización de gas licuado de petróleo – GLP
D46: Contrato de explotación
D47: Gastos asociados a las transacciones en el mercado mayorista
D48: Contrato de concesión
D49: Otros gastos bienes y servicios públicos para la venta
D50: Gastos asociados a las transacciones en el mercado minorista
D51: Total de bienes y servicios públicos para la venta | E51: =SUM(E38:E50) | F51: =SUM(F38:F50) | G51: =SUM(G38:G50) | H51: =SUM(H38:H50) | I51: =SUM(I38:I50) | J51: =SUM(J38:J50) | K51: =SUM(K38:K50) | L51: =SUM(L38:L50) | ... Y51: =SUM(Y38:Y50)
C52: Licencias, contribuciones y regalías [resumen]
D53: Secretaría Distrital del Medio Ambiente
D54: Ley 56 de 1981
D55: Medio Ambiente – Ley 99 de 1993
D56: Regalías
D57: Licencia De Operación Del Servicio
D58: FAZNI
D59: FAER
D60: Cuota de Fomento de gas
D61: Comité De Estratificación –Ley 505 De 1999
D62: Art 25 - Ley 142 - Concesiones, y permisos ambientales y sanitarios
D63: Otras licencias Ley 142 de 1994
D64: Total licencias, contribuciones y regalías | E64: =SUM(E53:E63) | F64: =SUM(F53:F63) | G64: =SUM(G53:G63) | H64: =SUM(H53:H63) | I64: =SUM(I53:I63) | J64: =SUM(J53:J63) | K64: =SUM(K53:K63) | L64: =SUM(L53:L63) | ... Y64: =SUM(Y53:Y63)
C65: Consumo de Insumos Directos [resumen]
D66: Productos Químicos
D67: Gas Combustible
D68: Carbón Mineral
D69: Energía
D70: ACPM, Fuel Oil
D71: Otros Elementos de Consumo de Insumos Directos
D72: Total consumo de insumos directos | E72: =SUM(E66:E71) | F72: =SUM(F66:F71) | G72: =SUM(G66:G71) | H72: =SUM(H66:H71) | I72: =SUM(I66:I71) | J72: =SUM(J66:J71) | K72: =SUM(K66:K71) | L72: =SUM(L66:L71) | ... Y72: =SUM(Y66:Y71)
C73: Ordenes y contratos de mantenimiento y reparaciones
C74: Peajes terrestres
C75: Disposición final
C76: Peajes por interconexión de acueductos
C77: Peajes por interconexión de alcantarillado
C78: Servicios públicos
C79: Materiales y otros gastos de operación
C80: Pérdidas en prestación del servicio de acueducto
C81: Seguros
C82: Órdenes y contratos por otros servicios
C83: Total gastos | E83: =SUM(E14:E20)+E25+E26+SUM(E34:E36)+E51+E64+SUM(E72:E82) | F83: =SUM(F14:F20)+F25+F26+SUM(F34:F36)+F51+F64+SUM(F72:F82) | G83: =SUM(G14:G20)+G25+G26+SUM(G34:G36)+G51+G64+SUM(G72:G82) | H83: =SUM(H14:H20)+H25+H26+SUM(H34:H36)+H51+H64+SUM(H72:H82) | I83: =SUM(I14:I20)+I25+I26+SUM(I34:I36)+I51+I64+SUM(I72:I82) | J83: =SUM(J14:J20)+J25+J26+SUM(J34:J36)+J51+J64+SUM(J72:J82) | K83: =SUM(K14:K20)+K25+K26+SUM(K34:K36)+K51+K64+SUM(K72:K82) | L83: =SUM(L14:L20)+L25+L26+SUM(L34:L36)+L51+L64+SUM(L72:L82) | ... Y83: =SUM(Y14:Y20)+Y25+Y26+SUM(Y34:Y36)+Y51+Y64+SUM(Y72:Y82)

Sheet Hoja21
B2: Indice
B3: Archivo: | C3: I:\Proyectos2025\proyecto_niif\_backup_legacy\R414\R414Ind_ID20037_2024-12-31.xbrl
B4: Empresa: | C4: 20037
B5: Vista: | C5: [900017f] FC01-6 - Gastos de servicios públicos - Gas licuado del petroleo
B6: Eje X: | C6: N/A
B7: Eje Y: | C7: N/A
B8: Eje Z: | C8: Periodo Actual
E10: Gas Licuado de Petróleo [miembro]
E11: Comercialización Mayorista [miembro] | H11: Distribución Inversionista [miembro] | K11: Comercialización Minorista [miembro] | N11: Transporte [miembro] | Q11: Gasto administrativo - GLP [miembro] | R11: Gasto operativo - GLP [miembro]
E12: Gasto administrativo - GLP - Comercialización mayorista [miembro] | F12: Gasto operativo - GLP - Comercialización mayorista [miembro] | H12: Gasto administrativo - GLP - Distribución inversionista [miembro] | I12: Gasto operativo - GLP - Distribución inversionista [miembro] | K12: Gasto administrativo - GLP - Comercialización minorista [miembro] | L12: Gasto operativo - GLP - Comercialización minorista [miembro] | N12: Gasto administrativo - GLP - Transporte [miembro] | O12: Gasto operativo - GLP - Transporte [miembro]
B13: Gastos [resumen]
C14: Beneficios a empleados
C15: Honorarios
C16: Impuestos, Tasas y Contribuciones (No incluye impuesto de renta)
C17: Generales
C18: Deterioro
C19: Depreciación
C20: Amortización
C21: Provisiones [resumen]
D22: Litigios y demandas
D23: Garantías
D24: Diversas
D25: Total gastos de provisiones | E25: =SUM(E22:E24) | F25: =SUM(F22:F24) | G25: =SUM(G22:G24) | H25: =SUM(H22:H24) | I25: =SUM(I22:I24) | J25: =SUM(J22:J24) | K25: =SUM(K22:K24) | L25: =SUM(L22:L24) | ... S25: =SUM(S22:S24)
C26: Arrendamientos
C27: Otros Gastos [resumen]
D28: Comisiones
D29: Ajuste por diferencia en cambio
D30: Financieros
D31: Pérdidas por aplicación del método de participación patrimonial
D32: Gastos diversos
D33: Donaciones
D34: Total otros gastos | E34: =SUM(E28:E33) | F34: =SUM(F28:F33) | G34: =SUM(G28:G33) | H34: =SUM(H28:H33) | I34: =SUM(I28:I33) | J34: =SUM(J28:J33) | K34: =SUM(K28:K33) | L34: =SUM(L28:L33) | ... S34: =SUM(S28:S33)
C35: Impuesto a las ganancias corrientes
C36: Impuesto a las ganancias diferido
C37: Bienes y servicios públicos para la venta [resumen]
D38: Compras en bloque y/o a largo plazo
D39: Compras en bolsa y/o a corto plazo
D40: Gastos por suministro de agua potable (agua en bloque)
D41: Gastos de conexión
D42: Uso de Líneas, redes y ductos
D43: Gastos de distribución y/o comercialización de gas combustible por redes
D44: Manejo comercial y financiero del servicio
D45: Gastos de distribución y/o comercialización de gas licuado de petróleo – GLP
D46: Contrato de explotación
D47: Gastos asociados a las transacciones en el mercado mayorista
D48: Contrato de concesión
D49: Otros gastos bienes y servicios públicos para la venta
D50: Gastos asociados a las transacciones en el mercado minorista
D51: Total de bienes y servicios públicos para la venta | E51: =SUM(E38:E50) | F51: =SUM(F38:F50) | G51: =SUM(G38:G50) | H51: =SUM(H38:H50) | I51: =SUM(I38:I50) | J51: =SUM(J38:J50) | K51: =SUM(K38:K50) | L51: =SUM(L38:L50) | ... S51: =SUM(S38:S50)
C52: Licencias, contribuciones y regalías [resumen]
D53: Secretaría Distrital del Medio Ambiente
D54: Ley 56 de 1981
D55: Medio Ambiente – Ley 99 de 1993
D56: Regalías
D57: Licencia De Operación Del Servicio
D58: FAZNI
D59: FAER
D60: Cuota de Fomento de gas
D61: Comité De Estratificación –Ley 505 De 1999
D62: Art 25 - Ley 142 - Concesiones, y permisos ambientales y sanitarios
D63: Otras licencias Ley 142 de 1994
D64: Total licencias, contribuciones y regalías | E64: =SUM(E53:E63) | F64: =SUM(F53:F63) | G64: =SUM(G53:G63) | H64: =SUM(H53:H63) | I64: =SUM(I53:I63) | J64: =SUM(J53:J63) | K64: =SUM(K53:K63) | L64: =SUM(L53:L63) | ... S64: =SUM(S53:S63)
C65: Consumo de Insumos Directos [resumen]
D66: Productos Químicos
D67: Gas Combustible
D68: Carbón Mineral
D69: Energía
D70: ACPM, Fuel Oil
D71: Otros Elementos de Consumo de Insumos Directos
D72: Total consumo de insumos directos | E72: =SUM(E66:E71) | F72: =SUM(F66:F71) | G72: =SUM(G66:G71) | H72: =SUM(H66:H71) | I72: =SUM(I66:I71) | J72: =SUM(J66:J71) | K72: =SUM(K66:K71) | L72: =SUM(L66:L71) | ... S72: =SUM(S66:S71)
C73: Ordenes y contratos de mantenimiento y reparaciones
C74: Peajes terrestres
C75: Disposición final
C76: Peajes por interconexión de acueductos
C77: Peajes por interconexión de alcantarillado
C78: Servicios públicos
C79: Materiales y otros gastos de operación
C80: Pérdidas en prestación del servicio de acueducto
C81: Seguros
C82: Órdenes y contratos por otros servicios
C83: Total gastos | E83: =SUM(E14:E20)+E25+E26+SUM(E34:E36)+E51+E64+SUM(E72:E82) | F83: =SUM(F14:F20)+F25+F26+SUM(F34:F36)+F51+F64+SUM(F72:F82) | G83: =SUM(G14:G20)+G25+G26+SUM(G34:G36)+G51+G64+SUM(G72:G82) | H83: =SUM(H14:H20)+H25+H26+SUM(H34:H36)+H51+H64+SUM(H72:H82) | I83: =SUM(I14:I20)+I25+I26+SUM(I34:I36)+I51+I64+SUM(I72:I82) | J83: =SUM(J14:J20)+J25+J26+SUM(J34:J36)+J51+J64+SUM(J72:J82) | K83: =SUM(K14:K20)+K25+K26+SUM(K34:K36)+K51+K64+SUM(K72:K82) | L83: =SUM(L14:L20)+L25+L26+SUM(L34:L36)+L51+L64+SUM(L72:L82) | ... S83: =SUM(S14:S20)+S25+S26+SUM(S34:S36)+S51+S64+SUM(S72:S82)

Sheet Hoja22
B2: Indice
B3: Archivo: | C3: I:\Proyectos2025\proyecto_niif\_backup_legacy\R414\R414Ind_ID20037_2024-12-31.xbrl
B4: Empresa: | C4: 20037
B5: Vista: | C5: [900017g] FC01-7 - Gastos de servicios públicos - Total servicios públicos
B6: Eje X: | C6: N/A
B7: Eje Y: | C7: N/A
B8: Eje Z: | C8: Periodo Actual
E10: Total Periodo [miembro]
E11: Total prestación servicios públicos nacionales [miembro] | H11: Otras actividades no vigiladas por la SSPD [miembro] | K11: Gasto administrativo - Total del periodo [miembro] | L11: Gasto operativo - Total del periodo [miembro]
E12: Gasto administrativo - Total de servicios públicos [miembro] | F12: Gasto operativo - Total de servicios públicos [miembro] | H12: Gasto administrativo - Otras actividades no vigiladas [miembro] | I12: Gasto operativo - Otras actividades no vigiladas [miembro]
B13: Gastos [resumen]
C14: Beneficios a empleados
C15: Honorarios
C16: Impuestos, Tasas y Contribuciones (No incluye impuesto de renta)
C17: Generales
C18: Deterioro
C19: Depreciación
C20: Amortización
C21: Provisiones [resumen]
D22: Litigios y demandas
D23: Garantías
D24: Diversas
D25: Total gastos de provisiones | E25: =SUM(E22:E24) | F25: =SUM(F22:F24) | G25: =SUM(G22:G24) | H25: =SUM(H22:H24) | I25: =SUM(I22:I24) | J25: =SUM(J22:J24) | K25: =SUM(K22:K24) | L25: =SUM(L22:L24) | M25: =SUM(M22:M24)
C26: Arrendamientos
C27: Otros Gastos [resumen]
D28: Comisiones
D29: Ajuste por diferencia en cambio
D30: Financieros
D31: Pérdidas por aplicación del método de participación patrimonial
D32: Gastos diversos
D33: Donaciones
D34: Total otros gastos | E34: =SUM(E28:E33) | F34: =SUM(F28:F33) | G34: =SUM(G28:G33) | H34: =SUM(H28:H33) | I34: =SUM(I28:I33) | J34: =SUM(J28:J33) | K34: =SUM(K28:K33) | L34: =SUM(L28:L33) | M34: =SUM(M28:M33)
C35: Impuesto a las ganancias corrientes
C36: Impuesto a las ganancias diferido
C37: Bienes y servicios públicos para la venta [resumen]
D38: Compras en bloque y/o a largo plazo
D39: Compras en bolsa y/o a corto plazo
D40: Gastos por suministro de agua potable (agua en bloque)
D41: Gastos de conexión
D42: Uso de Líneas, redes y ductos
D43: Gastos de distribución y/o comercialización de gas combustible por redes
D44: Manejo comercial y financiero del servicio
D45: Gastos de distribución y/o comercialización de gas licuado de petróleo – GLP
D46: Contrato de explotación
D47: Gastos asociados a las transacciones en el mercado mayorista
D48: Contrato de concesión
D49: Otros gastos bienes y servicios públicos para la venta
D50: Gastos asociados a las transacciones en el mercado minorista
D51: Total de bienes y servicios públicos para la venta | E51: =SUM(E38:E50) | F51: =SUM(F38:F50) | G51: =SUM(G38:G50) | H51: =SUM(H38:H50) | I51: =SUM(I38:I50) | J51: =SUM(J38:J50) | K51: =SUM(K38:K50) | L51: =SUM(L38:L50) | M51: =SUM(M38:M50)
C52: Licencias, contribuciones y regalías [resumen]
D53: Secretaría Distrital del Medio Ambiente
D54: Ley 56 de 1981
D55: Medio Ambiente – Ley 99 de 1993
D56: Regalías
D57: Licencia De Operación Del Servicio
D58: FAZNI
D59: FAER
D60: Cuota de Fomento de gas
D61: Comité De Estratificación –Ley 505 De 1999
D62: Art 25 - Ley 142 - Concesiones, y permisos ambientales y sanitarios
D63: Otras licencias Ley 142 de 1994
D64: Total licencias, contribuciones y regalías | E64: =SUM(E53:E63) | F64: =SUM(F53:F63) | G64: =SUM(G53:G63) | H64: =SUM(H53:H63) | I64: =SUM(I53:I63) | J64: =SUM(J53:J63) | K64: =SUM(K53:K63) | L64: =SUM(L53:L63) | M64: =SUM(M53:M63)
C65: Consumo de Insumos Directos [resumen]
D66: Productos Químicos
D67: Gas Combustible
D68: Carbón Mineral
D69: Energía
D70: ACPM, Fuel Oil
D71: Otros Elementos de Consumo de Insumos Directos
D72: Total consumo de insumos directos | E72: =SUM(E66:E71) | F72: =SUM(F66:F71) | G72: =SUM(G66:G71) | H72: =SUM(H66:H71) | I72: =SUM(I66:I71) | J72: =SUM(J66:J71) | K72: =SUM(K66:K71) | L72: =SUM(L66:L71) | M72: =SUM(M66:M71)
C73: Ordenes y contratos de mantenimiento y reparaciones
C74: Peajes terrestres
C75: Disposición final
C76: Peajes por interconexión de acueductos
C77: Peajes por interconexión de alcantarillado
C78: Servicios públicos
C79: Materiales y otros gastos de operación
C80: Pérdidas en prestación del servicio de acueducto
C81: Seguros
C82: Órdenes y contratos por otros servicios
C83: Total gastos | E83: =SUM(E14:E20)+E25+E26+SUM(E34:E36)+E51+E64+SUM(E72:E82) | F83: =SUM(F14:F20)+F25+F26+SUM(F34:F36)+F51+F64+SUM(F72:F82) | G83: =SUM(G14:G20)+G25+G26+SUM(G34:G36)+G51+G64+SUM(G72:G82) | H83: =SUM(H14:H20)+H25+H26+SUM(H34:H36)+H51+H64+SUM(H72:H82) | I83: =SUM(I14:I20)+I25+I26+SUM(I34:I36)+I51+I64+SUM(I72:I82) | J83: =SUM(J14:J20)+J25+J26+SUM(J34:J36)+J51+J64+SUM(J72:J82) | K83: =SUM(K14:K20)+K25+K26+SUM(K34:K36)+K51+K64+SUM(K72:K82) | L83: =SUM(L14:L20)+L25+L26+SUM(L34:L36)+L51+L64+SUM(L72:L82) | M83: =SUM(M14:M20)+M25+M26+SUM(M34:M36)+M51+M64+SUM(M72:M82)

Sheet Hoja23
B2: Indice
B3: Archivo: | C3: I:\Proyectos2025\proyecto_niif\_backup_legacy\R414\R414Ind_ID20037_2024-12-31.xbrl
B4: Empresa: | C4: 20037
B5: Vista: | C5: [900019] FC02 - Complementario ingresos
B6: Eje X: | C6: N/A
B7: Eje Y: | C7: N/A
B8: Eje Z: | C8: Periodo Actual
I10: Ingresos, devoluciones, rebajas y descuentos [miembro]
I11: Ingresos brutos [miembro] | J11: Devoluciones, rebajas y descuentos [miembro] | K11: Ingresos netos [miembro]
B12: Información a revelar sobre ingresos y devoluciones [resumen]
C13: Información a revelar sobre ingresos [resumen]
D14: Acueducto [resumen]
E15: Abastecimiento
E16: Distribución
E17: Comercialización
E18: Subtotal Ingresos Acueducto | I18: =SUM(I15:I17)
D19: Alcantarillado [resumen]
E20: Recolección y transporte
E21: Tratamiento de aguas residuales
E22: Comercialización
E23: Subtotal Ingresos Alcantarillado | I23: =SUM(I20:I22)
D24: Aseo [resumen]
E25: Recolección y transporte de residuos no aprovechables
E26: Disposición final
E27: Tratamiento de lixiviados
E28: Comercialización
E29: Corte de césped
E30: Poda de arboles
E31: Limpieza y lavado de áreas públicas
E32: Limpieza de playa costeras y rivereñas
E33: Suministro e Instalación de cestas en vías y áreas públicas
E34: Mantenimiento de cestas en vías y áreas públicas
E35: Barrido y Limpieza
E36: Transferencia
... E39: Otros ingresos servicio aseo
E40: Subtotal Ingresos Aseo | I40: =SUM(I25:I39)
D41: Energía Eléctrica [resumen]
E42: ENERGIA - SIN [resumen]
F43: Generación [resumen]
G44: Ventas de contratos bilaterales
G45: Transacciones de energía en bolsa [resumen]
H46: Arranques y paradas
H47: Desviaciones positivas
H48: Cargo por confiabilidad
H49: Servicio AGC
H50: Restricciones
H51: Ventas en bolsa
H52: Subtotal Transacciones de energía en bolsa | I52: =SUM(I46:I51) | J52: =SUM(J46:J51) | K52: =SUM(K46:K51)
G53: Otros ingresos de generación
G54: Subtotal Ingresos Generación | I54: =I44+I52+I53 | J54: =J44+J52+J53 | K54: =K44+K52+K53
F55: Transmisión
F56: Distribución
F57: Comercialización [resumen]
G58: Ventas contratos bilaterales
G59: Ventas energía en bolsa
G60: Subtotal Comercialización | I60: =I58+I59 | J60: =J58+J59 | K60: =K58+K59
F61: Subtotal Energia - SIN | I61: =SUM(I54:I56)+I60 | J61: =SUM(J54:J56)+J60 | K61: =SUM(K54:K56)+K60
E62: ENERGIA - ZNI [resumen]
F63: Generación
F64: Distribución
F65: Comercialización
F66: Subtotal Energia - ZNI | I66: =SUM(I63:I65) | J66: =SUM(J63:J65) | K66: =SUM(K63:K65)
E67: Subtotal Energia Eléctrica | I67: =I66+I61 | J67: =J66+J61 | K67: =K66+K61
D68: Gas combustible por redes [resumen]
E69: Producción, comercialización [resumen]
F70: Contrato de Suministro en Firme
F71: Contrato de Suministro con Firmeza condicionada
F72: Contrato de Suministro en Firme al 95% - CF95
F73: Contrato de Suministro C1
F74: Contrato de Suministro C2
F75: Contrato de Opción de Compra de Gas
F76: Contrato de Suministro de Contingencia
F77: Contrato de Opción de Compra de Gas contra exportaciones
F78: Contrato con Interrupciones
F79: Contrato de condiciones uniformes
F80: Otros
F81: Subtotal Producción, comercialización | I81: =SUM(I70:I80) | J81: =SUM(J70:J80) | K81: =SUM(K70:K80)
E82: Transporte [resumen]
F83: Contrato de Transporte Firme
F84: Contrato de Opción de Compra de Transporte
F85: Contrato de Transporte de Contingencia
F86: Contrato de Transporte con Firmeza Condicionada
F87: Parqueo Rodante
F88: Otros
F89: Subtotal Transporte | I89: =SUM(I83:I88) | J89: =SUM(J83:J88) | K89: =SUM(K83:K88)
E90: Distribución [resumen]
F91: Ingresos por Distribución de Gas Natural
F92: Ingresos por Distribución de GLP por Redes
F93: Ingresos por Distribución de Aire Propanado
F94: Subtotal Distribución | I94: =SUM(I91:I93) | J94: =SUM(J91:J93) | K94: =SUM(K91:K93)
E95: Comercialización [resumen]
F96: Contrato Firme que garantiza Firmeza de Suministro
F97: Contrato Firme que garantiza Firmeza de Transporte
F98: Contrato de Suministro con Firmeza condicionada
F99: Contrato de Opción de Compra de Gas contra exportaciones
F100: Contrato de Opción de Compra de Transporte
F101: Contrato de Suministro de Contingencia
F102: Contrato de Transporte de Contingencia
F103: Contrato con Interrupciones
F104: Otros
...

Sheet Hoja24
B2: Indice
B3: Archivo: | C3: I:\Proyectos2025\proyecto_niif\_backup_legacy\R414\R414Ind_ID20037_2024-12-31.xbrl
B4: Empresa: | C4: 20037
B5: Vista: | C5: [900021] FC03-1 - CXC - Acueducto (Detallado por estrato)
B6: Eje X: | C6: N/A
B7: Eje Y: | C7: N/A
B8: Eje Z: | C8: Periodo Actual
G10: Formato Complementario - Cuentas por cobrar (Acueducto - Detallado por estrato)
G11: Corriente / No corriente [miembro] | J11: Total [miembro]
G12: Corriente [miembro] | H12: No Corriente [miembro] | J12: No vencida [miembro] | K12: Vencida 1 a 30 días [miembro] | L12: Vencida 31 a 60 días [miembro] | M12: Vencida 61 a 90 días [miembro] | N12: Vencida 91 a 120 días [miembro] | O12: Vencida 121 a 150 días [miembro] | P12: Vencida 151 a 180 días [miembro] | Q12: Vencida 181 a 360 días [miembro] | R12: Vencida mayor de 360 días [miembro]
B13: Formato Complementario - Cuentas por cobrar (Acueducto - Detallado por estrato) [partidas]
C14: Detalle Cuentas por cobrar Servicio de Acueducto
D15: Servicio de acueducto [partidas]
E16: Distribución
E17: Otros Servicios
E18: Comercialización [resumen]
F19: Residencial Estrato 1
F20: Residencial Estrato 2
F21: Residencial Estrato 3
F22: Residencial Estrato 4
F23: Residencial Estrato 5
F24: Residencial Estrato 6
F25: No residencial industrial
F26: No residencial comercial
F27: No residencial oficial
F28: No residencial especial
F29: Total Comercialización | G29: =SUM(G19:G28) | H29: =SUM(H19:H28) | I29: =SUM(I19:I28) | J29: =SUM(J19:J28) | K29: =SUM(K19:K28) | L29: =SUM(L19:L28) | M29: =SUM(M19:M28) | N29: =SUM(N19:N28) | ... S29: =SUM(S19:S28)
E30: Cuentas por Cobrar brutas servicio de Acueducto | G30: =G16+G17+G29 | H30: =H16+H17+H29 | I30: =I16+I17+I29 | J30: =J16+J17+J29 | K30: =K16+K17+K29 | L30: =L16+L17+L29 | M30: =M16+M17+M29 | N30: =N16+N17+N29 | ... S30: =S16+S17+S29
C31: Detalle Deterioro cuentas por cobrar Servicio de Acueducto
D32: Deterioro de cuentas por cobrar [partidas]
E33: Distribución
E34: Otros Servicios
E35: Comercialización [resumen]
F36: Residencial Estrato 1
F37: Residencial Estrato 2
F38: Residencial Estrato 3
F39: Residencial Estrato 4
F40: Residencial Estrato 5
F41: Residencial Estrato 6
F42: No Residencial Industrial
F43: No Residencial Comercial
F44: No Residencial Oficial
F45: No Residencial Especial
F46: Total Comercialización | G46: =SUM(G36:G45) | H46: =SUM(H36:H45) | I46: =SUM(I36:I45) | J46: =SUM(J36:J45) | K46: =SUM(K36:K45) | L46: =SUM(L36:L45) | M46: =SUM(M36:M45) | N46: =SUM(N36:N45) | ... S46: =SUM(S36:S45)
E47: Total deterioro cuentas por cobrar Servicio Acueducto | G47: =G33+G34+G46 | H47: =H33+H34+H46 | I47: =I33+I34+I46 | J47: =J33+J34+J46 | K47: =K33+K34+K46 | L47: =L33+L34+L46 | M47: =M33+M34+M46 | N47: =N33+N34+N46 | ... S47: =S33+S34+S46
C48: Cuentas por cobrar netas Servicio Acueducto | G48: =G30-G47 | H48: =H30-H47 | I48: =I30-I47 | J48: =J30-J47 | K48: =K30-K47 | L48: =L30-L47 | M48: =M30-M47 | N48: =N30-N47 | ... S48: =S30-S47

Sheet Hoja25
B2: Indice
B3: Archivo: | C3: I:\Proyectos2025\proyecto_niif\_backup_legacy\R414\R414Ind_ID20037_2024-12-31.xbrl
B4: Empresa: | C4: 20037
B5: Vista: | C5: [900022] FC03-2 - CXC - Alcantarillado (Detallado por estrato)
B6: Eje X: | C6: N/A
B7: Eje Y: | C7: N/A
B8: Eje Z: | C8: Periodo Actual
G10: Formato Complementario - Cuentas por cobrar (Alcantarillado - Detallado por estrato)
G11: Corriente / No corriente [miembro] | J11: Total [miembro]
G12: Corriente [miembro] | H12: No Corriente [miembro] | J12: No vencida [miembro] | K12: Vencida 1 a 30 días [miembro] | L12: Vencida 31 a 60 días [miembro] | M12: Vencida 61 a 90 días [miembro] | N12: Vencida 91 a 120 días [miembro] | O12: Vencida 121 a 150 días [miembro] | P12: Vencida 151 a 180 días [miembro] | Q12: Vencida 181 a 360 días [miembro] | R12: Vencida mayor de 360 días [miembro]
B13: Formato Complementario - Cuentas por cobrar (Alcantarillado - Detallado por estrato) [partidas]
C14: Detalle Cuentas por cobrar Servicio de Alcantarillado
D15: Servicio de alcantarillado [resumen]
E16: Recolección
E17: Tratamiento y disposición final
E18: Comercialización [resumen]
F19: Residencial Estrato 1
F20: Residencial Estrato 2
F21: Residencial Estrato 3
F22: Residencial Estrato 4
F23: Residencial Estrato 5
F24: Residencial Estrato 6
F25: No residencial industrial
F26: No residencial comercial
F27: No residencial oficial
F28: No residencial especial
F29: Total Comercialización | G29: =SUM(G19:G28) | H29: =SUM(H19:H28) | I29: =SUM(I19:I28) | J29: =SUM(J19:J28) | K29: =SUM(K19:K28) | L29: =SUM(L19:L28) | M29: =SUM(M19:M28) | N29: =SUM(N19:N28) | ... S29: =SUM(S19:S28)
E30: Cuentas por Cobrar brutas servicio de Alcantarillado | G30: =G16+G17+G29 | H30: =H16+H17+H29 | I30: =I16+I17+I29 | J30: =J16+J17+J29 | K30: =K16+K17+K29 | L30: =L16+L17+L29 | M30: =M16+M17+M29 | N30: =N16+N17+N29 | ... S30: =S16+S17+S29
C31: Detalle Deterioro cuentas por cobrar Servicio de Alcantarillado
D32: Deterioro de cuentas por cobrar [partidas]
E33: Recolección
E34: Tratamiento y disposición final
E35: Comercialización [resumen]
F36: Residencial Estrato 1
F37: Residencial Estrato 2
F38: Residencial Estrato 3
F39: Residencial Estrato 4
F40: Residencial Estrato 5
F41: Residencial Estrato 6
F42: No Residencial Industrial
F43: No Residencial Comercial
F44: No Residencial Oficial
F45: No Residencial Especial
F46: Total Comercialización | G46: =SUM(G36:G45) | H46: =SUM(H36:H45) | I46: =SUM(I36:I45) | J46: =SUM(J36:J45) | K46: =SUM(K36:K45) | L46: =SUM(L36:L45) | M46: =SUM(M36:M45) | N46: =SUM(N36:N45) | ... S46: =SUM(S36:S45)
E47: Total deterioro cuentas por cobrar Servicio Alcantarillado | G47: =G33+G34+G46 | H47: =H33+H34+H46 | I47: =I33+I34+I46 | J47: =J33+J34+J46 | K47: =K33+K34+K46 | L47: =L33+L34+L46 | M47: =M33+M34+M46 | N47: =N33+N34+N46 | ... S47: =S33+S34+S46
C48: Cuentas por cobrar netas Servicio Alcantarillado | G48: =G30-G47 | H48: =H30-H47 | I48: =I30-I47 | J48: =J30-J47 | K48: =K30-K47 | L48: =L30-L47 | M48: =M30-M47 | N48: =N30-N47 | ... S48: =S30-S47

Sheet Hoja26
B2: Indice
B3: Archivo: | C3: I:\Proyectos2025\proyecto_niif\_backup_legacy\R414\R414Ind_ID20037_2024-12-31.xbrl
B4: Empresa: | C4: 20037
B5: Vista: | C5: [900023] FC03-3 - CXC - Aseo (Detallado por estrato)
B6: Eje X: | C6: N/A
B7: Eje Y: | C7: N/A
B8: Eje Z: | C8: Periodo Actual
E10: Formato Complementario - Cuentas por cobrar (Aseo - Detallado por estrato)
E11: Corriente / No corriente [miembro] | H11: Total [miembro]
E12: Corriente [miembro] | F12: No Corriente [miembro] | H12: No vencida [miembro] | I12: Vencida 1 a 30 días [miembro] | J12: Vencida 31 a 60 días [miembro] | K12: Vencida 61 a 90 días [miembro] | L12: Vencida 91 a 120 días [miembro] | M12: Vencida 121 a 150 días [miembro] | N12: Vencida 151 a 180 días [miembro] | O12: Vencida 181 a 360 días [miembro] | P12: Vencida mayor de 360 días [miembro]
B13: Formato Complementario - Cuentas por cobrar (Aseo - Detallado por estrato) [partidas]
C14: Detalle Cuentas por cobrar Servicio de Aseo
D15: Residencial Estrato 1
D16: Residencial Estrato 2
D17: Residencial Estrato 3
D18: Residencial Estrato 4
D19: Residencial Estrato 5
D20: Residencial Estrato 6
D21: No residencial industrial
D22: No residencial comercial
D23: No residencial oficial
D24: No residencial especial
D25: Cuentas por Cobrar brutas servicio de Aseo | E25: =SUM(E15:E24) | F25: =SUM(F15:F24) | G25: =SUM(G15:G24) | H25: =SUM(H15:H24) | I25: =SUM(I15:I24) | J25: =SUM(J15:J24) | K25: =SUM(K15:K24) | L25: =SUM(L15:L24) | ... Q25: =SUM(Q15:Q24)
C26: Detalle Deterioro cuentas por cobrar Servicio de Aseo
D27: Residencial Estrato 1
D28: Residencial Estrato 2
D29: Residencial Estrato 3
D30: Residencial Estrato 4
D31: Residencial Estrato 5
D32: Residencial Estrato 6
D33: No Residencial Industrial
D34: No Residencial Comercial
D35: No Residencial Oficial
D36: No Residencial Especial
D37: Total deterioro cuentas por cobrar Servicio Aseo | E37: =SUM(E27:E36) | F37: =SUM(F27:F36) | G37: =SUM(G27:G36) | H37: =SUM(H27:H36) | I37: =SUM(I27:I36) | J37: =SUM(J27:J36) | K37: =SUM(K27:K36) | L37: =SUM(L27:L36) | ... Q37: =SUM(Q27:Q36)
C38: Cuentas por cobrar netas Servicio Aseo | E38: =-E37+E25 | F38: =-F37+F25 | G38: =-G37+G25 | H38: =-H37+H25 | I38: =-I37+I25 | J38: =-J37+J25 | K38: =-K37+K25 | L38: =-L37+L25 | ... Q38: =-Q37+Q25

Sheet Hoja27
B2: Indice
B3: Archivo: | C3: I:\Proyectos2025\proyecto_niif\_backup_legacy\R414\R414Ind_ID20037_2024-12-31.xbrl
B4: Empresa: | C4: 20037
B5: Vista: | C5: [900024] FC03-4 - CXC - Energía (Detallado por estrato)
B6: Eje X: | C6: N/A
B7: Eje Y: | C7: N/A
B8: Eje Z: | C8: Periodo Actual
G10: Formato Complementario - Cuentas por cobrar (Energía Eléctrica - Detallado por estrato)
G11: Corriente / No corriente [miembro] | J11: Total [miembro]
G12: Corriente [miembro] | H12: No Corriente [miembro] | J12: No vencida [miembro] | K12: Vencida 1 a 30 días [miembro] | L12: Vencida 31 a 60 días [miembro] | M12: Vencida 61 a 90 días [miembro] | N12: Vencida 91 a 120 días [miembro] | O12: Vencida 121 a 150 días [miembro] | P12: Vencida 151 a 180 días [miembro] | Q12: Vencida 181 a 360 días [miembro] | R12: Vencida mayor de 360 días [miembro]
B13: Formato Complementario - Cuentas por cobrar (Energía Eléctrica - Detallado por estrato) [partidas]
C14: Detalle Cuentas por cobrar Servicio de Energía
D15: Servicio de Energía Eléctrica [resumen]
E16: Generación [resumen]
F17: Contratos bilaterales empresas del sector
F18: Contratos bilaterales usuarios no regulados
F19: Bolsa de energía
F20: Otros
F21: Total Generación | G21: =SUM(G17:G20) | H21: =SUM(H17:H20) | I21: =SUM(I17:I20) | J21: =SUM(J17:J20) | K21: =SUM(K17:K20) | L21: =SUM(L17:L20) | M21: =SUM(M17:M20) | N21: =SUM(N17:N20) | ... S21: =SUM(S17:S20)
E22: Transmisión [resumen]
F23: Ingreso regulado
F24: Cargos por conexión
F25: Otros
F26: Total Transmisión | G26: =SUM(G23:G25) | H26: =SUM(H23:H25) | I26: =SUM(I23:I25) | J26: =SUM(J23:J25) | K26: =SUM(K23:K25) | L26: =SUM(L23:L25) | M26: =SUM(M23:M25) | N26: =SUM(N23:N25) | ... S26: =SUM(S23:S25)
E27: Operador de red [resumen]
F28: Cargos por uso de usuarios regulados
F29: Cargos por uso de usuarios no regulados
F30: Ingreso regulado
F31: Otros
F32: Total Operador de red | G32: =SUM(G28:G31) | H32: =SUM(H28:H31) | I32: =SUM(I28:I31) | J32: =SUM(J28:J31) | K32: =SUM(K28:K31) | L32: =SUM(L28:L31) | M32: =SUM(M28:M31) | N32: =SUM(N28:N31) | ... S32: =SUM(S28:S31)
E33: Comercialización [resumen]
F34: Residencial Estrato 1
F35: Residencial Estrato 2
F36: Residencial Estrato 3
F37: Residencial Estrato 4
F38: Residencial Estrato 5
F39: Residencial Estrato 6
F40: Comercial
F41: Industrial
F42: Oficial
F43: Alumbrado público
F44: Empresas del sector
F45: Usuarios no regulados
F46: Otros
F47: Total Comercialización | G47: =SUM(G34:G46) | H47: =SUM(H34:H46) | I47: =SUM(I34:I46) | J47: =SUM(J34:J46) | K47: =SUM(K34:K46) | L47: =SUM(L34:L46) | M47: =SUM(M34:M46) | N47: =SUM(N34:N46) | ... S47: =SUM(S34:S46)
E48: Total Cuentas por cobrar Servicio de Energía Eléctrica | G48: =G32+G21+G47+G26 | H48: =H32+H21+H47+H26 | I48: =I32+I21+I47+I26 | J48: =J32+J21+J47+J26 | K48: =K32+K21+K47+K26 | L48: =L32+L21+L47+L26 | M48: =M32+M21+M47+M26 | N48: =N32+N21+N47+N26 | ... S48: =S32+S21+S47+S26
C49: Detalle Deterioro cuentas por cobrar Servicio de Energía
D50: Deterioro de cuentas por cobrar [partidas]
E51: Generación [resumen]
F52: Contratos bilaterales empresas del sector
F53: Contratos bilaterales usuarios no regulados
F54: Bolsa de energía
F55: Otros
F56: Total Generación | G56: =SUM(G52:G55) | H56: =SUM(H52:H55) | I56: =SUM(I52:I55) | J56: =SUM(J52:J55) | K56: =SUM(K52:K55) | L56: =SUM(L52:L55) | M56: =SUM(M52:M55) | N56: =SUM(N52:N55) | ... S56: =SUM(S52:S55)
E57: Transmisión [resumen]
F58: Ingreso regulado
F59: Cargos por conexión
F60: Otros
F61: Total Transmisión | G61: =SUM(G58:G60) | H61: =SUM(H58:H60) | I61: =SUM(I58:I60) | J61: =SUM(J58:J60) | K61: =SUM(K58:K60) | L61: =SUM(L58:L60) | M61: =SUM(M58:M60) | N61: =SUM(N58:N60) | ... S61: =SUM(S58:S60)
E62: Operador de red [resumen]
F63: Cargos por uso de usuarios regulados
F64: Cargos por uso de usuarios no regulados
F65: Ingreso regulado
F66: Otros
F67: Total Operador de red | G67: =SUM(G63:G66) | H67: =SUM(H63:H66) | I67: =SUM(I63:I66) | J67: =SUM(J63:J66) | K67: =SUM(K63:K66) | L67: =SUM(L63:L66) | M67: =SUM(M63:M66) | N67: =SUM(N63:N66) | ... S67: =SUM(S63:S66)
E68: Comercialización [resumen]
F69: Residencial Estrato 1
F70: Residencial Estrato 2
F71: Residencial Estrato 3
F72: Residencial Estrato 4
F73: Residencial Estrato 5
F74: Residencial Estrato 6
F75: Comercial
F76: Industrial
F77: Oficial
F78: Alumbrado público
F79: Empresas del sector
F80: Usuarios no regulados
F81: Otros
F82: Total Comercialización | G82: =SUM(G69:G81) | H82: =SUM(H69:H81) | I82: =SUM(I69:I81) | J82: =SUM(J69:J81) | K82: =SUM(K69:K81) | L82: =SUM(L69:L81) | M82: =SUM(M69:M81) | N82: =SUM(N69:N81) | ... S82: =SUM(S69:S81)
E83: Total Deterioro Cuentas por Cobrar Servicio de energía eléctrica | G83: =G82+G61+G67+G56 | H83: =H82+H61+H67+H56 | I83: =I82+I61+I67+I56 | J83: =J82+J61+J67+J56 | K83: =K82+K61+K67+K56 | L83: =L82+L61+L67+L56 | M83: =M82+M61+M67+M56 | N83: =N82+N61+N67+N56 | ... S83: =S82+S61+S67+S56
D84: Cuentas por cobrar netas Servicio Energía | G84: =-G83+G48 | H84: =-H83+H48 | I84: =-I83+I48 | J84: =-J83+J48 | K84: =-K83+K48 | L84: =-L83+L48 | M84: =-M83+M48 | N84: =-N83+N48 | ... S84: =-S83+S48

Sheet Hoja28
B2: Indice
B3: Archivo: | C3: I:\Proyectos2025\proyecto_niif\_backup_legacy\R414\R414Ind_ID20037_2024-12-31.xbrl
B4: Empresa: | C4: 20037
B5: Vista: | C5: [900025] FC03-5 - CXC - Gas combustible por redes (Detallado por estrato)
B6: Eje X: | C6: N/A
B7: Eje Y: | C7: N/A
B8: Eje Z: | C8: Periodo Actual
H10: Formato Complementario - Cuentas por cobrar (Gas combustible por redes - Detallado por estrato)
H11: Corriente / No corriente [miembro] | K11: Total [miembro]
H12: Corriente [miembro] | I12: No Corriente [miembro] | K12: No vencida [miembro] | L12: Vencida 1 a 30 días [miembro] | M12: Vencida 31 a 60 días [miembro] | N12: Vencida 61 a 90 días [miembro] | O12: Vencida 91 a 120 días [miembro] | P12: Vencida 121 a 150 días [miembro] | Q12: Vencida 151 a 180 días [miembro] | R12: Vencida 181 a 360 días [miembro] | S12: Vencida mayor de 360 días [miembro]
B13: Formato Complementario - Cuentas por cobrar Gas combustible por redes - Detallado por estrato [partidas]
C14: Detalle Cuentas por cobrar Servicio de Gas Combustible Por Redes
D15: Servicio de Gas combustible por redes [resumen]
E16: Negocio transporte de gas combustible [resumen]
F17: Empresas del sector
F18: Grandes consumidores
F19: Otros
F20: Total Transporte de gas combustible | H20: =SUM(H17:H19) | I20: =SUM(I17:I19) | J20: =SUM(J17:J19) | K20: =SUM(K17:K19) | L20: =SUM(L17:L19) | M20: =SUM(M17:M19) | N20: =SUM(N17:N19) | O20: =SUM(O17:O19) | ... T20: =SUM(T17:T19)
E21: Negocio distribución de gas combustible [resumen]
F22: Empresas del sector
F23: Grandes consumidores
F24: Otros
F25: Total Distribución de gas combustible | H25: =SUM(H22:H24) | I25: =SUM(I22:I24) | J25: =SUM(J22:J24) | K25: =SUM(K22:K24) | L25: =SUM(L22:L24) | M25: =SUM(M22:M24) | N25: =SUM(N22:N24) | O25: =SUM(O22:O24) | ... T25: =SUM(T22:T24)
E26: Negocio comercializacion de gas combustible [resumen]
F27: Residencial Estrato 1 | H27: =H28+H29 | I27: =I28+I29 | J27: =J28+J29 | K27: =K28+K29 | L27: =L28+L29 | M27: =M28+M29 | N27: =N28+N29 | O27: =O28+O29 | ... T27: =T28+T29
G28: Hogares sustitutos
G29: Otros residencial estrato 1
F30: Residencial Estrato 2
F31: Residencial Estrato 3
F32: Residencial Estrato 4
F33: Residencial Estrato 5
F34: Residencial Estrato 6
F35: Comercial
F36: Industrial
F37: Oficial
F38: Especial Asistencial
F39: Especial Educativo
F40: Grandes consumidores
F41: Empresas del sector
F42: Otros
F43: Total Comercialización de gas combustible | H43: =H27+SUM(H30:H42) | I43: =I27+SUM(I30:I42) | J43: =J27+SUM(J30:J42) | K43: =K27+SUM(K30:K42) | L43: =L27+SUM(L30:L42) | M43: =M27+SUM(M30:M42) | N43: =N27+SUM(N30:N42) | O43: =O27+SUM(O30:O42) | ... T43: =T27+SUM(T30:T42)
E44: Cuentas por Cobrar brutas servicio de Gas Combustible Por Redes | H44: =H43+H20+H25 | I44: =I43+I20+I25 | J44: =J43+J20+J25 | K44: =K43+K20+K25 | L44: =L43+L20+L25 | M44: =M43+M20+M25 | N44: =N43+N20+N25 | O44: =O43+O20+O25 | ... T44: =T43+T20+T25
C45: Detalle Deterioro cuentas por cobrar Servicio de Gas Combustible Por Redes
D46: Deterioro de cuentas por cobrar [resumen]
E47: Negocio transporte de gas combustible [resumen]
F48: Empresas del sector
F49: Grandes consumidores
F50: Otros
F51: Total Transporte de gas combustible | H51: =SUM(H48:H50) | I51: =SUM(I48:I50) | J51: =SUM(J48:J50) | K51: =SUM(K48:K50) | L51: =SUM(L48:L50) | M51: =SUM(M48:M50) | N51: =SUM(N48:N50) | O51: =SUM(O48:O50) | ... T51: =SUM(T48:T50)
E52: Negocio distribución de gas combustible [resumen]
F53: Empresas del sector
F54: Grandes consumidores
F55: Otros
F56: Total Distribución de gas combustible | H56: =SUM(H53:H55) | I56: =SUM(I53:I55) | J56: =SUM(J53:J55) | K56: =SUM(K53:K55) | L56: =SUM(L53:L55) | M56: =SUM(M53:M55) | N56: =SUM(N53:N55) | O56: =SUM(O53:O55) | ... T56: =SUM(T53:T55)
E57: Negocio comercializacion de gas combustible [resumen]
F58: Residencial estrato 1 | H58: =H59+H60 | I58: =I59+I60 | J58: =J59+J60 | K58: =K59+K60 | L58: =L59+L60 | M58: =M59+M60 | N58: =N59+N60 | O58: =O59+O60 | ... T58: =T59+T60
G59: Hogares sustitutos
G60: Otros residencial estrato 1
F61: Residencial Estrato 2
F62: Residencial Estrato 3
F63: Residencial Estrato 4
F64: Residencial Estrato 5
F65: Residencial Estrato 6
F66: Comercial
F67: Industrial
F68: Oficial
F69: Especial Asistencial
F70: Especial Educativo
F71: Grandes consumidores
F72: Empresas del sector
F73: Otros
F74: Total Comercialización de gas combustible | H74: =H58+SUM(H61:H73) | I74: =I58+SUM(I61:I73) | J74: =J58+SUM(J61:J73) | K74: =K58+SUM(K61:K73) | L74: =L58+SUM(L61:L73) | M74: =M58+SUM(M61:M73) | N74: =N58+SUM(N61:N73) | O74: =O58+SUM(O61:O73) | ... T74: =T58+SUM(T61:T73)
E75: Total deterioro cuentas por cobrar Servicio Gas Combustible Por Redes | H75: =H51+H56+H74 | I75: =I51+I56+I74 | J75: =J51+J56+J74 | K75: =K51+K56+K74 | L75: =L51+L56+L74 | M75: =M51+M56+M74 | N75: =N51+N56+N74 | O75: =O51+O56+O74 | ... T75: =T51+T56+T74
C76: Cuentas por cobrar netas Servicio Gas Combustible Por Redes | H76: =-H75+H44 | I76: =-I75+I44 | J76: =-J75+J44 | K76: =-K75+K44 | L76: =-L75+L44 | M76: =-M75+M44 | N76: =-N75+N44 | O76: =-O75+O44 | ... T76: =-T75+T44

Sheet Hoja29
B2: Indice
B3: Archivo: | C3: I:\Proyectos2025\proyecto_niif\_backup_legacy\R414\R414Ind_ID20037_2024-12-31.xbrl
B4: Empresa: | C4: 20037
B5: Vista: | C5: [900026] FC03-6 - CXC - Gas Licuado del Petróleo (Detallado por estrato)
B6: Eje X: | C6: N/A
B7: Eje Y: | C7: N/A
B8: Eje Z: | C8: Periodo Actual
G10: Formato Complementario - Cuentas por cobrar (Gas Licuado del Petróleo - Detallado por estrato)
G11: Corriente / No corriente [miembro] | J11: Total [miembro]
G12: Corriente [miembro] | H12: No Corriente [miembro] | J12: No vencida [miembro] | K12: Vencida 1 a 30 días [miembro] | L12: Vencida 31 a 60 días [miembro] | M12: Vencida 61 a 90 días [miembro] | N12: Vencida 91 a 120 días [miembro] | O12: Vencida 121 a 150 días [miembro] | P12: Vencida 151 a 180 días [miembro] | Q12: Vencida 181 a 360 días [miembro] | R12: Vencida mayor de 360 días [miembro]
B13: Formato Complementario - Cuentas por cobrar (Gas Licuado del Petróleo - Detallado por estrato) [partidas]
C14: Detalle Cuentas por cobrar Servicio de GLP
D15: Servicio de gas licuado del petróleo [resumen]
E16: Negocio transporte de GLP [resumen]
F17: Empresas del sector
F18: Usuarios No Regulados
F19: Otros
F20: Total Transporte de GLP | G20: =SUM(G17:G19) | H20: =SUM(H17:H19) | I20: =SUM(I17:I19) | J20: =SUM(J17:J19) | K20: =SUM(K17:K19) | L20: =SUM(L17:L19) | M20: =SUM(M17:M19) | N20: =SUM(N17:N19) | ... S20: =SUM(S17:S19)
E21: Negocio comercializacion Mayorista de GLP [resumen]
F22: Distribuidores Inversionistas
F23: Comercializadores Mayoristas
F24: Usuarios No Regulados
F25: Otros
F26: Total Comercializacion Mayorista de GLP | G26: =SUM(G22:G25) | H26: =SUM(H22:H25) | I26: =SUM(I22:I25) | J26: =SUM(J22:J25) | K26: =SUM(K22:K25) | L26: =SUM(L22:L25) | M26: =SUM(M22:M25) | N26: =SUM(N22:N25) | ... S26: =SUM(S22:S25)
E27: Negocio distribución de GLP [resumen]
F28: Comercializadores minoristas
F29: Tanques Estacionarios
F30: Puntos de Venta
F31: Estrato 1 Subsidiado
F32: Estrato 2 Subsidiado
F33: Otros
F34: Total distribución de GLP | G34: =SUM(G28:G33) | H34: =SUM(H28:H33) | I34: =SUM(I28:I33) | J34: =SUM(J28:J33) | K34: =SUM(K28:K33) | L34: =SUM(L28:L33) | M34: =SUM(M28:M33) | N34: =SUM(N28:N33) | ... S34: =SUM(S28:S33)
E35: Negocio comercialización Minorista GLP [resumen]
F36: Estrato 1 Subsidiado
F37: Estrato 2 Subsidiado
F38: Usuario Final
F39: Otros
F40: Total comercialización minorista de GLP | G40: =SUM(G36:G39) | H40: =SUM(H36:H39) | I40: =SUM(I36:I39) | J40: =SUM(J36:J39) | K40: =SUM(K36:K39) | L40: =SUM(L36:L39) | M40: =SUM(M36:M39) | N40: =SUM(N36:N39) | ... S40: =SUM(S36:S39)
E41: Cuentas por Cobrar brutas servicio de GLP | G41: =G20+G34+G26+G40 | H41: =H20+H34+H26+H40 | I41: =I20+I34+I26+I40 | J41: =J20+J34+J26+J40 | K41: =K20+K34+K26+K40 | L41: =L20+L34+L26+L40 | M41: =M20+M34+M26+M40 | N41: =N20+N34+N26+N40 | ... S41: =S20+S34+S26+S40
C42: Detalle Deterioro cuentas por cobrar Servicio de GLP
D43: Deterioro de cuentas por cobrar [resumen]
E44: Negocio transporte de GLP [resumen]
F45: Empresas del sector
F46: Usuarios No Regulados
F47: Otros
F48: Total Transporte de GLP | G48: =SUM(G45:G47) | H48: =SUM(H45:H47) | I48: =SUM(I45:I47) | J48: =SUM(J45:J47) | K48: =SUM(K45:K47) | L48: =SUM(L45:L47) | M48: =SUM(M45:M47) | N48: =SUM(N45:N47) | ... S48: =SUM(S45:S47)
E49: Negocio comercializacion Mayorista de GLP [resumen]
F50: Distribuidores Inversionistas
F51: Comercializadores mayoristas
F52: Usuarios No Regulados
F53: Otros
F54: Total Comercializacion Mayorista de GLP | G54: =SUM(G50:G53) | H54: =SUM(H50:H53) | I54: =SUM(I50:I53) | J54: =SUM(J50:J53) | K54: =SUM(K50:K53) | L54: =SUM(L50:L53) | M54: =SUM(M50:M53) | N54: =SUM(N50:N53) | ... S54: =SUM(S50:S53)
E55: Negocio distribución de GLP [resumen]
F56: Comercializadores minoristas
F57: Tanques Estacionarios
F58: Puntos de Venta
F59: Estrato 1 Subsidiado
F60: Estrato 2 Subsidiado
F61: Otros
F62: Total distribución de GLP | G62: =SUM(G56:G61) | H62: =SUM(H56:H61) | I62: =SUM(I56:I61) | J62: =SUM(J56:J61) | K62: =SUM(K56:K61) | L62: =SUM(L56:L61) | M62: =SUM(M56:M61) | N62: =SUM(N56:N61) | ... S62: =SUM(S56:S61)
E63: Negocio comercializacion Minorista GLP [resumen]
F64: Estrato 1 Subsidiado
F65: Estrato 2 Subsidiado
F66: Usuario Final
F67: Otros
F68: Total comercialización minorista de GLP | G68: =SUM(G64:G67) | H68: =SUM(H64:H67) | I68: =SUM(I64:I67) | J68: =SUM(J64:J67) | K68: =SUM(K64:K67) | L68: =SUM(L64:L67) | M68: =SUM(M64:M67) | N68: =SUM(N64:N67) | ... S68: =SUM(S64:S67)
E69: Total deterioro cuentas por cobrar Servicio GLP | G69: =G62+G54+G48+G68 | H69: =H62+H54+H48+H68 | I69: =I62+I54+I48+I68 | J69: =J62+J54+J48+J68 | K69: =K62+K54+K48+K68 | L69: =L62+L54+L48+L68 | M69: =M62+M54+M48+M68 | N69: =N62+N54+N48+N68 | ... S69: =S62+S54+S48+S68
C70: Cuentas por cobrar netas Servicio GLP | G70: =G41-G69 | H70: =H41-H69 | I70: =I41-I69 | J70: =J41-J69 | K70: =K41-K69 | L70: =L41-L69 | M70: =M41-M69 | N70: =N41-N69 | ... S70: =S41-S69

Sheet Hoja30
B2: Indice
B3: Archivo: | C3: I:\Proyectos2025\proyecto_niif\_backup_legacy\R414\R414Ind_ID20037_2024-12-31.xbrl
B4: Empresa: | C4: 20037
B5: Vista: | C5: [900027] FC04 - Información Subsidios y Contribuciones
B6: Eje X: | C6: N/A
B7: Eje Y: | C7: N/A
B8: Eje Z: | C8: Periodo Actual
E10: Total Periodo [miembro]
E11: Acueducto [miembro] | F11: Alcantarillado [miembro] | G11: Aseo [miembro] | H11: Energía Eléctrica [miembro] | I11: Gas combustible por redes [miembro] | J11: Gas Licuado de Petróleo [miembro]
B12: Formato Complementario - Subsidios y Contribuciones [partidas]
C13: Subsidios
D14: Estrato 1
D15: Estrato 2
D16: Estrato 3
D17: Total Subsidios | E17: =SUM(E14:E16) | F17: =SUM(F14:F16) | G17: =SUM(G14:G16) | H17: =SUM(H14:H16) | I17: =SUM(I14:I16) | J17: =SUM(J14:J16) | K17: =SUM(K14:K16)
C18: Contribuciones
D19: Estrato 5
D20: Estrato 6
D21: Comercial
D22: Industrial
D23: Total Contribución | E23: =SUM(E19:E22) | F23: =SUM(F19:F22) | G23: =SUM(G19:G22) | H23: =SUM(H19:H22) | I23: =SUM(I19:I22) | J23: =SUM(J19:J22) | K23: =SUM(K19:K22)
D24: Valor Neto Subsidios vs. Contribuciones | E24: =-E23+E17 | F24: =-F23+F17 | G24: =-G23+G17 | H24: =-H23+H17 | I24: =-I23+I17 | J24: =-J23+J17 | K24: =-K23+K17
C25: Detalle deterioro cartera de municipios
C26: Subsidio FOES
C27: Subsidio FAER
C28: Subsidio FAZNI
C29: Subsidio PRONE
C30: Subsidio Gas combustible por redes
C31: Subsidio GLP

Sheet Hoja31
B2: Indice
B3: Archivo: | C3: I:\Proyectos2025\proyecto_niif\_backup_legacy\R414\R414Ind_ID20037_2024-12-31.xbrl
B4: Empresa: | C4: 20037
B5: Vista: | C5: [900027a] FC04a - Detalle de los subsidios por cobrar
B6: Eje X: | C6: N/A
B7: Eje Y: | C7: N/A
B8: Eje Z: | C8: Periodo Actual
C10: Detalle de los subsidios por cobrar
C11: Periodo | E11: Total Corriente / No corriente | H11: Total Subsidios por cobrar | R11: Fecha de cobro | S11: Justificacion desautorización | T11: Gestiones realizadas para lograr el recaudo
C12: Año | D12: Mes | E12: Corriente | G12: No corriente | H12: Subsidios por cobrar no vencidos | J12: Vencidos hasta 30 Días | K12: Vencidos hasta 60 Días | L12: Vencidos hasta 90 Días | M12: Vencidos hasta 120 Días | N12: Vencidos hasta 150 Días | O12: Vencidos hasta 180 Días | P12: Vencidos hasta 360 Días | Q12: Vencidos mayores a 360 Días
B13: Fila Subsidios
B14: Total Subsidio

Sheet Hoja32
B2: Indice
B3: Archivo: | C3: I:\Proyectos2025\proyecto_niif\_backup_legacy\R414\R414Ind_ID20037_2024-12-31.xbrl
B4: Empresa: | C4: 20037
B5: Vista: | C5: [900028b] FC05b - Clase de pasivo por edades de vencimiento - Revelaciones
B6: Eje X: | C6: N/A
B7: Eje Y: | C7: N/A
B8: Eje Z: | C8: Periodo Actual
D10: Formato Complementario - Detalle de Pasivos [partidas]
D11: Total Corriente / No corriente | G11: Total pasivos por bandas de tiempo | P11: Incluya las revelaciones asociadas a las edades de los pasivos por cada clase
D12: Corriente | F12: No corriente | G12: Pasivos no vencidos | I12: Total pasivos vencidos
I13: Vencidos hasta 30 Días | K13: Vencidos hasta 60 Días | L13: Vencidos hasta 90 Días | M13: Vencidos hasta 180 Días | N13: Vencidos hasta 360 Días | O13: Vencidos mayores a 360 Días
B14: Formato Complementario - Detalle de pasivos [miembro]
C15: Nómina por pagar
C16: Prestaciones sociales por pagar
C17: Cuentas comerciales por pagar por adquisición de bienes y servicios
C18: Impuestos por pagar
C19: Cuentas por pagar a partes relacionadas y asociadas
C20: Obligaciones financieras por pagar
C21: Ingresos recibidos por anticipado e ingresos diferidos
C22: Pasivos por impuestos diferidos
C23: Provisiones
C24: Tasas ambientales y tasas de uso por pagar
C25: Otras tasas y contribuciones por pagar
C26: Pasivos pretoma (Solo intervenidas)
... C30: TOTAL

Sheet Hoja33
B2: Indice
B3: Archivo: | C3: I:\Proyectos2025\proyecto_niif\_backup_legacy\R414\R414Ind_ID20037_2024-12-31.xbrl
B4: Empresa: | C4: 20037
B5: Vista: | C5: [900029] FC06 - Depósitos en Garantía de GLP - Distribuidores Inversionistas
B6: Eje X: | C6: N/A
B7: Eje Y: | C7: N/A
B8: Eje Z: | C8: Periodo Actual
D10: Trimestres [miembro]
D11: Trimestre Enero - Marzo [miembro] | E11: Trimestre Abril - Junio [miembro] | F11: Trimestre Julio - Septiembre [miembro] | G11: Trimestre Octubre - Diciembre [miembro]
B12: Formato Complementario - Depósitos en Garantía de GLP - Distribuidores Inversionistas [partidas]
C13: Valor de la Fiducia
C14: Valor Depósitos en Garantía
C15: PORCENTAJE

Sheet Hoja34
B2: Indice
B3: Archivo: | C3: I:\Proyectos2025\proyecto_niif\_backup_legacy\R414\R414Ind_ID20037_2024-12-31.xbrl
B4: Empresa: | C4: 20037
B5: Vista: | C5: [900030] FC07 - Información sobre el cálculo actuarial
B6: Eje X: | C6: N/A
B7: Eje Y: | C7: N/A
B8: Eje Z: | C8: N/A
E10: Periodo Actual
B11: Formato Complementario 07 – Información sobre el cálculo actuarial
C12: Solicitud cálculo actuarial
D13: Representante legal
D14: NIT
D15: Domicilio
D16: Dirección
D17: Administración regional de impuestos que le corresponde
D18: Grandes contribuyentes (SI o NO)
C19: Nota técnica
D20: Nombre del actuario
D21: Identificacion
D22: Profesion
D23: Matrícula profesional de la persona natural o jurídica que elaboró el cálculo actuarial, matriculado como actuario
D24: Si pertenece a una persona Jurídica indique la Razón Social
D25: Si pertenece a una persona Jurídica indique el NIT
C26: Certificación
D27: Valor del cálculo actuarial
D28: Metodologia
D29: Procedimiento empleado
D30: Incremento del porcentaje acumulado de amortización respecto del año anterior
D31: Incremento del porcentaje anual de amortización respecto del año anterior

Sheet Hoja35
B2: Indice
B3: Archivo: | C3: I:\Proyectos2025\proyecto_niif\_backup_legacy\R414\R414Ind_ID20037_2024-12-31.xbrl
B4: Empresa: | C4: 20037
B5: Vista: | C5: [900031] FC08 - Conciliación de ingresos
B6: Eje X: | C6: N/A
B7: Eje Y: | C7: N/A
B8: Eje Z: | C8: Periodo Actual
G10: Diligenciar en este formulario, en los conceptos que el PSPD considere, los valores que a su criterio conforman los ingresos de actividades ordinarias en desarrollo de su objeto social.
G11: Servicios [miembro]
G12: Acueducto [miembro] | H12: Alcantarillado [miembro] | I12: Aseo [miembro] | J12: Energía Eléctrica [miembro] | K12: Gas combustible por redes [miembro] | L12: Gas Licuado de Petróleo [miembro]
B13: Conciliación de ingresos [partidas]
C14: Ingresos de actividades ordinarias [sinopsis]
D15: Ingresos de actividades ordinarias procedentes de la venta de bienes [resumen]
E16: Ingresos de actividades ordinarias por venta de energía, gas natural, gas licuado de petróleo, agua
E17: Ingresos de actividades ordinarias por venta de aire propanado, combustibles, hidrocarburos, derivados de petróleo
E18: Ingresos de actividades ordinarias por venta de equipos de medición de servicios públicos domiciliarios
E19: Ingresos de actividades ordinarias por venta de redes internas o partes de ellas
E20: Ingresos de actividades ordinarias por venta de electrodomésticos
E21: Ingresos de actividades ordinarias por venta de equipos y materiales
E22: Ingresos de actividades ordinarias por venta de bienes diferentes a los descritos anteriormente
F23: Si reporta ingresos de actividades ordinarias por venta de otros bienes indique cuales [bloque de texto]
E24: Total ingresos de actividades ordinarias por venta de bienes | G24: =SUM(G16:G22) | H24: =SUM(H16:H22) | I24: =SUM(I16:I22) | J24: =SUM(J16:J22) | K24: =SUM(K16:K22) | L24: =SUM(L16:L22)
D25: Ingresos de actividades ordinarias procedentes de la prestación de servicios [resumen]
E26: Ingresos de actividades ordinarias por prestación de servicios públicos domiciliarios
E27: Ingresos de actividades ordinarias por prestación de servicios de instalación de redes internas
E28: Ingresos de actividades ordinarias por prestación de servicios de mantenimiento de redes internas
E29: Ingresos de actividades ordinarias por prestación de servicios de asistencia técnica en servicios públicos domiciliarios
E30: Ingresos de actividades ordinarias por prestación de servicios de obras civiles relacionados con servicios públicos domiciliarios
E31: Ingresos de actividades ordinarias por cargo de conexión
E32: Ingresos de actividades ordinarias por honorarios, asesorías o comisiones por franquicias
E33: Ingresos de actividades ordinarias por cargo de confiabilidad
E34: Ingresos de actividades ordinarias por reconexiones
E35: Ingresos por almacenamiento relacionados con servicios públicos domiciliarios
E36: Ingresos de actividades ordinarias por arrendamientos relacionados con servicios públicos domiciliarios
E37: Ingresos de actividades ordinarias por reinstalaciones
... E41: Ingresos de actividades ordinarias por prestación de servicios diferentes a los descritos anteriormente
F42: Si reporta ingresos de actividades ordinarias por prestación de otros servicios indique cuales [bloque de texto]
E43: Total ingresos de actividades ordinarias por prestación de servicios | G43: =SUM(G26:G41) | H43: =SUM(H26:H41) | I43: =SUM(I26:I41) | J43: =SUM(J26:J41) | K43: =SUM(K26:K41) | L43: =SUM(L26:L41)
D44: Ingresos de actividades ordinarias por intereses [resumen]
E45: Ingresos de actividades ordinarias por intereses de financiación
E46: Ingresos de actividades ordinarias por intereses de mora
E47: Total de ingresos de actividades ordinarias por intereses | G47: =G45+G46 | H47: =H45+H46 | I47: =I45+I46 | J47: =J45+J46 | K47: =K45+K46 | L47: =L45+L46
D48: Ingresos de actividades ordinarias por dividendos
D49: Utilidad de actividades ordinarias en venta de propiedad, planta y equipo (Redes, cables, plantas, y otros directamente relacionados con el servicio público domiciliario)
D50: Ingresos de actividades ordinarias por contratos de operación
D51: Ingresos de actividades ordinarias por contratos de concesión
D52: Ingresos de actividades ordinarias por contratos de cuentas en participación
D53: Ingresos de actividades ordinarias por publicidad
D54: Otros ingresos de actividades ordinarias
E55: Si reporta otros ingresos de actividades ordinarias indique cuáles [bloque de texto]
D56: Total de ingresos de actividades ordinarias | G56: =G24+G43+SUM(G47:G54) | H56: =H24+H43+SUM(H47:H54) | I56: =I24+I43+SUM(I47:I54) | J56: =J24+J43+SUM(J47:J54) | K56: =K24+K43+SUM(K47:K54) | L56: =L24+L43+SUM(L47:L54)
C57: Ingresos que no son considerados de actividades ordinarias [sinopsis]
D58: Ingresos que no son considerados de actividades ordinarias
C59: Total Ingresos | G59: =G58+G56 | H59: =H58+H56 | I59: =I58+I56 | J59: =J58+J56 | K59: =K58+K56 | L59: =L58+L56

Sheet Hoja36
B2: Indice
B3: Archivo: | C3: I:\Proyectos2025\proyecto_niif\_backup_legacy\R414\R414Ind_ID20037_2024-12-31.xbrl
B4: Empresa: | C4: 20037
B5: Vista: | C5: [900032] FC09 - Detalle de costo de ventas
B6: Eje X: | C6: N/A
B7: Eje Y: | C7: N/A
B8: Eje Z: | C8: Periodo Actual
F10: Diligencie en este formulario la composición del Costo de Ventas, solo sì el detalle del gasto operativo del formulario FC01 es diferente del costo de ventas en el estado de resultados.
F11: Servicios [miembro]
F12: Acueducto [miembro] | G12: Alcantarillado [miembro] | H12: Aseo [miembro] | I12: Energía Eléctrica [miembro] | J12: Gas combustible por redes [miembro] | K12: Gas Licuado de Petróleo [miembro]
B13: Conciliación entre gastos por función y por naturaleza [partidas]
C14: Gastos por función [resumen]
D15: Costo de ventas
C16: Gastos [resumen]
D17: Beneficios a empleados
D18: Honorarios
D19: Impuestos, Tasas y Contribuciones (No incluye impuesto de renta)
D20: Generales
D21: Deterioro
D22: Depreciación
D23: Amortización
D24: Provisiones [resumen]
E25: Litigios y demandas
E26: Garantías
E27: Diversas
E28: Total gastos de provisiones | F28: =SUM(F25:F27) | G28: =SUM(G25:G27) | H28: =SUM(H25:H27) | I28: =SUM(I25:I27) | J28: =SUM(J25:J27) | K28: =SUM(K25:K27)
D29: Arrendamientos
D30: Otros Gastos [resumen]
E31: Comisiones
E32: Ajuste por diferencia en cambio
E33: Financieros
E34: Pérdidas por aplicación del método de participación patrimonial
E35: Gastos diversos
E36: Donaciones
E37: Total otros gastos | F37: =SUM(F31:F36) | G37: =SUM(G31:G36) | H37: =SUM(H31:H36) | I37: =SUM(I31:I36) | J37: =SUM(J31:J36) | K37: =SUM(K31:K36)
D38: Impuesto a las ganancias corrientes
D39: Impuesto a las ganancias diferido
D40: Bienes y servicios públicos para la venta [resumen]
E41: Compras en bloque y/o a largo plazo
E42: Compras en bolsa y/o a corto plazo
E43: Gastos por suministro de agua potable (agua en bloque)
E44: Gastos de conexión
E45: Uso de Líneas, redes y ductos
E46: Gastos de distribución y/o comercialización de gas combustible por redes
E47: Manejo comercial y financiero del servicio
E48: Gastos de distribución y/o comercialización de gas licuado de petróleo – GLP
E49: Contrato de explotación
E50: Gastos asociados a las transacciones en el mercado mayorista
E51: Contrato de concesión
E52: Otros gastos bienes y servicios públicos para la venta
E53: Gastos asociados a las transacciones en el mercado minorista
E54: Total de bienes y servicios públicos para la venta | F54: =SUM(F41:F53) | G54: =SUM(G41:G53) | H54: =SUM(H41:H53) | I54: =SUM(I41:I53) | J54: =SUM(J41:J53) | K54: =SUM(K41:K53)
D55: Licencias, contribuciones y regalías [resumen]
E56: Secretaría Distrital del Medio Ambiente
E57: Ley 56 de 1981
E58: Medio Ambiente – Ley 99 de 1993
E59: Regalías
E60: Licencia De Operación Del Servicio
E61: FAZNI
E62: FAER
E63: Cuota de Fomento de gas
E64: Comité De Estratificación –Ley 505 De 1999
E65: Art 25 - Ley 142 - Concesiones, y permisos ambientales y sanitarios
E66: Otras licencias Ley 142 de 1994
E67: Total licencias, contribuciones y regalías | F67: =SUM(F56:F66) | G67: =SUM(G56:G66) | H67: =SUM(H56:H66) | I67: =SUM(I56:I66) | J67: =SUM(J56:J66) | K67: =SUM(K56:K66)
D68: Consumo de Insumos Directos [resumen]
E69: Productos Químicos
E70: Gas Combustible
E71: Carbón Mineral
E72: Energía
E73: ACPM, Fuel Oil
E74: Otros Elementos de Consumo de Insumos Directos
E75: Total consumo de insumos directos | F75: =SUM(F69:F74) | G75: =SUM(G69:G74) | H75: =SUM(H69:H74) | I75: =SUM(I69:I74) | J75: =SUM(J69:J74) | K75: =SUM(K69:K74)
D76: Ordenes y contratos de mantenimiento y reparaciones
D77: Peajes terrestres
D78: Disposición final
D79: Peajes por interconexión de acueductos
D80: Peajes por interconexión de alcantarillado
D81: Servicios públicos
D82: Materiales y otros gastos de operación
D83: Pérdidas en prestación del servicio de acueducto
D84: Seguros
D85: Órdenes y contratos por otros servicios
D86: Total gastos | F86: =SUM(F17:F23)+F28+F29+SUM(F37:F39)+F54+F67+SUM(F75:F85) | G86: =SUM(G17:G23)+G28+G29+SUM(G37:G39)+G54+G67+SUM(G75:G85) | H86: =SUM(H17:H23)+H28+H29+SUM(H37:H39)+H54+H67+SUM(H75:H85) | I86: =SUM(I17:I23)+I28+I29+SUM(I37:I39)+I54+I67+SUM(I75:I85) | J86: =SUM(J17:J23)+J28+J29+SUM(J37:J39)+J54+J67+SUM(J75:J85) | K86: =SUM(K17:K23)+K28+K29+SUM(K37:K39)+K54+K67+SUM(K75:K85)

Sheet Hoja37
B2: Indice
B3: Archivo: | C3: I:\Proyectos2025\proyecto_niif\_backup_legacy\R414\R414Ind_ID20037_2024-12-31.xbrl
B4: Empresa: | C4: 20037
B5: Vista: | C5: [900040] FC15 - Información sobre el cálculo del IUS
B6: Eje X: | C6: N/A
B7: Eje Y: | C7: N/A
B8: Eje Z: | C8: Periodo Actual
E10: La información contenida en el presente formato es en cumplimiento de lo establecido en la Resolución CRA 906 de 2019 para el cálculo del IUS, para los prestadores de acueducto y/o alcantarillado
E11: Servicios [miembro] | H11: Información adicional [miembro]
E12: Acueducto [miembro] | F12: Alcantarillado [miembro] | G12: Total Empresa [miembro]
B13: Información sobre el cálculo del IUS
C14: Caracterización
D15: Clasifique su empresa de acuerdo al segmento establecido en la resolución CRA 906 de 2019
D16: ¿Tiene calificación crediticia con grado de inversión AAA a largo plazo, emitida por una calificadora de riesgo para el periodo de reporte? Seleccione de la lista, Sí o No.
C17: Variables
D18: RI: Recaudo en el periodo de evaluación
D19: If: Ingresos facturados en el periodo de evaluación
D20: CGGS: Costos y gastos totales destinados a la gestión social
D21: ICMI: Ingreso causado por concepto de Costo Medio de Inversión - CMI derivados del POIR para el servicio público
D22: ICMO: Ingreso causado por concepto de Costo Medio de Operación - CMO: por APS, durante el periodo de evaluación, para el servicio público
D23: ICMA: Ingreso causado por concepto de Costo Medio de Administración - CMA: por APS, durante el periodo de evaluación, para el servicio público
D24: TUR_AC: Gasto por concepto de Tasa de uso de agua
D25: TUR_AL: Gasto por concepto de Tasa retributiva
D26: COA: Costos operativos y gastos de administración
D27: SDNC: Servicio de deuda no corriente

Sheet Hoja38
B2: Indice
B3: Archivo: | C3: I:\Proyectos2025\proyecto_niif\_backup_legacy\R414\R414Ind_ID20037_2024-12-31.xbrl
B4: Empresa: | C4: 20037
B5: Vista: | C5: [900080] FC30 - Ingreso por tarifa y comercialización de aprovechamiento
B6: Eje X: | C6: N/A
B7: Eje Y: | C7: N/A
B8: Eje Z: | C8: Periodo Actual
D10: La información contenida en el presente formato debe ser diligenciada de acuerdo a la información reportada mes a mes
D11: Aprovechamiento [miembro]
D12: Ingreso por tarifa [miembro] | E12: Ingreso por comercialización de material [miembro]
B13: Información detallada por tarifa y comercialización de aprovechamiento
C14: Del 1 al 31 de Enero
C15: Del 1 al 28 de Febrero
C16: Del 1 al 31 de Marzo
C17: Del 1 al 30 de Abril
C18: Del 1 al 31 de Mayo
C19: Del 1 al 30 de Junio
C20: Del 1 al 31 de Julio
C21: Del 1 al 31 de Agosto
C22: Del 1 al 30 de Septiembre
C23: Del 1 al 31 de Octubre
C24: Del 1 al 30 de Noviembre
C25: Del 1 al 31 de Diciembre

Sheet Hoja39
B2: Indice
B3: Archivo: | C3: I:\Proyectos2025\proyecto_niif\_backup_legacy\R414\R414Ind_ID20037_2024-12-31.xbrl
B4: Empresa: | C4: 20037
B5: Vista: | C5: [900090] FC40 - Pagos tarifa de aprovechamiento a recicladores
B6: Eje X: | C6: N/A
B7: Eje Y: | C7: N/A
B8: Eje Z: | C8: Periodo Actual
D10: La información contenida en el presente formato debe ser diligenciada de acuerdo a la información reportada mes a mes
D11: Aprovechamiento [miembro]
D12: Pago mensual a recicladores [miembro]
B13: Información detallada de pagos a recicladores por tarifa de aprovechamiento
C14: Del 1 al 31 de Enero
C15: Del 1 al 28 de Febrero
C16: Del 1 al 31 de Marzo
C17: Del 1 al 30 de Abril
C18: Del 1 al 31 de Mayo
C19: Del 1 al 30 de Junio
C20: Del 1 al 31 de Julio
C21: Del 1 al 31 de Agosto
C22: Del 1 al 30 de Septiembre
C23: Del 1 al 31 de Octubre
C24: Del 1 al 30 de Noviembre
C25: Del 1 al 31 de Diciembre

Sheet Hoja40
B2: Indice
B3: Archivo: | C3: I:\Proyectos2025\proyecto_niif\_backup_legacy\R414\R414Ind_ID20037_2024-12-31.xbrl
B4: Empresa: | C4: 20037
B5: Vista: | C5: [900100] FC50 - Detalle de ventas a comercializadores de materiales aprovechables
B6: Eje X: | C6: N/A
B7: Eje Y: | C7: N/A
B8: Eje Z: | C8: Periodo Actual
C10: Detalle de ventas a comercializadores de materiales de aprovechamiento [Resumen]
C11: Tipo de identificación del comercializador | D11: Nit del comercializador | E11: Nombre o Razón social del comercializador | F11: Del 1 al 31 de Enero | G11: Del 1 al 28 de Febrero | H11: Del 1 al 31 de Marzo | I11: Del 1 al 30 de Abril | J11: Del 1 al 31 de Mayo | K11: Del 1 al 30 de Junio | L11: Del 1 al 31 de Julio | M11: Del 1 al 31 de Agosto | N11: Del 1 al 30 de Septiembre | O11: Del 1 al 31 de Octubre | P11: Del 1 al 30 de Noviembre | Q11: Del 1 al 31 de Diciembre
B12: # Fila comercializador de materiales

Sheet Hoja41
B2: Indice
B3: Archivo: | C3: I:\Proyectos2025\proyecto_niif\_backup_legacy\R414\R414Ind_ID20037_2024-12-31.xbrl
B4: Empresa: | C4: 20037
B5: Vista: | C5: [900110] FC60 - Porcentaje de provisión de la tarifa de aprovechamiento
B6: Eje X: | C6: N/A
B7: Eje Y: | C7: N/A
B8: Eje Z: | C8: Periodo Actual
D10: Información detallada del porcentaje de provisión por tarifa de aprovechamiento
D11: Año | E11: Porcentaje de provisión que aplicó con respecto al valor de la tarifa de aprovechamiento (%) | F11: Valor en pesos de la provisión que aplicó
B12: Fase de progresividad:
C13: Fase de progresividad cinco: 5
C14: Fase de progresividad seis: 6
C15: Fase de progresividad siete: 7
C16: Fase de progresividad ocho: 8
